Workbook
Name Fund: #REF!
Name Scenario: #REF!

Sheet Table of Contents
A1: Workbook Table of Contents
A2: Overview of Monte Carlo Simulation Results & Task 1 (Red)
A3: Dashboard
A4: Decision Tree
A5: Task 2 (Purple)
A6: model
A7: living expenditure actually
A8: health expenditure
A9: Transport expenditure
A10: Task 3 (No Colour)
A11: Economic Scenarios
A12: fundGrowth
... A22: t4_salaryGrowthevent

Sheet Dashboard
A1: Simulations | B1: Income Y37 | C1: Expense | D1: Balance | E1: Recession | F1: Normal | G1: Boom | H1: Promotion≤45 | I1: Promotion46–59 | J1: Layoff≤45 | K1: Layoff46–59 | L1: Layoff≥60 | M1: EarlyRetire≥60 | P1: Customize Rate You can change the numbers below
A2: {=_xlfn.SEQUENCE(5000,1,1,1)} -> 1 | B2: 871310.39 | C2: 883717.72 | D2: =B2-C2 -> -12407.329 | E2: 10 | F2: 22 | G2: 3 | H2: 1 | I2: 1 | J2: 0 | K2: 1 | L2: 0 | M2: 1 | P2: Select KiwiSaver Contribution Rate | Q2: 0.1
A3: 2 | B3: 844899.45 | C3: 470982.66 | D3: =B3-C3 -> 373916.79 | E3: 24 | F3: 9 | G3: 2 | H3: 2 | I3: 0 | J3: 0 | K3: 1 | L3: 1 | M3: 1 | P3: Recession (Conservative) | R3: ='t4_Income from 30-64'!T37 -> 930999.09 | S3: Use default weights
A4: 3 | B4: 943200.01 | C4: 1101862.7 | D4: =B4-C4 -> -158662.71 | E4: 23 | F4: 10 | G4: 2 | H4: 0 | I4: 1 | J4: 1 | K4: 0 | L4: 0 | M4: 0 | P4: Input HarbourSafe Rate | Q4: 1 | R4: ='t4_Income from 30-64'!T37 -> 930999.09 | S4: Use optimized weights
A5: 4 | B5: 991101.68 | C5: 901618.92 | D5: =B5-C5 -> 89482.757 | E5: 11 | F5: 18 | G5: 6 | H5: 0 | I5: 1 | J5: 0 | K5: 1 | L5: 0 | M5: 0 | P5: Input Horizon Rate | Q5: 0
A6: 5 | B6: 903866.96 | C6: 795928.04 | D6: =B6-C6 -> 107938.92 | E6: 10 | F6: 20 | G6: 5 | H6: 1 | I6: 0 | J6: 2 | K6: 0 | L6: 0 | M6: 0 | P6: Input SkyHigh Rate | Q6: 0
A7: 6 | B7: 911373.83 | C7: 1127233.8 | D7: =B7-C7 -> -215859.93 | E7: 17 | F7: 15 | G7: 3 | H7: 1 | I7: 0 | J7: 0 | K7: 1 | L7: 0 | M7: 0 | P7: Normal (Balanced)
A8: 7 | B8: 919447.02 | C8: 594222.47 | D8: =B8-C8 -> 325224.55 | E8: 19 | F8: 11 | G8: 5 | H8: 0 | I8: 1 | J8: 0 | K8: 0 | L8: 0 | M8: 0 | P8: Input HarbourSafe Rate | Q8: 0
A9: 8 | B9: 1109723.1 | C9: 1047744.4 | D9: =B9-C9 -> 61978.674 | E9: 12 | F9: 17 | G9: 6 | H9: 0 | I9: 0 | J9: 0 | K9: 0 | L9: 0 | M9: 1 | P9: Input Horizon Rate | Q9: 0.5
A10: 9 | B10: 896328.68 | C10: 879059.66 | D10: =B10-C10 -> 17269.021 | E10: 17 | F10: 12 | G10: 6 | H10: 0 | I10: 0 | J10: 1 | K10: 1 | L10: 0 | M10: 0 | P10: Input SkyHigh Rate | Q10: 0.5
A11: 10 | B11: 951587.3 | C11: 981796.92 | D11: =B11-C11 -> -30209.623 | E11: 14 | F11: 15 | G11: 6 | H11: 1 | I11: 0 | J11: 0 | K11: 1 | L11: 0 | M11: 0 | P11: Boom (Growth)
A12: 11 | B12: 961008.39 | C12: 635148.57 | D12: =B12-C12 -> 325859.82 | E12: 7 | F12: 22 | G12: 6 | H12: 2 | I12: 0 | J12: 0 | K12: 0 | L12: 0 | M12: 0 | P12: Input HarbourSafe Rate | Q12: 0
A13: 12 | B13: 949477.55 | C13: 535794.3 | D13: =B13-C13 -> 413683.25 | E13: 20 | F13: 10 | G13: 5 | H13: 2 | I13: 0 | J13: 1 | K13: 0 | L13: 0 | M13: 1 | P13: Input Horizon Rate | Q13: 0
A14: 13 | B14: 997748.17 | C14: 1317405.9 | D14: =B14-C14 -> -319657.74 | E14: 11 | F14: 19 | G14: 5 | H14: 1 | I14: 0 | J14: 0 | K14: 1 | L14: 0 | M14: 0 | P14: Input SkyHigh Rate | Q14: 1
A15: 14 | B15: 1037184.6 | C15: 1400100.3 | D15: =B15-C15 -> -362915.72 | E15: 12 | F15: 18 | G15: 5 | H15: 1 | I15: 0 | J15: 1 | K15: 0 | L15: 0 | M15: 1
A16: 15 | B16: 920490.64 | C16: 732627.66 | D16: =B16-C16 -> 187862.98 | E16: 11 | F16: 19 | G16: 5 | H16: 1 | I16: 0 | J16: 0 | K16: 0 | L16: 0 | M16: 0
A17: 16 | B17: 931045.67 | C17: 889977.42 | D17: =B17-C17 -> 41068.248 | E17: 18 | F17: 13 | G17: 4 | H17: 1 | I17: 0 | J17: 0 | K17: 0 | L17: 0 | M17: 1
A18: 17 | B18: 888446.38 | C18: 553338.33 | D18: =B18-C18 -> 335108.05 | E18: 19 | F18: 12 | G18: 4 | H18: 1 | I18: 0 | J18: 2 | K18: 0 | L18: 0 | M18: 0
A19: 18 | B19: 934750.27 | C19: 809477.45 | D19: =B19-C19 -> 125272.82 | E19: 11 | F19: 21 | G19: 3 | H19: 0 | I19: 0 | J19: 0 | K19: 1 | L19: 0 | M19: 0
A20: 19 | B20: 904397.09 | C20: 673648.07 | D20: =B20-C20 -> 230749.02 | E20: 14 | F20: 16 | G20: 5 | H20: 0 | I20: 0 | J20: 1 | K20: 0 | L20: 0 | M20: 0
A21: 20 | B21: 908722.92 | C21: 1033424.8 | D21: =B21-C21 -> -124701.91 | E21: 19 | F21: 11 | G21: 5 | H21: 0 | I21: 0 | J21: 0 | K21: 1 | L21: 0 | M21: 0
A22: 21 | B22: 871657.11 | C22: 1140586.7 | D22: =B22-C22 -> -268929.59 | E22: 20 | F22: 7 | G22: 8 | H22: 2 | I22: 0 | J22: 2 | K22: 0 | L22: 0 | M22: 0
A23: 22 | B23: 938866.03 | C23: 758733.31 | D23: =B23-C23 -> 180132.71 | E23: 5 | F23: 27 | G23: 3 | H23: 0 | I23: 0 | J23: 1 | K23: 1 | L23: 0 | M23: 1
A24: 23 | B24: 915127.3 | C24: 1031302.5 | D24: =B24-C24 -> -116175.24 | E24: 11 | F24: 20 | G24: 4 | H24: 2 | I24: 0 | J24: 2 | K24: 0 | L24: 0 | M24: 0
A25: 24 | B25: 826181.84 | C25: 691780.89 | D25: =B25-C25 -> 134400.95 | E25: 13 | F25: 18 | G25: 4 | H25: 1 | I25: 0 | J25: 2 | K25: 0 | L25: 0 | M25: 1 | P25: Metric | Q25: Investment (B) | R25: Expenditure (C) | S25: Difference(D)
A26: 25 | B26: 858755.86 | C26: 1023123 | D26: =B26-C26 -> -164367.19 | E26: 24 | F26: 7 | G26: 4 | H26: 2 | I26: 0 | J26: 0 | K26: 2 | L26: 0 | M26: 1 | P26: Average | Q26: =AVERAGE(B2:B5001) -> 937991.04 | R26: =AVERAGE(C2:C5001) -> 948313.05 | S26: =AVERAGE(D2:D5001) -> -10322.013
A27: 26 | B27: 950510.27 | C27: 585698.78 | D27: =B27-C27 -> 364811.49 | E27: 7 | F27: 22 | G27: 6 | H27: 0 | I27: 1 | J27: 0 | K27: 0 | L27: 0 | M27: 0 | P27: Standard Deviation | Q27: =_xlfn.STDEV.P(B2:B5001) -> 64337.558 | R27: =_xlfn.STDEV.P(C2:C5001) -> 440668.1
A28: 27 | B28: 970195.86 | C28: 758460.54 | D28: =B28-C28 -> 211735.32 | E28: 8 | F28: 24 | G28: 3 | H28: 0 | I28: 1 | J28: 2 | K28: 0 | L28: 0 | M28: 1 | P28: Min | Q28: =MIN(B2:B5001) -> 753018.22 | R28: =MIN(C2:C5001) -> 265772.44
A29: 28 | B29: 908304.95 | C29: 933922.83 | D29: =B29-C29 -> -25617.884 | E29: 18 | F29: 9 | G29: 8 | H29: 1 | I29: 1 | J29: 2 | K29: 0 | L29: 0 | M29: 1 | P29: Max | Q29: =MAX(B2:B5001) -> 1210886.5 | R29: =MAX(C2:C5001) -> 14697149
A30: 29 | B30: 890267.28 | C30: 910425.44 | D30: =B30-C30 -> -20158.158 | E30: 18 | F30: 13 | G30: 4 | H30: 1 | I30: 0 | J30: 2 | K30: 0 | L30: 0 | M30: 0 | P30: 95% CI Lower | Q30: =AVERAGE(B2:B5001)-1.96*_xlfn.STDEV.P(B2:B5001)/SQRT(5000) -> 936207.69 | R30: =AVERAGE(C2:C5001)-1.96*_xlfn.STDEV.P(C2:C5001)/SQRT(1000) -> 921000.16
A31: 30 | B31: 910429.34 | C31: 1148279.4 | D31: =B31-C31 -> -237850.05 | E31: 13 | F31: 16 | G31: 6 | H31: 2 | I31: 0 | J31: 2 | K31: 0 | L31: 0 | M31: 1 | P31: 95% CI Upper | Q31: =AVERAGE(B2:B5001)+1.96*_xlfn.STDEV.P(B2:B5001)/SQRT(1000) -> 941978.72 | R31: =AVERAGE(C2:C5001)+1.96*_xlfn.STDEV.P(C2:C5001)/SQRT(1000) -> 975625.94
A32: 31 | B32: 917258.6 | C32: 896256.77 | D32: =B32-C32 -> 21001.823 | E32: 18 | F32: 14 | G32: 3 | H32: 0 | I32: 0 | J32: 0 | K32: 1 | L32: 0 | M32: 0 | P32: 2.5% Percentile | Q32: =_xlfn.PERCENTILE.INC(B2:B5001, 0.025) -> 826531.05 | R32: =_xlfn.PERCENTILE.INC(C2:C5001, 0.025) -> 484385.41
A33: 32 | B33: 831727.25 | C33: 1502660.3 | D33: =B33-C33 -> -670933.1 | E33: 15 | F33: 15 | G33: 5 | H33: 0 | I33: 2 | J33: 1 | K33: 1 | L33: 0 | M33: 0 | P33: 97.5% Percentile | Q33: =_xlfn.PERCENTILE.INC(B2:B5001, 0.975) -> 1078537.9 | R33: =_xlfn.PERCENTILE.INC(C2:C5001, 0.975) -> 1880500.9
A34: 33 | B34: 970590.67 | C34: 1032646.9 | D34: =B34-C34 -> -62056.191 | E34: 17 | F34: 12 | G34: 6 | H34: 1 | I34: 1 | J34: 1 | K34: 0 | L34: 0 | M34: 1
A35: 34 | B35: 908267.14 | C35: 974145.11 | D35: =B35-C35 -> -65877.967 | E35: 10 | F35: 19 | G35: 6 | H35: 1 | I35: 0 | J35: 1 | K35: 1 | L35: 0 | M35: 0 | P35: Negative Count (D < 0) | Q35: =COUNTIF(D2:D5001, "<0") -> 1980
A36: 35 | B36: 970295.33 | C36: 596846.43 | D36: =B36-C36 -> 373448.9 | E36: 8 | F36: 18 | G36: 9 | H36: 2 | I36: 0 | J36: 1 | K36: 1 | L36: 0 | M36: 0
A37: 36 | B37: 881242.46 | C37: 924970.48 | D37: =B37-C37 -> -43728.014 | E37: 10 | F37: 22 | G37: 3 | H37: 1 | I37: 1 | J37: 0 | K37: 0 | L37: 0 | M37: 0
A38: 37 | B38: 876691.75 | C38: 1289855.9 | D38: =B38-C38 -> -413164.18 | E38: 22 | F38: 10 | G38: 3 | H38: 2 | I38: 0 | J38: 1 | K38: 1 | L38: 0 | M38: 0
A39: 38 | B39: 896513.82 | C39: 708543.24 | D39: =B39-C39 -> 187970.58 | E39: 17 | F39: 16 | G39: 2 | H39: 0 | I39: 0 | J39: 2 | K39: 0 | L39: 0 | M39: 0 | P39: Event Type | Q39: Total Count
A40: 39 | B40: 902309.07 | C40: 893635.08 | D40: =B40-C40 -> 8673.9933 | E40: 16 | F40: 15 | G40: 4 | H40: 1 | I40: 0 | J40: 0 | K40: 2 | L40: 0 | M40: 0 | P40: Event Type | Q40: Total Count | R40: ≤45 years | S40: 46–59 years | T40: ≥60 years
A41: 40 | B41: 802350.45 | C41: 1229398.9 | D41: =B41-C41 -> -427048.46 | E41: 9 | F41: 20 | G41: 6 | H41: 1 | I41: 0 | J41: 0 | K41: 1 | L41: 1 | M41: 0 | P41: Promotion | Q41: 1084 | R41: 875 | S41: 209 | T41: 0
A42: 41 | B42: 836560.58 | C42: 777287.62 | D42: =B42-C42 -> 59272.954 | E42: 16 | F42: 14 | G42: 5 | H42: 2 | I42: 0 | J42: 0 | K42: 0 | L42: 0 | M42: 0 | P42: Job Change | Q42: 1257 | R42: 851 | S42: 388 | T42: 18
A43: 42 | B43: 1030429.9 | C43: 620665.62 | D43: =B43-C43 -> 409764.33 | E43: 5 | F43: 22 | G43: 8 | H43: 0 | I43: 0 | J43: 2 | K43: 0 | L43: 0 | M43: 1 | P43: Layoff | Q43: 967 | R43: 440 | S43: 459 | T43: 68
A44: 43 | B44: 941204.06 | C44: 1145494.5 | D44: =B44-C44 -> -204290.43 | E44: 16 | F44: 17 | G44: 2 | H44: 0 | I44: 0 | J44: 0 | K44: 1 | L44: 0 | M44: 0 | P44: Pay Cut | Q44: 792 | R44: 324 | S44: 350 | T44: 118
A45: 44 | B45: 924878.26 | C45: 1523640.3 | D45: =B45-C45 -> -598762.04 | E45: 11 | F45: 19 | G45: 5 | H45: 1 | I45: 1 | J45: 1 | K45: 0 | L45: 1 | M45: 0 | P45: Career Shift | Q45: 480 | R45: 165 | S45: 269 | T45: 46
A46: 45 | B46: 926563.39 | C46: 620330.03 | D46: =B46-C46 -> 306233.36 | E46: 17 | F46: 16 | G46: 2 | H46: 0 | I46: 0 | J46: 1 | K46: 1 | L46: 0 | M46: 0 | P46: Parental Leave | Q46: 508 | R46: 508 | S46: 0 | T46: 0
A47: 46 | B47: 803194.2 | C47: 979790.88 | D47: =B47-C47 -> -176596.68 | E47: 9 | F47: 21 | G47: 5 | H47: 0 | I47: 1 | J47: 0 | K47: 2 | L47: 0 | M47: 0 | P47: Early Retirement | Q47: 252 | R47: 0 | S47: 0 | T47: 252
A48: 47 | B48: 992336.96 | C48: 975150.28 | D48: =B48-C48 -> 17186.68 | E48: 8 | F48: 22 | G48: 5 | H48: 1 | I48: 1 | J48: 0 | K48: 0 | L48: 1 | M48: 0
A49: 48 | B49: 904915.94 | C49: 915719.77 | D49: =B49-C49 -> -10803.825 | E49: 16 | F49: 13 | G49: 6 | H49: 1 | I49: 0 | J49: 0 | K49: 2 | L49: 0 | M49: 1
A50: 49 | B50: 914536.75 | C50: 1140578 | D50: =B50-C50 -> -226041.22 | E50: 10 | F50: 20 | G50: 5 | H50: 0 | I50: 0 | J50: 0 | K50: 0 | L50: 0 | M50: 0
A51: 50 | B51: 986616.57 | C51: 552836.19 | D51: =B51-C51 -> 433780.38 | E51: 15 | F51: 18 | G51: 2 | H51: 0 | I51: 0 | J51: 0 | K51: 0 | L51: 0 | M51: 0
A52: 51 | B52: 898661.68 | C52: 1690883.8 | D52: =B52-C52 -> -792222.09 | E52: 7 | F52: 24 | G52: 4 | H52: 0 | I52: 0 | J52: 1 | K52: 1 | L52: 0 | M52: 0
A53: 52 | B53: 944664.2 | C53: 595066.53 | D53: =B53-C53 -> 349597.67 | E53: 12 | F53: 19 | G53: 4 | H53: 0 | I53: 0 | J53: 0 | K53: 0 | L53: 0 | M53: 0
A54: 53 | B54: 953541.87 | C54: 581829.82 | D54: =B54-C54 -> 371712.05 | E54: 7 | F54: 21 | G54: 7 | H54: 0 | I54: 0 | J54: 2 | K54: 0 | L54: 0 | M54: 0
A55: 54 | B55: 861165.29 | C55: 908886.23 | D55: =B55-C55 -> -47720.938 | E55: 15 | F55: 15 | G55: 5 | H55: 2 | I55: 0 | J55: 1 | K55: 1 | L55: 0 | M55: 0
A56: 55 | B56: 1016587.9 | C56: 615891.95 | D56: =B56-C56 -> 400695.95 | E56: 13 | F56: 16 | G56: 6 | H56: 2 | I56: 0 | J56: 1 | K56: 0 | L56: 0 | M56: 0
A57: 56 | B57: 975558.73 | C57: 626606.75 | D57: =B57-C57 -> 348951.98 | E57: 17 | F57: 12 | G57: 6 | H57: 0 | I57: 0 | J57: 0 | K57: 1 | L57: 0 | M57: 1
A58: 57 | B58: 798928.14 | C58: 455557.4 | D58: =B58-C58 -> 343370.74 | E58: 24 | F58: 7 | G58: 4 | H58: 0 | I58: 1 | J58: 0 | K58: 0 | L58: 0 | M58: 1
A59: 58 | B59: 974755.9 | C59: 990292.39 | D59: =B59-C59 -> -15536.486 | E59: 15 | F59: 14 | G59: 6 | H59: 1 | I59: 0 | J59: 1 | K59: 0 | L59: 0 | M59: 0
... A5001: 5000 | B5001: 911836.19 | C5001: 753688.79 | D5001: =B5001-C5001 -> 158147.41 | E5001: 9 | F5001: 20 | G5001: 6 | H5001: 2 | I5001: 0 | J5001: 0 | K5001: 2 | L5001: 0 | M5001: 0

Sheet Decision Tree
A1: Node 1 | B1: Node 2 | C1: Node 3 | D1: Node 4 | E1: Node 5 | F1: Difference | G1: PathProbability | H1: ExpectedValue | I1: BestPath
A2: Recession | B2: Conservative | C2: Early Retirement: Yes | D2: Promotion: Yes | E2: Layoff: Yes | F2: 190263 | G2: 0.05126 | H2: 9752.8814 | I2: FALSE
A3: Recession | B3: Conservative | C3: Early Retirement: Yes | D3: Promotion: Yes | E3: Layoff: No | F3: 205972 | G3: 0.015711 | H3: 3236.0261 | I3: FALSE
A4: Recession | B4: Conservative | C4: Early Retirement: Yes | D4: Promotion: No | E4: Layoff: Yes | F4: 206847 | G4: 0.021162 | H4: 4377.2962 | I4: FALSE
A5: Recession | B5: Conservative | C5: Early Retirement: Yes | D5: Promotion: No | E5: Layoff: No | F5: 207132 | G5: 0.006486 | H5: 1343.4582 | I5: FALSE
A6: Recession | B6: Conservative | C6: Early Retirement: No | D6: Promotion: Yes | E6: Layoff: Yes | F6: 197159 | G6: 0.12936 | H6: 25504.488 | I6: TRUE
A7: Recession | B7: Conservative | C7: Early Retirement: No | D7: Promotion: Yes | E7: Layoff: No | F7: 177288 | G7: 0.03965 | H7: 7029.4692 | I7: FALSE
A8: Recession | B8: Conservative | C8: Early Retirement: No | D8: Promotion: No | E8: Layoff: Yes | F8: 208423 | G8: 0.053403 | H8: 11130.413 | I8: FALSE
A9: Recession | B9: Conservative | C9: Early Retirement: No | D9: Promotion: No | E9: Layoff: No | F9: 199340 | G9: 0.016368 | H9: 3262.7971 | I9: FALSE
A10: Recession | B10: Balanced | C10: Early Retirement: Yes | D10: Promotion: Yes | E10: Layoff: Yes | F10: 161047 | G10: 0.05126 | H10: 8255.2692 | I10: FALSE
A11: Recession | B11: Balanced | C11: Early Retirement: Yes | D11: Promotion: Yes | E11: Layoff: No | F11: 186605 | G11: 0.015711 | H11: 2931.7512 | I11: FALSE
A12: Recession | B12: Balanced | C12: Early Retirement: Yes | D12: Promotion: No | E12: Layoff: Yes | F12: 190244 | G12: 0.021162 | H12: 4025.9435 | I12: FALSE
A13: Recession | B13: Balanced | C13: Early Retirement: Yes | D13: Promotion: No | E13: Layoff: No | F13: 175228 | G13: 0.006486 | H13: 1136.5288 | I13: FALSE
... A73: Boom | B73: Growth | C73: Early Retirement: No | D73: Promotion: No | E73: Layoff: No | F73: 363822 | G73: 0.016359 | H73: 5951.7641 | I73: FALSE

Sheet t4_Income from 30-64
A1: Age | B1: Salary growth rate | C1: Payroll net income before tax | D1: Payroll net income after tax | E1: KiwiSaver gross contributions (6%) | F1: Employer superannuation contribution tax (ESCT) | G1: KiwiSaver net contributions (6%)+Subsidy | H1: Economic Scenarios | I1: HarbourSafe return rate | J1: Horizon return rate | K1: SkyHigh return rate | L1: Total funds investment return rate (current weights) | M1: Net returns of Emily's KiwiSaver Investment (deduct 28% PIR) | N1: Real value of Emily;s KiwiSaver inverstment net return (per year) | O1: Total Income (funds+salary) | P1: Inflation | Q1: Deflation factor (per year) | S1: KiwiSaver net returns(deduct 28% PIR, customized contributions and fund weights) | T1: Real value of KiwiSaver returns(consider inflation and customized contributions and fund weights) | X1: KiwiSaver net returns(deduct 28% PIR, customized contributions and fund weights) | Y1: Real value of KiwiSaver returns(consider inflation and customized contributions and fund weights) | Z1: Salary growth rate (use for simulations)
A2: {=_xlfn.SEQUENCE(35,1,30,1)} -> 30 | B2: 0.035 | C2: =VLOOKUP(t4_salaryGrowthevent!B2,t4_salaryGrowthevent!B:B,1,FALSE) -> 70000 | D2: {=_xlfn.LET( _xlpm.taxable, C2, _xlpm.kiwisaver,C2*0.03, _xlpm.incomeTax, _xlfn.IFS( _xlpm.taxable <= 15600, _xlpm.taxable * 10.5%, AND(_xlpm.taxable > 15600, _xlpm.taxable <= 53500), (_xlpm.taxable - 15600) * 17.5% + 15600 * 10.5%, AND(_xlpm.taxable > 53500, _xlpm.taxable <= 78100), (_xlpm.taxable - 53500) * 30% + (53500 - 15600) * 17.5% + 15600 * 10.5%, AND(_xlpm.taxable > 78100, _xlpm.taxable <= 180000), (_xlpm.taxable - 78100) * 33% + (78100 - 53500) * 30% + (53500 - 15600) * 17.5% + 15600 * 10.5%, _xlpm.taxable > 180000, (_xlpm.taxable - 180000) * 39% + (180000 - 78100) * 33% + (78100 - 53500) * 30% + (53500 - 15600) * 17.5% + 15600 * 10.5% ), _xlpm.acc, C2 * 0.0167, _xlpm.taxable - _xlpm.incomeTax - _xlpm.acc - _xlpm.kiwisaver )} -> 53510.5 | E2: =6%*C2 -> 4200 | F2: {=C2 * 3% * _xlfn.IFS( C2 + C2 * 3% <= 18720, 10.5%, C2 + C2 * 3% <= 64200, 17.5%, C2 + C2 * 3% <= 93720, 30%, C2 + C2 * 3% <= 216000, 33%, C2 + C2 * 3% > 216000, 39% )} -> 630 | G2: =E2-F2+521.43 -> 4091.43 | H2: Normal | I2: {=_xlfn.LET( _xlpm.ε, (_xlfn.BETA.INV(RAND(), 5, 5) - 0.5) * 2, _xlpm.Scenario,H2, _xlpm.μ, _xlfn.XLOOKUP("HarbourSafe", fundGrowth!$A$2:$A$4, INDEX(fundGrowth!$B$2:$J$4,0, MATCH(_xlpm.Scenario & " μ", fundGrowth!$B$1:$J$1, 0))), _xlpm.σ, _xlfn.XLOOKUP("HarbourSafe", fundGrowth!$A$2:$A$4, INDEX(fundGrowth!$B$2:$J$4,0, MATCH(_xlpm.Scenario & " σ", fundGrowth!$B$1:$J$1, 0))), _xlpm.μ + _xlpm.σ * _xlpm.ε )} -> 0.011039737 | J2: {=_xlfn.LET( _xlpm.ε, (_xlfn.BETA.INV(RAND(), 5, 5) - 0.5) * 2, _xlpm.Scenario,H2, _xlpm.μ, _xlfn.XLOOKUP("Horizon", fundGrowth!$A$2:$A$4, INDEX(fundGrowth!$B$2:$J$4,0, MATCH(_xlpm.Scenario & " μ", fundGrowth!$B$1:$J$1, 0))), _xlpm.σ, _xlfn.XLOOKUP("Horizon", fundGrowth!$A$2:$A$4, INDEX(fundGrowth!$B$2:$J$4,0, MATCH(_xlpm.Scenario & " σ", fundGrowth!$B$1:$J$1, 0))), _xlpm.μ + _xlpm.σ * _xlpm.ε )} -> 0.060387737 | K2: {=_xlfn.LET( _xlpm.ε, (_xlfn.BETA.INV(RAND(), 5, 5) - 0.5) * 2, _xlpm.Scenario,H2, _xlpm.μ, _xlfn.XLOOKUP("SkyHigh", fundGrowth!$A$2:$A$4, INDEX(fundGrowth!$B$2:$J$4,0, MATCH(_xlpm.Scenario & " μ", fundGrowth!$B$1:$J$1, 0))), _xlpm.σ, _xlfn.XLOOKUP("SkyHigh", fundGrowth!$A$2:$A$4, INDEX(fundGrowth!$B$2:$J$4,0, MATCH(_xlpm.Scenario & " σ", fundGrowth!$B$1:$J$1, 0))), _xlpm.μ + _xlpm.σ * _xlpm.ε )} -> 0.20930115 | L2: =0.4*I2+0.3*J2+0.3*K2 -> 0.085322562 | M2: =G2*(1+L2)*(1-28%) -> 3197.1753 | N2: =M2*Q2 -> 3168.568 | O2: =N2+D2*Q2 -> 56200.273 | P2: =_xlfn.LET( _xlpm.μ, IF(RAND() < 0.001, 6% + 1.5% * _xlfn.NORM.S.INV(RAND()), _xlfn.BETA.INV(RAND(), 1.19, 1.22, 0.003, 0.04) ), _xlpm.ρ, _xlfn.BETA.INV(RAND(), 2, 2, 0.34,0.6), _xlpm.ε, MAX(0,_xlfn.NORM.S.INV(RAND())), _xlpm.μ + _xlpm.ρ * (_xlpm.μ - _xlpm.μ) + 1% * _xlpm.ε + MAX(0,_xlfn.IFS(A2=49,-_xlfn.NORM.INV(RAND(), 0.01, 0.005), A2=57,ABS(_xlfn.NORM.INV(RAND(), 0.02, 0.01)),TRUE,0)) ) -> 0.0090284707 | Q2: =1/(1+P2) -> 0.99105231 | S2: {=_xlfn.LET( _xlpm.KS_rate, $V$2 + 3%, _xlpm.ESCT_rate, 3%, _xlpm.W_HS, $V$3, _xlpm.W_HR, $V$4, _xlpm.W_SH, $V$5, _xlpm.salary, C2, _xlpm.salary_with_employer, _xlpm.salary + _xlpm.salary * _xlpm.ESCT_rate, _xlpm.esct, _xlpm.salary * _xlpm.ESCT_rate * _xlfn.IFS( _xlpm.salary_with_employer <= 18720, 10.5%, _xlpm.salary_with_employer <= 64200, 17.5%, _xlpm.salary_with_employer <= 93720, 30%, _xlpm.salary_with_employer <= 216000, 33%, _xlpm.salary_with_employer > 216000, 39% ), _xlpm.ks_contrib, _xlpm.salary * _xlpm.KS_rate - _xlpm.esct + 521.43, _xlpm.return_rate, _xlpm.W_HS * I2 + _xlpm.W_HR * J2 + _xlpm.W_SH * K2, _xlpm.net_growth, (1 + _xlpm.return_rate) * (1 - 28%), _xlpm.result, _xlpm.ks_contrib * _xlpm.net_growth, _xlpm.result )} -> 7026.1933 | T2: {=_xlfn.LET( _xlpm.KS_rate, $V$2 + 3%, _xlpm.ESCT_rate, 3%, _xlpm.W_HS, $V$3, _xlpm.W_HR, $V$4, _xlpm.W_SH, $V$5, _xlpm.salary, C2, _xlpm.salary_with_employer, _xlpm.salary + _xlpm.salary * _xlpm.ESCT_rate, _xlpm.esct, _xlpm.salary * _xlpm.ESCT_rate * _xlfn.IFS( _xlpm.salary_with_employer <= 18720, 10.5%, _xlpm.salary_with_employer <= 64200, 17.5%, _xlpm.salary_with_employer <= 93720, 30%, _xlpm.salary_with_employer <= 216000, 33%, _xlpm.salary_with_employer > 216000, 39% ), _xlpm.ks_contrib, _xlpm.salary * _xlpm.KS_rate - _xlpm.esct + 521.43, _xlpm.return_rate, _xlpm.W_HS * I2 + _xlpm.W_HR * J2 + _xlpm.W_SH * K2, _xlpm.net_growth, (1 + _xlpm.return_rate) * (1 - 28%), _xlpm.prev_value, IF(ROW()=2, 0, S1), _xlpm.base, IF(ROW()=2, _xlpm.ks_contrib, _xlpm.prev_value + _xlpm.ks_contrib ), _xlpm.current_value, _xlpm.base * _xlpm.net_growth, _xlpm.real_value, _xlpm.current_value * Q2, _xlpm.real_value )} -> 6963.3251 | U2: KiwiSaver Contribution Rate | V2: =Dashboard!Q2 -> 0.1 | X2: {=_xlfn.LET( _xlpm.KS_rate, Dashboard!$Q$2 + 3%, _xlpm.ESCT_rate, 3%, _xlpm.W_HS, _xlfn.SWITCH(H2, "Recession", Dashboard!$Q$4, "Normal", Dashboard!$Q$8, "Boom", Dashboard!$Q$12 ), _xlpm.W_HR, _xlfn.SWITCH(H2, "Recession", Dashboard!$Q$5, "Normal", Dashboard!$Q$9, "Boom", Dashboard!$Q$13 ), _xlpm.W_SH, _xlfn.SWITCH(H2, "Recession", Dashboard!$Q$6, "Normal", Dashboard!$Q$10, "Boom", Dashboard!$Q$14 ), _xlpm.salary, C2, _xlpm.salary_with_employer, _xlpm.salary + _xlpm.salary * _xlpm.ESCT_rate, _xlpm.esct, _xlpm.salary * _xlpm.ESCT_rate * _xlfn.IFS( _xlpm.salary_with_employer <= 18720, 10.5%, _xlpm.salary_with_employer <= 64200, 17.5%, _xlpm.salary_with_employer <= 93720, 30%, _xlpm.salary_with_employer <= 216000, 33%, _xlpm.salary_with_employer > 216000, 39% ), _xlpm.ks_contrib, _xlpm.salary * _xlpm.KS_rate - _xlpm.esct + 521.43, _xlpm.return_rate, _xlpm.W_HS * I2 + _xlpm.W_HR * J2 + _xlpm.W_SH * K2, _xlpm.net_growth, (1 + _xlpm.return_rate) * (1 - 28%), _xlpm.result, _xlpm.ks_contrib * _xlpm.net_growth, _xlpm.result )} -> 7346.7896 | Y2: {=_xlfn.LET( _xlpm.KS_rate, Dashboard!$Q$2 + 3%, _xlpm.ESCT_rate, 3%, _xlpm.W_HS, _xlfn.SWITCH(H2, "Recession", Dashboard!$Q$4, "Normal", Dashboard!$Q$8, "Boom", Dashboard!$Q$12 ), _xlpm.W_HR, _xlfn.SWITCH(H2, "Recession", Dashboard!$Q$5, "Normal", Dashboard!$Q$9, "Boom", Dashboard!$Q$13 ), _xlpm.W_SH, _xlfn.SWITCH(H2, "Recession", Dashboard!$Q$6, "Normal", Dashboard!$Q$10, "Boom", Dashboard!$Q$14 ), _xlpm.salary, C2, _xlpm.salary_with_employer, _xlpm.salary + _xlpm.salary * _xlpm.ESCT_rate, _xlpm.esct, _xlpm.salary * _xlpm.ESCT_rate * _xlfn.IFS( _xlpm.salary_with_employer <= 18720, 10.5%, _xlpm.salary_with_employer <= 64200, 17.5%, _xlpm.salary_with_employer <= 93720, 30%, _xlpm.salary_with_employer <= 216000, 33%, _xlpm.salary_with_employer > 216000, 39% ), _xlpm.ks_contrib, _xlpm.salary * _xlpm.KS_rate - _xlpm.esct + 521.43, _xlpm.return_rate, _xlpm.W_HS * I2 + _xlpm.W_HR * J2 + _xlpm.W_SH * K2, _xlpm.net_growth, (1 + _xlpm.return_rate) * (1 - 28%), _xlpm.prev_value, IF(ROW()=2, 0, X1), _xlpm.base, IF(ROW()=2, _xlpm.ks_contrib, _xlpm.prev_value + _xlpm.ks_contrib), _xlpm.current_value, _xlpm.base * _xlpm.net_growth, _xlpm.real_value, _xlpm.current_value * Q2, _xlpm.real_value )} -> 7281.0528 | Z2: 70000 | AG2: 0.03
A3: 31 | B3: =VLOOKUP(t4_salaryGrowthevent!J3,t4_salaryGrowthevent!J:J,1,FALSE) -> 0.03475 | C3: =VLOOKUP(t4_salaryGrowthevent!B3,t4_salaryGrowthevent!B:B,1,FALSE) -> 72432.5 | D3: {=_xlfn.LET( _xlpm.taxable, C3, _xlpm.kiwisaver,C3*0.03, _xlpm.incomeTax, _xlfn.IFS( _xlpm.taxable <= 15600, _xlpm.taxable * 10.5%, AND(_xlpm.taxable > 15600, _xlpm.taxable <= 53500), (_xlpm.taxable - 15600) * 17.5% + 15600 * 10.5%, AND(_xlpm.taxable > 53500, _xlpm.taxable <= 78100), (_xlpm.taxable - 53500) * 30% + (53500 - 15600) * 17.5% + 15600 * 10.5%, AND(_xlpm.taxable > 78100, _xlpm.taxable <= 180000), (_xlpm.taxable - 78100) * 33% + (78100 - 53500) * 30% + (53500 - 15600) * 17.5% + 15600 * 10.5%, _xlpm.taxable > 180000, (_xlpm.taxable - 180000) * 39% + (180000 - 78100) * 33% + (78100 - 53500) * 30% + (53500 - 15600) * 17.5% + 15600 * 10.5% ), _xlpm.acc, C3 * 0.0167, _xlpm.taxable - _xlpm.incomeTax - _xlpm.acc - _xlpm.kiwisaver )} -> 55099.652 | E3: =6%*C3 -> 4345.95 | F3: {=C3 * 3% * _xlfn.IFS( C3 + C3 * 3% <= 18720, 10.5%, C3 + C3 * 3% <= 64200, 17.5%, C3 + C3 * 3% <= 93720, 30%, C3 + C3 * 3% <= 216000, 33%, C3 + C3 * 3% > 216000, 39% )} -> 651.8925 | G3: =E3-F3+521.43 -> 4215.4875 | H3: {=_xlfn.IFS( H2="Boom", CHOOSE(MATCH(RAND(), {0,0.67,1}, 1), "Normal", "Recession"), H2="Normal", CHOOSE(MATCH(RAND(), {0,0.18,0.82,1}, 1), "Boom", "Normal", "Recession"), H2="Recession", CHOOSE(MATCH(RAND(), {0,0.17,0.34,1}, 1), "Boom", "Normal", "Recession") )} -> Boom | I3: {=_xlfn.LET( _xlpm.ε, (_xlfn.BETA.INV(RAND(), 5, 5) - 0.5) * 2, _xlpm.Scenario,H3, _xlpm.pre_scenario,H2, _xlpm.μ, _xlfn.XLOOKUP("HarbourSafe", fundGrowth!$A$2:$A$4, INDEX(fundGrowth!$B$2:$J$4,0, MATCH(_xlpm.Scenario & " μ", fundGrowth!$B$1:$J$1, 0))), _xlpm.σ, _xlfn.XLOOKUP("HarbourSafe", fundGrowth!$A$2:$A$4, INDEX(fundGrowth!$B$2:$J$4,0, MATCH(_xlpm.Scenario & " σ", fundGrowth!$B$1:$J$1, 0))), _xlpm.ρ, _xlfn.XLOOKUP("HarbourSafe", fundGrowth!$A$2:$A$4, INDEX(fundGrowth!$B$2:$J$4,0, MATCH(_xlpm.Scenario & " ρ", fundGrowth!$B$1:$J$1, 0))), _xlpm.μ_prev, _xlfn.XLOOKUP("HarbourSafe", fundGrowth!$A$2:$A$4, INDEX(fundGrowth!$B$2:$J$4,0, MATCH(_xlpm.pre_scenario & " μ", fundGrowth!$B$1:$J$1, 0))), _xlpm.μ + _xlpm.ρ*(I2-_xlpm.μ_prev) + _xlpm.σ * _xlpm.ε )} -> 0.038085905 | J3: {=_xlfn.LET( _xlpm.ε, (_xlfn.BETA.INV(RAND(), 5, 5) - 0.5) * 2, _xlpm.Scenario,H3, _xlpm.pre_scenario,H2, _xlpm.μ, _xlfn.XLOOKUP("Horizon", fundGrowth!$A$2:$A$4, INDEX(fundGrowth!$B$2:$J$4,0, MATCH(_xlpm.Scenario & " μ", fundGrowth!$B$1:$J$1, 0))), _xlpm.σ, _xlfn.XLOOKUP("Horizon", fundGrowth!$A$2:$A$4, INDEX(fundGrowth!$B$2:$J$4,0, MATCH(_xlpm.Scenario & " σ", fundGrowth!$B$1:$J$1, 0))), _xlpm.ρ, _xlfn.XLOOKUP("Horizon", fundGrowth!$A$2:$A$4, INDEX(fundGrowth!$B$2:$J$4,0, MATCH(_xlpm.Scenario & " ρ", fundGrowth!$B$1:$J$1, 0))), _xlpm.μ_prev, _xlfn.XLOOKUP("Horizon", fundGrowth!$A$2:$A$4, INDEX(fundGrowth!$B$2:$J$4,0, MATCH(_xlpm.pre_scenario & " μ", fundGrowth!$B$1:$J$1, 0))), _xlpm.μ + _xlpm.ρ*(MAX(J2, -0.05)-_xlpm.μ_prev) + _xlpm.σ * _xlpm.ε )} -> -0.14550929 | K3: {=_xlfn.LET( _xlpm.ε, (_xlfn.BETA.INV(RAND(), 5, 5) - 0.5) * 2, _xlpm.Scenario,H3, _xlpm.pre_scenario,H2, _xlpm.μ, _xlfn.XLOOKUP("SkyHigh", fundGrowth!$A$2:$A$4, INDEX(fundGrowth!$B$2:$J$4,0, MATCH(_xlpm.Scenario & " μ", fundGrowth!$B$1:$J$1, 0))), _xlpm.σ, _xlfn.XLOOKUP("SkyHigh", fundGrowth!$A$2:$A$4, INDEX(fundGrowth!$B$2:$J$4,0, MATCH(_xlpm.Scenario & " σ", fundGrowth!$B$1:$J$1, 0))), _xlpm.ρ, _xlfn.XLOOKUP("SkyHigh", fundGrowth!$A$2:$A$4, INDEX(fundGrowth!$B$2:$J$4,0, MATCH(_xlpm.Scenario & " ρ", fundGrowth!$B$1:$J$1, 0))), _xlpm.μ_prev, _xlfn.XLOOKUP("SkyHigh", fundGrowth!$A$2:$A$4, INDEX(fundGrowth!$B$2:$J$4,0, MATCH(_xlpm.pre_scenario & " μ", fundGrowth!$B$1:$J$1, 0))), _xlpm.μ + _xlpm.ρ*(MAX(K2, -0.07)-_xlpm.μ_prev) + _xlpm.σ * _xlpm.ε )} -> 0.2483702 | L3: =0.4*I3+0.3*J3+0.3*K3 -> 0.046092635 | M3: =(M2+G3)*(1+L3)*(1-28%) -> 5583.119 | N3: =M3*Q3 -> 5462.0687 | O3: =N3+D3*Q3 -> 59367.078 | P3: {=_xlfn.LET( _xlpm.state, H3, _xlpm.last, P2, _xlpm.μ, IF(RAND() < 0.001, 6% + 1.5% * _xlfn.NORM.S.INV(RAND()), _xlfn.BETA.INV(RAND(), 1.19, 1.22, 0.003, 0.04) ), _xlpm.ρ_min, _xlfn.IFS(_xlpm.state="Boom", 0.61, _xlpm.state="Normal", 0.34, _xlpm.state="Recession", 0.2), _xlpm.ρ_max, _xlfn.IFS(_xlpm.state="Boom", 0.8, _xlpm.state="Normal", 0.6, _xlpm.state="Recession", 0.33), _xlpm.α, _xlfn.IFS(_xlpm.state="Boom", 3, _xlpm.state="Normal", 2, _xlpm.state="Recession", 2), _xlpm.β, _xlfn.IFS(_xlpm.state="Boom", 2, _xlpm.state="Normal", 2, _xlpm.state="Recession", 3), _xlpm.ρ, _xlfn.BETA.INV(RAND(), _xlpm.α, _xlpm.β, _xlpm.ρ_min, _xlpm.ρ_max), _xlpm.ε, _xlfn.NORM.S.INV(RAND()), _xlpm.μ + _xlpm.ρ * (_xlpm.last - _xlpm.μ) + 0 * _xlpm.ε + MAX(0,_xlfn.IFS(A2=49,-_xlfn.NORM.INV(RAND(), 0.01, 0.005), A2=57,ABS(_xlfn.NORM.INV(RAND(), 0.02, 0.01)),TRUE,0)) )} -> 0.013016013 | Q3: =Q2/(1+P3) -> 0.97831851 | S3: {=_xlfn.LET( _xlpm.KS_rate, $V$2 + 3%, _xlpm.ESCT_rate, 3%, _xlpm.W_HS, $V$3, _xlpm.W_HR, $V$4, _xlpm.W_SH, $V$5, _xlpm.salary, C3, _xlpm.salary_with_employer, _xlpm.salary + _xlpm.salary * _xlpm.ESCT_rate, _xlpm.esct, _xlpm.salary * _xlpm.ESCT_rate * _xlfn.IFS( _xlpm.salary_with_employer <= 18720, 10.5%, _xlpm.salary_with_employer <= 64200, 17.5%, _xlpm.salary_with_employer <= 93720, 30%, _xlpm.salary_with_employer <= 216000, 33%, _xlpm.salary_with_employer > 216000, 39% ), _xlpm.ks_contrib, _xlpm.salary * _xlpm.KS_rate - _xlpm.esct + 521.43, _xlpm.return_rate, _xlpm.W_HS * I3 + _xlpm.W_HR * J3 + _xlpm.W_SH * K3, _xlpm.net_growth, (1 + _xlpm.return_rate) * (1 - 28%), _xlpm.prev_value, S2, _xlpm.result, (_xlpm.prev_value + _xlpm.ks_contrib) * _xlpm.net_growth, _xlpm.result )} -> 12285.948 | T3: {=_xlfn.LET( _xlpm.KS_rate, $V$2 + 3%, _xlpm.ESCT_rate, 3%, _xlpm.W_HS, $V$3, _xlpm.W_HR, $V$4, _xlpm.W_SH, $V$5, _xlpm.salary, C3, _xlpm.salary_with_employer, _xlpm.salary + _xlpm.salary * _xlpm.ESCT_rate, _xlpm.esct, _xlpm.salary * _xlpm.ESCT_rate * _xlfn.IFS( _xlpm.salary_with_employer <= 18720, 10.5%, _xlpm.salary_with_employer <= 64200, 17.5%, _xlpm.salary_with_employer <= 93720, 30%, _xlpm.salary_with_employer <= 216000, 33%, _xlpm.salary_with_employer > 216000, 39% ), _xlpm.ks_contrib, _xlpm.salary * _xlpm.KS_rate - _xlpm.esct + 521.43, _xlpm.return_rate, _xlpm.W_HS * I3 + _xlpm.W_HR * J3 + _xlpm.W_SH * K3, _xlpm.net_growth, (1 + _xlpm.return_rate) * (1 - 28%), _xlpm.prev_value, IF(ROW()=2, 0, S2), _xlpm.base, IF(ROW()=2, _xlpm.ks_contrib, _xlpm.prev_value + _xlpm.ks_contrib ), _xlpm.current_value, _xlpm.base * _xlpm.net_growth, _xlpm.real_value, _xlpm.current_value * Q3, _xlpm.real_value )} -> 12019.57 | U3: HarbourSafe Rate | V3: 0.4 | X3: {=_xlfn.LET( _xlpm.KS_rate, Dashboard!$Q$2 + 3%, _xlpm.ESCT_rate, 3%, _xlpm.W_HS, _xlfn.SWITCH(H2, "Recession", Dashboard!$Q$4, "Normal", Dashboard!$Q$8, "Boom", Dashboard!$Q$12 ), _xlpm.W_HR, _xlfn.SWITCH(H2, "Recession", Dashboard!$Q$5, "Normal", Dashboard!$Q$9, "Boom", Dashboard!$Q$13 ), _xlpm.W_SH, _xlfn.SWITCH(H2, "Recession", Dashboard!$Q$6, "Normal", Dashboard!$Q$10, "Boom", Dashboard!$Q$14 ), _xlpm.salary, C3, _xlpm.salary_with_employer, _xlpm.salary + _xlpm.salary * _xlpm.ESCT_rate, _xlpm.esct, _xlpm.salary * _xlpm.ESCT_rate * _xlfn.IFS( _xlpm.salary_with_employer <= 18720, 10.5%, _xlpm.salary_with_employer <= 64200, 17.5%, _xlpm.salary_with_employer <= 93720, 30%, _xlpm.salary_with_employer <= 216000, 33%, _xlpm.salary_with_employer > 216000, 39% ), _xlpm.ks_contrib, _xlpm.salary * _xlpm.KS_rate - _xlpm.esct + 521.43, _xlpm.return_rate, _xlpm.W_HS * I3 + _xlpm.W_HR * J3 + _xlpm.W_SH * K3, _xlpm.net_growth, (1 + _xlpm.return_rate) * (1 - 28%), _xlpm.prev_value, S2, _xlpm.result, (_xlpm.prev_value + _xlpm.ks_contrib) * _xlpm.net_growth, _xlpm.result )} -> 12348.639 | Y3: {=_xlfn.LET( _xlpm.KS_rate, Dashboard!$Q$2 + 3%, _xlpm.ESCT_rate, 3%, _xlpm.W_HS, _xlfn.SWITCH(H3, "Recession", Dashboard!$Q$4, "Normal", Dashboard!$Q$8, "Boom", Dashboard!$Q$12 ), _xlpm.W_HR, _xlfn.SWITCH(H3, "Recession", Dashboard!$Q$5, "Normal", Dashboard!$Q$9, "Boom", Dashboard!$Q$13 ), _xlpm.W_SH, _xlfn.SWITCH(H3, "Recession", Dashboard!$Q$6, "Normal", Dashboard!$Q$10, "Boom", Dashboard!$Q$14 ), _xlpm.salary, C3, _xlpm.salary_with_employer, _xlpm.salary + _xlpm.salary * _xlpm.ESCT_rate, _xlpm.esct, _xlpm.salary * _xlpm.ESCT_rate * _xlfn.IFS( _xlpm.salary_with_employer <= 18720, 10.5%, _xlpm.salary_with_employer <= 64200, 17.5%, _xlpm.salary_with_employer <= 93720, 30%, _xlpm.salary_with_employer <= 216000, 33%, _xlpm.salary_with_employer > 216000, 39% ), _xlpm.ks_contrib, _xlpm.salary * _xlpm.KS_rate - _xlpm.esct + 521.43, _xlpm.return_rate, _xlpm.W_HS * I3 + _xlpm.W_HR * J3 + _xlpm.W_SH * K3, _xlpm.net_growth, (1 + _xlpm.return_rate) * (1 - 28%), _xlpm.prev_value, IF(ROW()=2, 0, X2), _xlpm.base, IF(ROW()=2, _xlpm.ks_contrib, _xlpm.prev_value + _xlpm.ks_contrib), _xlpm.current_value, _xlpm.base * _xlpm.net_growth, _xlpm.real_value, _xlpm.current_value * Q3, _xlpm.real_value )} -> 14625.646 | Z3: 72432.5 | AG3: 0.04
A4: 32 | B4: =VLOOKUP(t4_salaryGrowthevent!J4,t4_salaryGrowthevent!J:J,1,FALSE) -> 0.03475 | C4: =VLOOKUP(t4_salaryGrowthevent!B4,t4_salaryGrowthevent!B:B,1,FALSE) -> 74949.529 | D4: {=_xlfn.LET( _xlpm.taxable, C4, _xlpm.kiwisaver,C4*0.03, _xlpm.incomeTax, _xlfn.IFS( _xlpm.taxable <= 15600, _xlpm.taxable * 10.5%, AND(_xlpm.taxable > 15600, _xlpm.taxable <= 53500), (_xlpm.taxable - 15600) * 17.5% + 15600 * 10.5%, AND(_xlpm.taxable > 53500, _xlpm.taxable <= 78100), (_xlpm.taxable - 53500) * 30% + (53500 - 15600) * 17.5% + 15600 * 10.5%, AND(_xlpm.taxable > 78100, _xlpm.taxable <= 180000), (_xlpm.taxable - 78100) * 33% + (78100 - 53500) * 30% + (53500 - 15600) * 17.5% + 15600 * 10.5%, _xlpm.taxable > 180000, (_xlpm.taxable - 180000) * 39% + (180000 - 78100) * 33% + (78100 - 53500) * 30% + (53500 - 15600) * 17.5% + 15600 * 10.5% ), _xlpm.acc, C4 * 0.0167, _xlpm.taxable - _xlpm.incomeTax - _xlpm.acc - _xlpm.kiwisaver )} -> 56744.028 | E4: =6%*C4 -> 4496.9718 | F4: {=C4 * 3% * _xlfn.IFS( C4 + C4 * 3% <= 18720, 10.5%, C4 + C4 * 3% <= 64200, 17.5%, C4 + C4 * 3% <= 93720, 30%, C4 + C4 * 3% <= 216000, 33%, C4 + C4 * 3% > 216000, 39% )} -> 674.54576 | G4: =E4-F4+521.43 -> 4343.856 | H4: {=_xlfn.IFS( H3="Boom", CHOOSE(MATCH(RAND(), {0,0.67,1}, 1), "Normal", "Recession"), H3="Normal", CHOOSE(MATCH(RAND(), {0,0.18,0.82,1}, 1), "Boom", "Normal", "Recession"), H3="Recession", CHOOSE(MATCH(RAND(), {0,0.17,0.34,1}, 1), "Boom", "Normal", "Recession") )} -> Normal | I4: {=_xlfn.LET( _xlpm.ε, (_xlfn.BETA.INV(RAND(), 5, 5) - 0.5) * 2, _xlpm.Scenario,H4, _xlpm.pre_scenario,H3, _xlpm.μ, _xlfn.XLOOKUP("HarbourSafe", fundGrowth!$A$2:$A$4, INDEX(fundGrowth!$B$2:$J$4,0, MATCH(_xlpm.Scenario & " μ", fundGrowth!$B$1:$J$1, 0))), _xlpm.σ, _xlfn.XLOOKUP("HarbourSafe", fundGrowth!$A$2:$A$4, INDEX(fundGrowth!$B$2:$J$4,0, MATCH(_xlpm.Scenario & " σ", fundGrowth!$B$1:$J$1, 0))), _xlpm.ρ, _xlfn.XLOOKUP("HarbourSafe", fundGrowth!$A$2:$A$4, INDEX(fundGrowth!$B$2:$J$4,0, MATCH(_xlpm.Scenario & " ρ", fundGrowth!$B$1:$J$1, 0))), _xlpm.μ_prev, _xlfn.XLOOKUP("HarbourSafe", fundGrowth!$A$2:$A$4, INDEX(fundGrowth!$B$2:$J$4,0, MATCH(_xlpm.pre_scenario & " μ", fundGrowth!$B$1:$J$1, 0))), _xlpm.μ + _xlpm.ρ*(I3-_xlpm.μ_prev) + _xlpm.σ * _xlpm.ε )} -> 0.02923501 | J4: {=_xlfn.LET( _xlpm.ε, (_xlfn.BETA.INV(RAND(), 5, 5) - 0.5) * 2, _xlpm.Scenario,H4, _xlpm.pre_scenario,H3, _xlpm.μ, _xlfn.XLOOKUP("Horizon", fundGrowth!$A$2:$A$4, INDEX(fundGrowth!$B$2:$J$4,0, MATCH(_xlpm.Scenario & " μ", fundGrowth!$B$1:$J$1, 0))), _xlpm.σ, _xlfn.XLOOKUP("Horizon", fundGrowth!$A$2:$A$4, INDEX(fundGrowth!$B$2:$J$4,0, MATCH(_xlpm.Scenario & " σ", fundGrowth!$B$1:$J$1, 0))), _xlpm.ρ, _xlfn.XLOOKUP("Horizon", fundGrowth!$A$2:$A$4, INDEX(fundGrowth!$B$2:$J$4,0, MATCH(_xlpm.Scenario & " ρ", fundGrowth!$B$1:$J$1, 0))), _xlpm.μ_prev, _xlfn.XLOOKUP("Horizon", fundGrowth!$A$2:$A$4, INDEX(fundGrowth!$B$2:$J$4,0, MATCH(_xlpm.pre_scenario & " μ", fundGrowth!$B$1:$J$1, 0))), _xlpm.μ + _xlpm.ρ*(MAX(J3, -0.05)-_xlpm.μ_prev) + _xlpm.σ * _xlpm.ε )} -> 0.012295627 | K4: {=_xlfn.LET( _xlpm.ε, (_xlfn.BETA.INV(RAND(), 5, 5) - 0.5) * 2, _xlpm.Scenario,H4, _xlpm.pre_scenario,H3, _xlpm.μ, _xlfn.XLOOKUP("SkyHigh", fundGrowth!$A$2:$A$4, INDEX(fundGrowth!$B$2:$J$4,0, MATCH(_xlpm.Scenario & " μ", fundGrowth!$B$1:$J$1, 0))), _xlpm.σ, _xlfn.XLOOKUP("SkyHigh", fundGrowth!$A$2:$A$4, INDEX(fundGrowth!$B$2:$J$4,0, MATCH(_xlpm.Scenario & " σ", fundGrowth!$B$1:$J$1, 0))), _xlpm.ρ, _xlfn.XLOOKUP("SkyHigh", fundGrowth!$A$2:$A$4, INDEX(fundGrowth!$B$2:$J$4,0, MATCH(_xlpm.Scenario & " ρ", fundGrowth!$B$1:$J$1, 0))), _xlpm.μ_prev, _xlfn.XLOOKUP("SkyHigh", fundGrowth!$A$2:$A$4, INDEX(fundGrowth!$B$2:$J$4,0, MATCH(_xlpm.pre_scenario & " μ", fundGrowth!$B$1:$J$1, 0))), _xlpm.μ + _xlpm.ρ*(MAX(K3, -0.07)-_xlpm.μ_prev) + _xlpm.σ * _xlpm.ε )} -> 0.14404413 | L4: =0.4*I4+0.3*J4+0.3*K4 -> 0.058595932 | M4: =(M3+G4)*(1+L4)*(1-28%) -> 7566.2319 | N4: =M4*Q4 -> 7237.0006 | O4: =N4+D4*Q4 -> 61511.911 | P4: {=_xlfn.LET( _xlpm.state, H4, _xlpm.last, P3, _xlpm.μ, IF(RAND() < 0.001, 6% + 1.5% * _xlfn.NORM.S.INV(RAND()), _xlfn.BETA.INV(RAND(), 1.19, 1.22, 0.003, 0.04) ), _xlpm.ρ_min, _xlfn.IFS(_xlpm.state="Boom", 0.61, _xlpm.state="Normal", 0.34, _xlpm.state="Recession", 0.2), _xlpm.ρ_max, _xlfn.IFS(_xlpm.state="Boom", 0.8, _xlpm.state="Normal", 0.6, _xlpm.state="Recession", 0.33), _xlpm.α, _xlfn.IFS(_xlpm.state="Boom", 3, _xlpm.state="Normal", 2, _xlpm.state="Recession", 2), _xlpm.β, _xlfn.IFS(_xlpm.state="Boom", 2, _xlpm.state="Normal", 2, _xlpm.state="Recession", 3), _xlpm.ρ, _xlfn.BETA.INV(RAND(), _xlpm.α, _xlpm.β, _xlpm.ρ_min, _xlpm.ρ_max), _xlpm.ε, _xlfn.NORM.S.INV(RAND()), _xlpm.μ + _xlpm.ρ * (_xlpm.last - _xlpm.μ) + 0 * _xlpm.ε + MAX(0,_xlfn.IFS(A3=49,-_xlfn.NORM.INV(RAND(), 0.01, 0.005), A3=57,ABS(_xlfn.NORM.INV(RAND(), 0.02, 0.01)),TRUE,0)) )} -> 0.022824937 | Q4: =Q3/(1+P4) -> 0.95648676 | S4: {=_xlfn.LET( _xlpm.KS_rate, $V$2 + 3%, _xlpm.ESCT_rate, 3%, _xlpm.W_HS, $V$3, _xlpm.W_HR, $V$4, _xlpm.W_SH, $V$5, _xlpm.salary, C4, _xlpm.salary_with_employer, _xlpm.salary + _xlpm.salary * _xlpm.ESCT_rate, _xlpm.esct, _xlpm.salary * _xlpm.ESCT_rate * _xlfn.IFS( _xlpm.salary_with_employer <= 18720, 10.5%, _xlpm.salary_with_employer <= 64200, 17.5%, _xlpm.salary_with_employer <= 93720, 30%, _xlpm.salary_with_employer <= 216000, 33%, _xlpm.salary_with_employer > 216000, 39% ), _xlpm.ks_contrib, _xlpm.salary * _xlpm.KS_rate - _xlpm.esct + 521.43, _xlpm.return_rate, _xlpm.W_HS * I4 + _xlpm.W_HR * J4 + _xlpm.W_SH * K4, _xlpm.net_growth, (1 + _xlpm.return_rate) * (1 - 28%), _xlpm.prev_value, S3, _xlpm.result, (_xlpm.prev_value + _xlpm.ks_contrib) * _xlpm.net_growth, _xlpm.result )} -> 16673.855 | T4: {=_xlfn.LET( _xlpm.KS_rate, $V$2 + 3%, _xlpm.ESCT_rate, 3%, _xlpm.W_HS, $V$3, _xlpm.W_HR, $V$4, _xlpm.W_SH, $V$5, _xlpm.salary, C4, _xlpm.salary_with_employer, _xlpm.salary + _xlpm.salary * _xlpm.ESCT_rate, _xlpm.esct, _xlpm.salary * _xlpm.ESCT_rate * _xlfn.IFS( _xlpm.salary_with_employer <= 18720, 10.5%, _xlpm.salary_with_employer <= 64200, 17.5%, _xlpm.salary_with_employer <= 93720, 30%, _xlpm.salary_with_employer <= 216000, 33%, _xlpm.salary_with_employer > 216000, 39% ), _xlpm.ks_contrib, _xlpm.salary * _xlpm.KS_rate - _xlpm.esct + 521.43, _xlpm.return_rate, _xlpm.W_HS * I4 + _xlpm.W_HR * J4 + _xlpm.W_SH * K4, _xlpm.net_growth, (1 + _xlpm.return_rate) * (1 - 28%), _xlpm.prev_value, IF(ROW()=2, 0, S3), _xlpm.base, IF(ROW()=2, _xlpm.ks_contrib, _xlpm.prev_value + _xlpm.ks_contrib ), _xlpm.current_value, _xlpm.base * _xlpm.net_growth, _xlpm.real_value, _xlpm.current_value * Q4, _xlpm.real_value )} -> 15948.321 | U4: Horizon Rate | V4: 0.3 | X4: {=_xlfn.LET( _xlpm.KS_rate, Dashboard!$Q$2 + 3%, _xlpm.ESCT_rate, 3%, _xlpm.W_HS, _xlfn.SWITCH(H3, "Recession", Dashboard!$Q$4, "Normal", Dashboard!$Q$8, "Boom", Dashboard!$Q$12 ), _xlpm.W_HR, _xlfn.SWITCH(H3, "Recession", Dashboard!$Q$5, "Normal", Dashboard!$Q$9, "Boom", Dashboard!$Q$13 ), _xlpm.W_SH, _xlfn.SWITCH(H3, "Recession", Dashboard!$Q$6, "Normal", Dashboard!$Q$10, "Boom", Dashboard!$Q$14 ), _xlpm.salary, C4, _xlpm.salary_with_employer, _xlpm.salary + _xlpm.salary * _xlpm.ESCT_rate, _xlpm.esct, _xlpm.salary * _xlpm.ESCT_rate * _xlfn.IFS( _xlpm.salary_with_employer <= 18720, 10.5%, _xlpm.salary_with_employer <= 64200, 17.5%, _xlpm.salary_with_employer <= 93720, 30%, _xlpm.salary_with_employer <= 216000, 33%, _xlpm.salary_with_employer > 216000, 39% ), _xlpm.ks_contrib, _xlpm.salary * _xlpm.KS_rate - _xlpm.esct + 521.43, _xlpm.return_rate, _xlpm.W_HS * I4 + _xlpm.W_HR * J4 + _xlpm.W_SH * K4, _xlpm.net_growth, (1 + _xlpm.return_rate) * (1 - 28%), _xlpm.prev_value, S3, _xlpm.result, (_xlpm.prev_value + _xlpm.ks_contrib) * _xlpm.net_growth, _xlpm.result )} -> 18019.742 | Y4: {=_xlfn.LET( _xlpm.KS_rate, Dashboard!$Q$2 + 3%, _xlpm.ESCT_rate, 3%, _xlpm.W_HS, _xlfn.SWITCH(H4, "Recession", Dashboard!$Q$4, "Normal", Dashboard!$Q$8, "Boom", Dashboard!$Q$12 ), _xlpm.W_HR, _xlfn.SWITCH(H4, "Recession", Dashboard!$Q$5, "Normal", Dashboard!$Q$9, "Boom", Dashboard!$Q$13 ), _xlpm.W_SH, _xlfn.SWITCH(H4, "Recession", Dashboard!$Q$6, "Normal", Dashboard!$Q$10, "Boom", Dashboard!$Q$14 ), _xlpm.salary, C4, _xlpm.salary_with_employer, _xlpm.salary + _xlpm.salary * _xlpm.ESCT_rate, _xlpm.esct, _xlpm.salary * _xlpm.ESCT_rate * _xlfn.IFS( _xlpm.salary_with_employer <= 18720, 10.5%, _xlpm.salary_with_employer <= 64200, 17.5%, _xlpm.salary_with_employer <= 93720, 30%, _xlpm.salary_with_employer <= 216000, 33%, _xlpm.salary_with_employer > 216000, 39% ), _xlpm.ks_contrib, _xlpm.salary * _xlpm.KS_rate - _xlpm.esct + 521.43, _xlpm.return_rate, _xlpm.W_HS * I4 + _xlpm.W_HR * J4 + _xlpm.W_SH * K4, _xlpm.net_growth, (1 + _xlpm.return_rate) * (1 - 28%), _xlpm.prev_value, IF(ROW()=2, 0, X3), _xlpm.base, IF(ROW()=2, _xlpm.ks_contrib, _xlpm.prev_value + _xlpm.ks_contrib), _xlpm.current_value, _xlpm.base * _xlpm.net_growth, _xlpm.real_value, _xlpm.current_value * Q4, _xlpm.real_value )} -> 16289.761 | Z4: 74949.529 | AG4: 0.06
A5: 33 | B5: =VLOOKUP(t4_salaryGrowthevent!J5,t4_salaryGrowthevent!J:J,1,FALSE) -> 0.03475 | C5: =VLOOKUP(t4_salaryGrowthevent!B5,t4_salaryGrowthevent!B:B,1,FALSE) -> 77554.026 | D5: {=_xlfn.LET( _xlpm.taxable, C5, _xlpm.kiwisaver,C5*0.03, _xlpm.incomeTax, _xlfn.IFS( _xlpm.taxable <= 15600, _xlpm.taxable * 10.5%, AND(_xlpm.taxable > 15600, _xlpm.taxable <= 53500), (_xlpm.taxable - 15600) * 17.5% + 15600 * 10.5%, AND(_xlpm.taxable > 53500, _xlpm.taxable <= 78100), (_xlpm.taxable - 53500) * 30% + (53500 - 15600) * 17.5% + 15600 * 10.5%, AND(_xlpm.taxable > 78100, _xlpm.taxable <= 180000), (_xlpm.taxable - 78100) * 33% + (78100 - 53500) * 30% + (53500 - 15600) * 17.5% + 15600 * 10.5%, _xlpm.taxable > 180000, (_xlpm.taxable - 180000) * 39% + (180000 - 78100) * 33% + (78100 - 53500) * 30% + (53500 - 15600) * 17.5% + 15600 * 10.5% ), _xlpm.acc, C5 * 0.0167, _xlpm.taxable - _xlpm.incomeTax - _xlpm.acc - _xlpm.kiwisaver )} -> 58445.545 | E5: =6%*C5 -> 4653.2415 | F5: {=C5 * 3% * _xlfn.IFS( C5 + C5 * 3% <= 18720, 10.5%, C5 + C5 * 3% <= 64200, 17.5%, C5 + C5 * 3% <= 93720, 30%, C5 + C5 * 3% <= 216000, 33%, C5 + C5 * 3% > 216000, 39% )} -> 697.98623 | G5: =E5-F5+521.43 -> 4476.6853 | H5: {=_xlfn.IFS( H4="Boom", CHOOSE(MATCH(RAND(), {0,0.67,1}, 1), "Normal", "Recession"), H4="Normal", CHOOSE(MATCH(RAND(), {0,0.18,0.82,1}, 1), "Boom", "Normal", "Recession"), H4="Recession", CHOOSE(MATCH(RAND(), {0,0.17,0.34,1}, 1), "Boom", "Normal", "Recession") )} -> Normal | I5: {=_xlfn.LET( _xlpm.ε, (_xlfn.BETA.INV(RAND(), 5, 5) - 0.5) * 2, _xlpm.Scenario,H5, _xlpm.pre_scenario,H4, _xlpm.μ, _xlfn.XLOOKUP("HarbourSafe", fundGrowth!$A$2:$A$4, INDEX(fundGrowth!$B$2:$J$4,0, MATCH(_xlpm.Scenario & " μ", fundGrowth!$B$1:$J$1, 0))), _xlpm.σ, _xlfn.XLOOKUP("HarbourSafe", fundGrowth!$A$2:$A$4, INDEX(fundGrowth!$B$2:$J$4,0, MATCH(_xlpm.Scenario & " σ", fundGrowth!$B$1:$J$1, 0))), _xlpm.ρ, _xlfn.XLOOKUP("HarbourSafe", fundGrowth!$A$2:$A$4, INDEX(fundGrowth!$B$2:$J$4,0, MATCH(_xlpm.Scenario & " ρ", fundGrowth!$B$1:$J$1, 0))), _xlpm.μ_prev, _xlfn.XLOOKUP("HarbourSafe", fundGrowth!$A$2:$A$4, INDEX(fundGrowth!$B$2:$J$4,0, MATCH(_xlpm.pre_scenario & " μ", fundGrowth!$B$1:$J$1, 0))), _xlpm.μ + _xlpm.ρ*(I4-_xlpm.μ_prev) + _xlpm.σ * _xlpm.ε )} -> 0.042967787 | J5: {=_xlfn.LET( _xlpm.ε, (_xlfn.BETA.INV(RAND(), 5, 5) - 0.5) * 2, _xlpm.Scenario,H5, _xlpm.pre_scenario,H4, _xlpm.μ, _xlfn.XLOOKUP("Horizon", fundGrowth!$A$2:$A$4, INDEX(fundGrowth!$B$2:$J$4,0, MATCH(_xlpm.Scenario & " μ", fundGrowth!$B$1:$J$1, 0))), _xlpm.σ, _xlfn.XLOOKUP("Horizon", fundGrowth!$A$2:$A$4, INDEX(fundGrowth!$B$2:$J$4,0, MATCH(_xlpm.Scenario & " σ", fundGrowth!$B$1:$J$1, 0))), _xlpm.ρ, _xlfn.XLOOKUP("Horizon", fundGrowth!$A$2:$A$4, INDEX(fundGrowth!$B$2:$J$4,0, MATCH(_xlpm.Scenario & " ρ", fundGrowth!$B$1:$J$1, 0))), _xlpm.μ_prev, _xlfn.XLOOKUP("Horizon", fundGrowth!$A$2:$A$4, INDEX(fundGrowth!$B$2:$J$4,0, MATCH(_xlpm.pre_scenario & " μ", fundGrowth!$B$1:$J$1, 0))), _xlpm.μ + _xlpm.ρ*(MAX(J4, -0.05)-_xlpm.μ_prev) + _xlpm.σ * _xlpm.ε )} -> 0.0092928476 | K5: {=_xlfn.LET( _xlpm.ε, (_xlfn.BETA.INV(RAND(), 5, 5) - 0.5) * 2, _xlpm.Scenario,H5, _xlpm.pre_scenario,H4, _xlpm.μ, _xlfn.XLOOKUP("SkyHigh", fundGrowth!$A$2:$A$4, INDEX(fundGrowth!$B$2:$J$4,0, MATCH(_xlpm.Scenario & " μ", fundGrowth!$B$1:$J$1, 0))), _xlpm.σ, _xlfn.XLOOKUP("SkyHigh", fundGrowth!$A$2:$A$4, INDEX(fundGrowth!$B$2:$J$4,0, MATCH(_xlpm.Scenario & " σ", fundGrowth!$B$1:$J$1, 0))), _xlpm.ρ, _xlfn.XLOOKUP("SkyHigh", fundGrowth!$A$2:$A$4, INDEX(fundGrowth!$B$2:$J$4,0, MATCH(_xlpm.Scenario & " ρ", fundGrowth!$B$1:$J$1, 0))), _xlpm.μ_prev, _xlfn.XLOOKUP("SkyHigh", fundGrowth!$A$2:$A$4, INDEX(fundGrowth!$B$2:$J$4,0, MATCH(_xlpm.pre_scenario & " μ", fundGrowth!$B$1:$J$1, 0))), _xlpm.μ + _xlpm.ρ*(MAX(K4, -0.07)-_xlpm.μ_prev) + _xlpm.σ * _xlpm.ε )} -> 0.17686776 | L5: =0.4*I5+0.3*J5+0.3*K5 -> 0.073035296 | M5: =(M4+G5)*(1+L5)*(1-28%) -> 9304.1821 | N5: =M5*Q5 -> 8722.949 | O5: =N5+D5*Q5 -> 63517.395 | P5: {=_xlfn.LET( _xlpm.state, H5, _xlpm.last, P4, _xlpm.μ, IF(RAND() < 0.001, 6% + 1.5% * _xlfn.NORM.S.INV(RAND()), _xlfn.BETA.INV(RAND(), 1.19, 1.22, 0.003, 0.04) ), _xlpm.ρ_min, _xlfn.IFS(_xlpm.state="Boom", 0.61, _xlpm.state="Normal", 0.34, _xlpm.state="Recession", 0.2), _xlpm.ρ_max, _xlfn.IFS(_xlpm.state="Boom", 0.8, _xlpm.state="Normal", 0.6, _xlpm.state="Recession", 0.33), _xlpm.α, _xlfn.IFS(_xlpm.state="Boom", 3, _xlpm.state="Normal", 2, _xlpm.state="Recession", 2), _xlpm.β, _xlfn.IFS(_xlpm.state="Boom", 2, _xlpm.state="Normal", 2, _xlpm.state="Recession", 3), _xlpm.ρ, _xlfn.BETA.INV(RAND(), _xlpm.α, _xlpm.β, _xlpm.ρ_min, _xlpm.ρ_max), _xlpm.ε, _xlfn.NORM.S.INV(RAND()), _xlpm.μ + _xlpm.ρ * (_xlpm.last - _xlpm.μ) + 0 * _xlpm.ε + MAX(0,_xlfn.IFS(A4=49,-_xlfn.NORM.INV(RAND(), 0.01, 0.005), A4=57,ABS(_xlfn.NORM.INV(RAND(), 0.02, 0.01)),TRUE,0)) )} -> 0.02022 | Q5: =Q4/(1+P5) -> 0.9375299 | S5: {=_xlfn.LET( _xlpm.KS_rate, $V$2 + 3%, _xlpm.ESCT_rate, 3%, _xlpm.W_HS, $V$3, _xlpm.W_HR, $V$4, _xlpm.W_SH, $V$5, _xlpm.salary, C5, _xlpm.salary_with_employer, _xlpm.salary + _xlpm.salary * _xlpm.ESCT_rate, _xlpm.esct, _xlpm.salary * _xlpm.ESCT_rate * _xlfn.IFS( _xlpm.salary_with_employer <= 18720, 10.5%, _xlpm.salary_with_employer <= 64200, 17.5%, _xlpm.salary_with_employer <= 93720, 30%, _xlpm.salary_with_employer <= 216000, 33%, _xlpm.salary_with_employer > 216000, 39% ), _xlpm.ks_contrib, _xlpm.salary * _xlpm.KS_rate - _xlpm.esct + 521.43, _xlpm.return_rate, _xlpm.W_HS * I5 + _xlpm.W_HR * J5 + _xlpm.W_SH * K5, _xlpm.net_growth, (1 + _xlpm.return_rate) * (1 - 28%), _xlpm.prev_value, S4, _xlpm.result, (_xlpm.prev_value + _xlpm.ks_contrib) * _xlpm.net_growth, _xlpm.result )} -> 20534.796 | T5: {=_xlfn.LET( _xlpm.KS_rate, $V$2 + 3%, _xlpm.ESCT_rate, 3%, _xlpm.W_HS, $V$3, _xlpm.W_HR, $V$4, _xlpm.W_SH, $V$5, _xlpm.salary, C5, _xlpm.salary_with_employer, _xlpm.salary + _xlpm.salary * _xlpm.ESCT_rate, _xlpm.esct, _xlpm.salary * _xlpm.ESCT_rate * _xlfn.IFS( _xlpm.salary_with_employer <= 18720, 10.5%, _xlpm.salary_with_employer <= 64200, 17.5%, _xlpm.salary_with_employer <= 93720, 30%, _xlpm.salary_with_employer <= 216000, 33%, _xlpm.salary_with_employer > 216000, 39% ), _xlpm.ks_contrib, _xlpm.salary * _xlpm.KS_rate - _xlpm.esct + 521.43, _xlpm.return_rate, _xlpm.W_HS * I5 + _xlpm.W_HR * J5 + _xlpm.W_SH * K5, _xlpm.net_growth, (1 + _xlpm.return_rate) * (1 - 28%), _xlpm.prev_value, IF(ROW()=2, 0, S4), _xlpm.base, IF(ROW()=2, _xlpm.ks_contrib, _xlpm.prev_value + _xlpm.ks_contrib ), _xlpm.current_value, _xlpm.base * _xlpm.net_growth, _xlpm.real_value, _xlpm.current_value * Q5, _xlpm.real_value )} -> 19251.986 | U5: SkyHigh Rate | V5: 0.3 | X5: {=_xlfn.LET( _xlpm.KS_rate, Dashboard!$Q$2 + 3%, _xlpm.ESCT_rate, 3%, _xlpm.W_HS, _xlfn.SWITCH(H4, "Recession", Dashboard!$Q$4, "Normal", Dashboard!$Q$8, "Boom", Dashboard!$Q$12 ), _xlpm.W_HR, _xlfn.SWITCH(H4, "Recession", Dashboard!$Q$5, "Normal", Dashboard!$Q$9, "Boom", Dashboard!$Q$13 ), _xlpm.W_SH, _xlfn.SWITCH(H4, "Recession", Dashboard!$Q$6, "Normal", Dashboard!$Q$10, "Boom", Dashboard!$Q$14 ), _xlpm.salary, C5, _xlpm.salary_with_employer, _xlpm.salary + _xlpm.salary * _xlpm.ESCT_rate, _xlpm.esct, _xlpm.salary * _xlpm.ESCT_rate * _xlfn.IFS( _xlpm.salary_with_employer <= 18720, 10.5%, _xlpm.salary_with_employer <= 64200, 17.5%, _xlpm.salary_with_employer <= 93720, 30%, _xlpm.salary_with_employer <= 216000, 33%, _xlpm.salary_with_employer > 216000, 39% ), _xlpm.ks_contrib, _xlpm.salary * _xlpm.KS_rate - _xlpm.esct + 521.43, _xlpm.return_rate, _xlpm.W_HS * I5 + _xlpm.W_HR * J5 + _xlpm.W_SH * K5, _xlpm.net_growth, (1 + _xlpm.return_rate) * (1 - 28%), _xlpm.prev_value, S4, _xlpm.result, (_xlpm.prev_value + _xlpm.ks_contrib) * _xlpm.net_growth, _xlpm.result )} -> 20918.4 | Y5: {=_xlfn.LET( _xlpm.KS_rate, Dashboard!$Q$2 + 3%, _xlpm.ESCT_rate, 3%, _xlpm.W_HS, _xlfn.SWITCH(H5, "Recession", Dashboard!$Q$4, "Normal", Dashboard!$Q$8, "Boom", Dashboard!$Q$12 ), _xlpm.W_HR, _xlfn.SWITCH(H5, "Recession", Dashboard!$Q$5, "Normal", Dashboard!$Q$9, "Boom", Dashboard!$Q$13 ), _xlpm.W_SH, _xlfn.SWITCH(H5, "Recession", Dashboard!$Q$6, "Normal", Dashboard!$Q$10, "Boom", Dashboard!$Q$14 ), _xlpm.salary, C5, _xlpm.salary_with_employer, _xlpm.salary + _xlpm.salary * _xlpm.ESCT_rate, _xlpm.esct, _xlpm.salary * _xlpm.ESCT_rate * _xlfn.IFS( _xlpm.salary_with_employer <= 18720, 10.5%, _xlpm.salary_with_employer <= 64200, 17.5%, _xlpm.salary_with_employer <= 93720, 30%, _xlpm.salary_with_employer <= 216000, 33%, _xlpm.salary_with_employer > 216000, 39% ), _xlpm.ks_contrib, _xlpm.salary * _xlpm.KS_rate - _xlpm.esct + 521.43, _xlpm.return_rate, _xlpm.W_HS * I5 + _xlpm.W_HR * J5 + _xlpm.W_SH * K5, _xlpm.net_growth, (1 + _xlpm.return_rate) * (1 - 28%), _xlpm.prev_value, IF(ROW()=2, 0, X4), _xlpm.base, IF(ROW()=2, _xlpm.ks_contrib, _xlpm.prev_value + _xlpm.ks_contrib), _xlpm.current_value, _xlpm.base * _xlpm.net_growth, _xlpm.real_value, _xlpm.current_value * Q5, _xlpm.real_value )} -> 20604.692 | Z5: 77554.026 | AG5: 0.08
A6: 34 | B6: =VLOOKUP(t4_salaryGrowthevent!J6,t4_salaryGrowthevent!J:J,1,FALSE) -> 0.03475 | C6: =VLOOKUP(t4_salaryGrowthevent!B6,t4_salaryGrowthevent!B:B,1,FALSE) -> 80249.028 | D6: {=_xlfn.LET( _xlpm.taxable, C6, _xlpm.kiwisaver,C6*0.03, _xlpm.incomeTax, _xlfn.IFS( _xlpm.taxable <= 15600, _xlpm.taxable * 10.5%, AND(_xlpm.taxable > 15600, _xlpm.taxable <= 53500), (_xlpm.taxable - 15600) * 17.5% + 15600 * 10.5%, AND(_xlpm.taxable > 53500, _xlpm.taxable <= 78100), (_xlpm.taxable - 53500) * 30% + (53500 - 15600) * 17.5% + 15600 * 10.5%, AND(_xlpm.taxable > 78100, _xlpm.taxable <= 180000), (_xlpm.taxable - 78100) * 33% + (78100 - 53500) * 30% + (53500 - 15600) * 17.5% + 15600 * 10.5%, _xlpm.taxable > 180000, (_xlpm.taxable - 180000) * 39% + (180000 - 78100) * 33% + (78100 - 53500) * 30% + (53500 - 15600) * 17.5% + 15600 * 10.5% ), _xlpm.acc, C6 * 0.0167, _xlpm.taxable - _xlpm.incomeTax - _xlpm.acc - _xlpm.kiwisaver )} -> 60141.719 | E6: =6%*C6 -> 4814.9417 | F6: {=C6 * 3% * _xlfn.IFS( C6 + C6 * 3% <= 18720, 10.5%, C6 + C6 * 3% <= 64200, 17.5%, C6 + C6 * 3% <= 93720, 30%, C6 + C6 * 3% <= 216000, 33%, C6 + C6 * 3% > 216000, 39% )} -> 722.24125 | G6: =E6-F6+521.43 -> 4614.1304 | H6: {=_xlfn.IFS( H5="Boom", CHOOSE(MATCH(RAND(), {0,0.67,1}, 1), "Normal", "Recession"), H5="Normal", CHOOSE(MATCH(RAND(), {0,0.18,0.82,1}, 1), "Boom", "Normal", "Recession"), H5="Recession", CHOOSE(MATCH(RAND(), {0,0.17,0.34,1}, 1), "Boom", "Normal", "Recession") )} -> Normal | I6: {=_xlfn.LET( _xlpm.ε, (_xlfn.BETA.INV(RAND(), 5, 5) - 0.5) * 2, _xlpm.Scenario,H6, _xlpm.pre_scenario,H5, _xlpm.μ, _xlfn.XLOOKUP("HarbourSafe", fundGrowth!$A$2:$A$4, INDEX(fundGrowth!$B$2:$J$4,0, MATCH(_xlpm.Scenario & " μ", fundGrowth!$B$1:$J$1, 0))), _xlpm.σ, _xlfn.XLOOKUP("HarbourSafe", fundGrowth!$A$2:$A$4, INDEX(fundGrowth!$B$2:$J$4,0, MATCH(_xlpm.Scenario & " σ", fundGrowth!$B$1:$J$1, 0))), _xlpm.ρ, _xlfn.XLOOKUP("HarbourSafe", fundGrowth!$A$2:$A$4, INDEX(fundGrowth!$B$2:$J$4,0, MATCH(_xlpm.Scenario & " ρ", fundGrowth!$B$1:$J$1, 0))), _xlpm.μ_prev, _xlfn.XLOOKUP("HarbourSafe", fundGrowth!$A$2:$A$4, INDEX(fundGrowth!$B$2:$J$4,0, MATCH(_xlpm.pre_scenario & " μ", fundGrowth!$B$1:$J$1, 0))), _xlpm.μ + _xlpm.ρ*(I5-_xlpm.μ_prev) + _xlpm.σ * _xlpm.ε )} -> 0.068419423 | J6: {=_xlfn.LET( _xlpm.ε, (_xlfn.BETA.INV(RAND(), 5, 5) - 0.5) * 2, _xlpm.Scenario,H6, _xlpm.pre_scenario,H5, _xlpm.μ, _xlfn.XLOOKUP("Horizon", fundGrowth!$A$2:$A$4, INDEX(fundGrowth!$B$2:$J$4,0, MATCH(_xlpm.Scenario & " μ", fundGrowth!$B$1:$J$1, 0))), _xlpm.σ, _xlfn.XLOOKUP("Horizon", fundGrowth!$A$2:$A$4, INDEX(fundGrowth!$B$2:$J$4,0, MATCH(_xlpm.Scenario & " σ", fundGrowth!$B$1:$J$1, 0))), _xlpm.ρ, _xlfn.XLOOKUP("Horizon", fundGrowth!$A$2:$A$4, INDEX(fundGrowth!$B$2:$J$4,0, MATCH(_xlpm.Scenario & " ρ", fundGrowth!$B$1:$J$1, 0))), _xlpm.μ_prev, _xlfn.XLOOKUP("Horizon", fundGrowth!$A$2:$A$4, INDEX(fundGrowth!$B$2:$J$4,0, MATCH(_xlpm.pre_scenario & " μ", fundGrowth!$B$1:$J$1, 0))), _xlpm.μ + _xlpm.ρ*(MAX(J5, -0.05)-_xlpm.μ_prev) + _xlpm.σ * _xlpm.ε )} -> 0.015874884 | K6: {=_xlfn.LET( _xlpm.ε, (_xlfn.BETA.INV(RAND(), 5, 5) - 0.5) * 2, _xlpm.Scenario,H6, _xlpm.pre_scenario,H5, _xlpm.μ, _xlfn.XLOOKUP("SkyHigh", fundGrowth!$A$2:$A$4, INDEX(fundGrowth!$B$2:$J$4,0, MATCH(_xlpm.Scenario & " μ", fundGrowth!$B$1:$J$1, 0))), _xlpm.σ, _xlfn.XLOOKUP("SkyHigh", fundGrowth!$A$2:$A$4, INDEX(fundGrowth!$B$2:$J$4,0, MATCH(_xlpm.Scenario & " σ", fundGrowth!$B$1:$J$1, 0))), _xlpm.ρ, _xlfn.XLOOKUP("SkyHigh", fundGrowth!$A$2:$A$4, INDEX(fundGrowth!$B$2:$J$4,0, MATCH(_xlpm.Scenario & " ρ", fundGrowth!$B$1:$J$1, 0))), _xlpm.μ_prev, _xlfn.XLOOKUP("SkyHigh", fundGrowth!$A$2:$A$4, INDEX(fundGrowth!$B$2:$J$4,0, MATCH(_xlpm.pre_scenario & " μ", fundGrowth!$B$1:$J$1, 0))), _xlpm.μ + _xlpm.ρ*(MAX(K5, -0.07)-_xlpm.μ_prev) + _xlpm.σ * _xlpm.ε )} -> 0.081035543 | L6: =0.4*I6+0.3*J6+0.3*K6 -> 0.056440897 | M6: =(M5+G6)*(1+L6)*(1-28%) -> 10586.79 | N6: =M6*Q6 -> 9775.5343 | O6: =N6+D6*Q6 -> 65308.652 | P6: {=_xlfn.LET( _xlpm.state, H6, _xlpm.last, P5, _xlpm.μ, IF(RAND() < 0.001, 6% + 1.5% * _xlfn.NORM.S.INV(RAND()), _xlfn.BETA.INV(RAND(), 1.19, 1.22, 0.003, 0.04) ), _xlpm.ρ_min, _xlfn.IFS(_xlpm.state="Boom", 0.61, _xlpm.state="Normal", 0.34, _xlpm.state="Recession", 0.2), _xlpm.ρ_max, _xlfn.IFS(_xlpm.state="Boom", 0.8, _xlpm.state="Normal", 0.6, _xlpm.state="Recession", 0.33), _xlpm.α, _xlfn.IFS(_xlpm.state="Boom", 3, _xlpm.state="Normal", 2, _xlpm.state="Recession", 2), _xlpm.β, _xlfn.IFS(_xlpm.state="Boom", 2, _xlpm.state="Normal", 2, _xlpm.state="Recession", 3), _xlpm.ρ, _xlfn.BETA.INV(RAND(), _xlpm.α, _xlpm.β, _xlpm.ρ_min, _xlpm.ρ_max), _xlpm.ε, _xlfn.NORM.S.INV(RAND()), _xlpm.μ + _xlpm.ρ * (_xlpm.last - _xlpm.μ) + 0 * _xlpm.ε + MAX(0,_xlfn.IFS(A5=49,-_xlfn.NORM.INV(RAND(), 0.01, 0.005), A5=57,ABS(_xlfn.NORM.INV(RAND(), 0.02, 0.01)),TRUE,0)) )} -> 0.015333959 | Q6: =Q5/(1+P6) -> 0.92337097 | S6: {=_xlfn.LET( _xlpm.KS_rate, $V$2 + 3%, _xlpm.ESCT_rate, 3%, _xlpm.W_HS, $V$3, _xlpm.W_HR, $V$4, _xlpm.W_SH, $V$5, _xlpm.salary, C6, _xlpm.salary_with_employer, _xlpm.salary + _xlpm.salary * _xlpm.ESCT_rate, _xlpm.esct, _xlpm.salary * _xlpm.ESCT_rate * _xlfn.IFS( _xlpm.salary_with_employer <= 18720, 10.5%, _xlpm.salary_with_employer <= 64200, 17.5%, _xlpm.salary_with_employer <= 93720, 30%, _xlpm.salary_with_employer <= 216000, 33%, _xlpm.salary_with_employer > 216000, 39% ), _xlpm.ks_contrib, _xlpm.salary * _xlpm.KS_rate - _xlpm.esct + 521.43, _xlpm.return_rate, _xlpm.W_HS * I6 + _xlpm.W_HR * J6 + _xlpm.W_SH * K6, _xlpm.net_growth, (1 + _xlpm.return_rate) * (1 - 28%), _xlpm.prev_value, S5, _xlpm.result, (_xlpm.prev_value + _xlpm.ks_contrib) * _xlpm.net_growth, _xlpm.result )} -> 23402.045 | T6: {=_xlfn.LET( _xlpm.KS_rate, $V$2 + 3%, _xlpm.ESCT_rate, 3%, _xlpm.W_HS, $V$3, _xlpm.W_HR, $V$4, _xlpm.W_SH, $V$5, _xlpm.salary, C6, _xlpm.salary_with_employer, _xlpm.salary + _xlpm.salary * _xlpm.ESCT_rate, _xlpm.esct, _xlpm.salary * _xlpm.ESCT_rate * _xlfn.IFS( _xlpm.salary_with_employer <= 18720, 10.5%, _xlpm.salary_with_employer <= 64200, 17.5%, _xlpm.salary_with_employer <= 93720, 30%, _xlpm.salary_with_employer <= 216000, 33%, _xlpm.salary_with_employer > 216000, 39% ), _xlpm.ks_contrib, _xlpm.salary * _xlpm.KS_rate - _xlpm.esct + 521.43, _xlpm.return_rate, _xlpm.W_HS * I6 + _xlpm.W_HR * J6 + _xlpm.W_SH * K6, _xlpm.net_growth, (1 + _xlpm.return_rate) * (1 - 28%), _xlpm.prev_value, IF(ROW()=2, 0, S5), _xlpm.base, IF(ROW()=2, _xlpm.ks_contrib, _xlpm.prev_value + _xlpm.ks_contrib ), _xlpm.current_value, _xlpm.base * _xlpm.net_growth, _xlpm.real_value, _xlpm.current_value * Q6, _xlpm.real_value )} -> 21608.769 | X6: {=_xlfn.LET( _xlpm.KS_rate, Dashboard!$Q$2 + 3%, _xlpm.ESCT_rate, 3%, _xlpm.W_HS, _xlfn.SWITCH(H5, "Recession", Dashboard!$Q$4, "Normal", Dashboard!$Q$8, "Boom", Dashboard!$Q$12 ), _xlpm.W_HR, _xlfn.SWITCH(H5, "Recession", Dashboard!$Q$5, "Normal", Dashboard!$Q$9, "Boom", Dashboard!$Q$13 ), _xlpm.W_SH, _xlfn.SWITCH(H5, "Recession", Dashboard!$Q$6, "Normal", Dashboard!$Q$10, "Boom", Dashboard!$Q$14 ), _xlpm.salary, C6, _xlpm.salary_with_employer, _xlpm.salary + _xlpm.salary * _xlpm.ESCT_rate, _xlpm.esct, _xlpm.salary * _xlpm.ESCT_rate * _xlfn.IFS( _xlpm.salary_with_employer <= 18720, 10.5%, _xlpm.salary_with_employer <= 64200, 17.5%, _xlpm.salary_with_employer <= 93720, 30%, _xlpm.salary_with_employer <= 216000, 33%, _xlpm.salary_with_employer > 216000, 39% ), _xlpm.ks_contrib, _xlpm.salary * _xlpm.KS_rate - _xlpm.esct + 521.43, _xlpm.return_rate, _xlpm.W_HS * I6 + _xlpm.W_HR * J6 + _xlpm.W_SH * K6, _xlpm.net_growth, (1 + _xlpm.return_rate) * (1 - 28%), _xlpm.prev_value, S5, _xlpm.result, (_xlpm.prev_value + _xlpm.ks_contrib) * _xlpm.net_growth, _xlpm.result )} -> 23225.147 | Y6: {=_xlfn.LET( _xlpm.KS_rate, Dashboard!$Q$2 + 3%, _xlpm.ESCT_rate, 3%, _xlpm.W_HS, _xlfn.SWITCH(H6, "Recession", Dashboard!$Q$4, "Normal", Dashboard!$Q$8, "Boom", Dashboard!$Q$12 ), _xlpm.W_HR, _xlfn.SWITCH(H6, "Recession", Dashboard!$Q$5, "Normal", Dashboard!$Q$9, "Boom", Dashboard!$Q$13 ), _xlpm.W_SH, _xlfn.SWITCH(H6, "Recession", Dashboard!$Q$6, "Normal", Dashboard!$Q$10, "Boom", Dashboard!$Q$14 ), _xlpm.salary, C6, _xlpm.salary_with_employer, _xlpm.salary + _xlpm.salary * _xlpm.ESCT_rate, _xlpm.esct, _xlpm.salary * _xlpm.ESCT_rate * _xlfn.IFS( _xlpm.salary_with_employer <= 18720, 10.5%, _xlpm.salary_with_employer <= 64200, 17.5%, _xlpm.salary_with_employer <= 93720, 30%, _xlpm.salary_with_employer <= 216000, 33%, _xlpm.salary_with_employer > 216000, 39% ), _xlpm.ks_contrib, _xlpm.salary * _xlpm.KS_rate - _xlpm.esct + 521.43, _xlpm.return_rate, _xlpm.W_HS * I6 + _xlpm.W_HR * J6 + _xlpm.W_SH * K6, _xlpm.net_growth, (1 + _xlpm.return_rate) * (1 - 28%), _xlpm.prev_value, IF(ROW()=2, 0, X5), _xlpm.base, IF(ROW()=2, _xlpm.ks_contrib, _xlpm.prev_value + _xlpm.ks_contrib), _xlpm.current_value, _xlpm.base * _xlpm.net_growth, _xlpm.real_value, _xlpm.current_value * Q6, _xlpm.real_value )} -> 21712.815 | Z6: 80249.028 | AG6: 0.1
A7: 35 | B7: =VLOOKUP(t4_salaryGrowthevent!J7,t4_salaryGrowthevent!J:J,1,FALSE) -> 0.03475 | C7: =VLOOKUP(t4_salaryGrowthevent!B7,t4_salaryGrowthevent!B:B,1,FALSE) -> 83037.682 | D7: {=_xlfn.LET( _xlpm.taxable, C7, _xlpm.kiwisaver,C7*0.03, _xlpm.incomeTax, _xlfn.IFS( _xlpm.taxable <= 15600, _xlpm.taxable * 10.5%, AND(_xlpm.taxable > 15600, _xlpm.taxable <= 53500), (_xlpm.taxable - 15600) * 17.5% + 15600 * 10.5%, AND(_xlpm.taxable > 53500, _xlpm.taxable <= 78100), (_xlpm.taxable - 53500) * 30% + (53500 - 15600) * 17.5% + 15600 * 10.5%, AND(_xlpm.taxable > 78100, _xlpm.taxable <= 180000), (_xlpm.taxable - 78100) * 33% + (78100 - 53500) * 30% + (53500 - 15600) * 17.5% + 15600 * 10.5%, _xlpm.taxable > 180000, (_xlpm.taxable - 180000) * 39% + (180000 - 78100) * 33% + (78100 - 53500) * 30% + (53500 - 15600) * 17.5% + 15600 * 10.5% ), _xlpm.acc, C7 * 0.0167, _xlpm.taxable - _xlpm.incomeTax - _xlpm.acc - _xlpm.kiwisaver )} -> 61879.887 | E7: =6%*C7 -> 4982.2609 | F7: {=C7 * 3% * _xlfn.IFS( C7 + C7 * 3% <= 18720, 10.5%, C7 + C7 * 3% <= 64200, 17.5%, C7 + C7 * 3% <= 93720, 30%, C7 + C7 * 3% <= 216000, 33%, C7 + C7 * 3% > 216000, 39% )} -> 747.33913 | G7: =E7-F7+521.43 -> 4756.3518 | H7: {=_xlfn.IFS( H6="Boom", CHOOSE(MATCH(RAND(), {0,0.67,1}, 1), "Normal", "Recession"), H6="Normal", CHOOSE(MATCH(RAND(), {0,0.18,0.82,1}, 1), "Boom", "Normal", "Recession"), H6="Recession", CHOOSE(MATCH(RAND(), {0,0.17,0.34,1}, 1), "Boom", "Normal", "Recession") )} -> Boom | I7: {=_xlfn.LET( _xlpm.ε, (_xlfn.BETA.INV(RAND(), 5, 5) - 0.5) * 2, _xlpm.Scenario,H7, _xlpm.pre_scenario,H6, _xlpm.μ, _xlfn.XLOOKUP("HarbourSafe", fundGrowth!$A$2:$A$4, INDEX(fundGrowth!$B$2:$J$4,0, MATCH(_xlpm.Scenario & " μ", fundGrowth!$B$1:$J$1, 0))), _xlpm.σ, _xlfn.XLOOKUP("HarbourSafe", fundGrowth!$A$2:$A$4, INDEX(fundGrowth!$B$2:$J$4,0, MATCH(_xlpm.Scenario & " σ", fundGrowth!$B$1:$J$1, 0))), _xlpm.ρ, _xlfn.XLOOKUP("HarbourSafe", fundGrowth!$A$2:$A$4, INDEX(fundGrowth!$B$2:$J$4,0, MATCH(_xlpm.Scenario & " ρ", fundGrowth!$B$1:$J$1, 0))), _xlpm.μ_prev, _xlfn.XLOOKUP("HarbourSafe", fundGrowth!$A$2:$A$4, INDEX(fundGrowth!$B$2:$J$4,0, MATCH(_xlpm.pre_scenario & " μ", fundGrowth!$B$1:$J$1, 0))), _xlpm.μ + _xlpm.ρ*(I6-_xlpm.μ_prev) + _xlpm.σ * _xlpm.ε )} -> 0.04001842 | J7: {=_xlfn.LET( _xlpm.ε, (_xlfn.BETA.INV(RAND(), 5, 5) - 0.5) * 2, _xlpm.Scenario,H7, _xlpm.pre_scenario,H6, _xlpm.μ, _xlfn.XLOOKUP("Horizon", fundGrowth!$A$2:$A$4, INDEX(fundGrowth!$B$2:$J$4,0, MATCH(_xlpm.Scenario & " μ", fundGrowth!$B$1:$J$1, 0))), _xlpm.σ, _xlfn.XLOOKUP("Horizon", fundGrowth!$A$2:$A$4, INDEX(fundGrowth!$B$2:$J$4,0, MATCH(_xlpm.Scenario & " σ", fundGrowth!$B$1:$J$1, 0))), _xlpm.ρ, _xlfn.XLOOKUP("Horizon", fundGrowth!$A$2:$A$4, INDEX(fundGrowth!$B$2:$J$4,0, MATCH(_xlpm.Scenario & " ρ", fundGrowth!$B$1:$J$1, 0))), _xlpm.μ_prev, _xlfn.XLOOKUP("Horizon", fundGrowth!$A$2:$A$4, INDEX(fundGrowth!$B$2:$J$4,0, MATCH(_xlpm.pre_scenario & " μ", fundGrowth!$B$1:$J$1, 0))), _xlpm.μ + _xlpm.ρ*(MAX(J6, -0.05)-_xlpm.μ_prev) + _xlpm.σ * _xlpm.ε )} -> -0.20483847 | K7: {=_xlfn.LET( _xlpm.ε, (_xlfn.BETA.INV(RAND(), 5, 5) - 0.5) * 2, _xlpm.Scenario,H7, _xlpm.pre_scenario,H6, _xlpm.μ, _xlfn.XLOOKUP("SkyHigh", fundGrowth!$A$2:$A$4, INDEX(fundGrowth!$B$2:$J$4,0, MATCH(_xlpm.Scenario & " μ", fundGrowth!$B$1:$J$1, 0))), _xlpm.σ, _xlfn.XLOOKUP("SkyHigh", fundGrowth!$A$2:$A$4, INDEX(fundGrowth!$B$2:$J$4,0, MATCH(_xlpm.Scenario & " σ", fundGrowth!$B$1:$J$1, 0))), _xlpm.ρ, _xlfn.XLOOKUP("SkyHigh", fundGrowth!$A$2:$A$4, INDEX(fundGrowth!$B$2:$J$4,0, MATCH(_xlpm.Scenario & " ρ", fundGrowth!$B$1:$J$1, 0))), _xlpm.μ_prev, _xlfn.XLOOKUP("SkyHigh", fundGrowth!$A$2:$A$4, INDEX(fundGrowth!$B$2:$J$4,0, MATCH(_xlpm.pre_scenario & " μ", fundGrowth!$B$1:$J$1, 0))), _xlpm.μ + _xlpm.ρ*(MAX(K6, -0.07)-_xlpm.μ_prev) + _xlpm.σ * _xlpm.ε )} -> 0.31558457 | L7: =0.4*I7+0.3*J7+0.3*K7 -> 0.049231196 | M7: =(M6+G7)*(1+L7)*(1-28%) -> 11590.922 | N7: =M7*Q7 -> 10487.493 | O7: =N7+D7*Q7 -> 66476.559 | P7: {=_xlfn.LET( _xlpm.state, H7, _xlpm.last, P6, _xlpm.μ, IF(RAND() < 0.001, 6% + 1.5% * _xlfn.NORM.S.INV(RAND()), _xlfn.BETA.INV(RAND(), 1.19, 1.22, 0.003, 0.04) ), _xlpm.ρ_min, _xlfn.IFS(_xlpm.state="Boom", 0.61, _xlpm.state="Normal", 0.34, _xlpm.state="Recession", 0.2), _xlpm.ρ_max, _xlfn.IFS(_xlpm.state="Boom", 0.8, _xlpm.state="Normal", 0.6, _xlpm.state="Recession", 0.33), _xlpm.α, _xlfn.IFS(_xlpm.state="Boom", 3, _xlpm.state="Normal", 2, _xlpm.state="Recession", 2), _xlpm.β, _xlfn.IFS(_xlpm.state="Boom", 2, _xlpm.state="Normal", 2, _xlpm.state="Recession", 3), _xlpm.ρ, _xlfn.BETA.INV(RAND(), _xlpm.α, _xlpm.β, _xlpm.ρ_min, _xlpm.ρ_max), _xlpm.ε, _xlfn.NORM.S.INV(RAND()), _xlpm.μ + _xlpm.ρ * (_xlpm.last - _xlpm.μ) + 0 * _xlpm.ε + MAX(0,_xlfn.IFS(A6=49,-_xlfn.NORM.INV(RAND(), 0.01, 0.005), A6=57,ABS(_xlfn.NORM.INV(RAND(), 0.02, 0.01)),TRUE,0)) )} -> 0.020522321 | Q7: =Q6/(1+P7) -> 0.90480233 | S7: {=_xlfn.LET( _xlpm.KS_rate, $V$2 + 3%, _xlpm.ESCT_rate, 3%, _xlpm.W_HS, $V$3, _xlpm.W_HR, $V$4, _xlpm.W_SH, $V$5, _xlpm.salary, C7, _xlpm.salary_with_employer, _xlpm.salary + _xlpm.salary * _xlpm.ESCT_rate, _xlpm.esct, _xlpm.salary * _xlpm.ESCT_rate * _xlfn.IFS( _xlpm.salary_with_employer <= 18720, 10.5%, _xlpm.salary_with_employer <= 64200, 17.5%, _xlpm.salary_with_employer <= 93720, 30%, _xlpm.salary_with_employer <= 216000, 33%, _xlpm.salary_with_employer > 216000, 39% ), _xlpm.ks_contrib, _xlpm.salary * _xlpm.KS_rate - _xlpm.esct + 521.43, _xlpm.return_rate, _xlpm.W_HS * I7 + _xlpm.W_HR * J7 + _xlpm.W_SH * K7, _xlpm.net_growth, (1 + _xlpm.return_rate) * (1 - 28%), _xlpm.prev_value, S6, _xlpm.result, (_xlpm.prev_value + _xlpm.ks_contrib) * _xlpm.net_growth, _xlpm.result )} -> 25663.297 | T7: {=_xlfn.LET( _xlpm.KS_rate, $V$2 + 3%, _xlpm.ESCT_rate, 3%, _xlpm.W_HS, $V$3, _xlpm.W_HR, $V$4, _xlpm.W_SH, $V$5, _xlpm.salary, C7, _xlpm.salary_with_employer, _xlpm.salary + _xlpm.salary * _xlpm.ESCT_rate, _xlpm.esct, _xlpm.salary * _xlpm.ESCT_rate * _xlfn.IFS( _xlpm.salary_with_employer <= 18720, 10.5%, _xlpm.salary_with_employer <= 64200, 17.5%, _xlpm.salary_with_employer <= 93720, 30%, _xlpm.salary_with_employer <= 216000, 33%, _xlpm.salary_with_employer > 216000, 39% ), _xlpm.ks_contrib, _xlpm.salary * _xlpm.KS_rate - _xlpm.esct + 521.43, _xlpm.return_rate, _xlpm.W_HS * I7 + _xlpm.W_HR * J7 + _xlpm.W_SH * K7, _xlpm.net_growth, (1 + _xlpm.return_rate) * (1 - 28%), _xlpm.prev_value, IF(ROW()=2, 0, S6), _xlpm.base, IF(ROW()=2, _xlpm.ks_contrib, _xlpm.prev_value + _xlpm.ks_contrib ), _xlpm.current_value, _xlpm.base * _xlpm.net_growth, _xlpm.real_value, _xlpm.current_value * Q7, _xlpm.real_value )} -> 23220.211 | X7: {=_xlfn.LET( _xlpm.KS_rate, Dashboard!$Q$2 + 3%, _xlpm.ESCT_rate, 3%, _xlpm.W_HS, _xlfn.SWITCH(H6, "Recession", Dashboard!$Q$4, "Normal", Dashboard!$Q$8, "Boom", Dashboard!$Q$12 ), _xlpm.W_HR, _xlfn.SWITCH(H6, "Recession", Dashboard!$Q$5, "Normal", Dashboard!$Q$9, "Boom", Dashboard!$Q$13 ), _xlpm.W_SH, _xlfn.SWITCH(H6, "Recession", Dashboard!$Q$6, "Normal", Dashboard!$Q$10, "Boom", Dashboard!$Q$14 ), _xlpm.salary, C7, _xlpm.salary_with_employer, _xlpm.salary + _xlpm.salary * _xlpm.ESCT_rate, _xlpm.esct, _xlpm.salary * _xlpm.ESCT_rate * _xlfn.IFS( _xlpm.salary_with_employer <= 18720, 10.5%, _xlpm.salary_with_employer <= 64200, 17.5%, _xlpm.salary_with_employer <= 93720, 30%, _xlpm.salary_with_employer <= 216000, 33%, _xlpm.salary_with_employer > 216000, 39% ), _xlpm.ks_contrib, _xlpm.salary * _xlpm.KS_rate - _xlpm.esct + 521.43, _xlpm.return_rate, _xlpm.W_HS * I7 + _xlpm.W_HR * J7 + _xlpm.W_SH * K7, _xlpm.net_growth, (1 + _xlpm.return_rate) * (1 - 28%), _xlpm.prev_value, S6, _xlpm.result, (_xlpm.prev_value + _xlpm.ks_contrib) * _xlpm.net_growth, _xlpm.result )} -> 25813.522 | Y7: {=_xlfn.LET( _xlpm.KS_rate, Dashboard!$Q$2 + 3%, _xlpm.ESCT_rate, 3%, _xlpm.W_HS, _xlfn.SWITCH(H7, "Recession", Dashboard!$Q$4, "Normal", Dashboard!$Q$8, "Boom", Dashboard!$Q$12 ), _xlpm.W_HR, _xlfn.SWITCH(H7, "Recession", Dashboard!$Q$5, "Normal", Dashboard!$Q$9, "Boom", Dashboard!$Q$13 ), _xlpm.W_SH, _xlfn.SWITCH(H7, "Recession", Dashboard!$Q$6, "Normal", Dashboard!$Q$10, "Boom", Dashboard!$Q$14 ), _xlpm.salary, C7, _xlpm.salary_with_employer, _xlpm.salary + _xlpm.salary * _xlpm.ESCT_rate, _xlpm.esct, _xlpm.salary * _xlpm.ESCT_rate * _xlfn.IFS( _xlpm.salary_with_employer <= 18720, 10.5%, _xlpm.salary_with_employer <= 64200, 17.5%, _xlpm.salary_with_employer <= 93720, 30%, _xlpm.salary_with_employer <= 216000, 33%, _xlpm.salary_with_employer > 216000, 39% ), _xlpm.ks_contrib, _xlpm.salary * _xlpm.KS_rate - _xlpm.esct + 521.43, _xlpm.return_rate, _xlpm.W_HS * I7 + _xlpm.W_HR * J7 + _xlpm.W_SH * K7, _xlpm.net_growth, (1 + _xlpm.return_rate) * (1 - 28%), _xlpm.prev_value, IF(ROW()=2, 0, X6), _xlpm.base, IF(ROW()=2, _xlpm.ks_contrib, _xlpm.prev_value + _xlpm.ks_contrib), _xlpm.current_value, _xlpm.base * _xlpm.net_growth, _xlpm.real_value, _xlpm.current_value * Q7, _xlpm.real_value )} -> 28963.186 | Z7: 83037.682
A8: 36 | B8: =VLOOKUP(t4_salaryGrowthevent!J8,t4_salaryGrowthevent!J:J,1,FALSE) -> 0.03475 | C8: =VLOOKUP(t4_salaryGrowthevent!B8,t4_salaryGrowthevent!B:B,1,FALSE) -> 85923.241 | D8: {=_xlfn.LET( _xlpm.taxable, C8, _xlpm.kiwisaver,C8*0.03, _xlpm.incomeTax, _xlfn.IFS( _xlpm.taxable <= 15600, _xlpm.taxable * 10.5%, AND(_xlpm.taxable > 15600, _xlpm.taxable <= 53500), (_xlpm.taxable - 15600) * 17.5% + 15600 * 10.5%, AND(_xlpm.taxable > 53500, _xlpm.taxable <= 78100), (_xlpm.taxable - 53500) * 30% + (53500 - 15600) * 17.5% + 15600 * 10.5%, AND(_xlpm.taxable > 78100, _xlpm.taxable <= 180000), (_xlpm.taxable - 78100) * 33% + (78100 - 53500) * 30% + (53500 - 15600) * 17.5% + 15600 * 10.5%, _xlpm.taxable > 180000, (_xlpm.taxable - 180000) * 39% + (180000 - 78100) * 33% + (78100 - 53500) * 30% + (53500 - 15600) * 17.5% + 15600 * 10.5% ), _xlpm.acc, C8 * 0.0167, _xlpm.taxable - _xlpm.incomeTax - _xlpm.acc - _xlpm.kiwisaver )} -> 63678.456 | E8: =6%*C8 -> 5155.3945 | F8: {=C8 * 3% * _xlfn.IFS( C8 + C8 * 3% <= 18720, 10.5%, C8 + C8 * 3% <= 64200, 17.5%, C8 + C8 * 3% <= 93720, 30%, C8 + C8 * 3% <= 216000, 33%, C8 + C8 * 3% > 216000, 39% )} -> 773.30917 | G8: =E8-F8+521.43 -> 4903.5153 | H8: {=_xlfn.IFS( H7="Boom", CHOOSE(MATCH(RAND(), {0,0.67,1}, 1), "Normal", "Recession"), H7="Normal", CHOOSE(MATCH(RAND(), {0,0.18,0.82,1}, 1), "Boom", "Normal", "Recession"), H7="Recession", CHOOSE(MATCH(RAND(), {0,0.17,0.34,1}, 1), "Boom", "Normal", "Recession") )} -> Recession | I8: {=_xlfn.LET( _xlpm.ε, (_xlfn.BETA.INV(RAND(), 5, 5) - 0.5) * 2, _xlpm.Scenario,H8, _xlpm.pre_scenario,H7, _xlpm.μ, _xlfn.XLOOKUP("HarbourSafe", fundGrowth!$A$2:$A$4, INDEX(fundGrowth!$B$2:$J$4,0, MATCH(_xlpm.Scenario & " μ", fundGrowth!$B$1:$J$1, 0))), _xlpm.σ, _xlfn.XLOOKUP("HarbourSafe", fundGrowth!$A$2:$A$4, INDEX(fundGrowth!$B$2:$J$4,0, MATCH(_xlpm.Scenario & " σ", fundGrowth!$B$1:$J$1, 0))), _xlpm.ρ, _xlfn.XLOOKUP("HarbourSafe", fundGrowth!$A$2:$A$4, INDEX(fundGrowth!$B$2:$J$4,0, MATCH(_xlpm.Scenario & " ρ", fundGrowth!$B$1:$J$1, 0))), _xlpm.μ_prev, _xlfn.XLOOKUP("HarbourSafe", fundGrowth!$A$2:$A$4, INDEX(fundGrowth!$B$2:$J$4,0, MATCH(_xlpm.pre_scenario & " μ", fundGrowth!$B$1:$J$1, 0))), _xlpm.μ + _xlpm.ρ*(I7-_xlpm.μ_prev) + _xlpm.σ * _xlpm.ε )} -> 0.024711555 | J8: {=_xlfn.LET( _xlpm.ε, (_xlfn.BETA.INV(RAND(), 5, 5) - 0.5) * 2, _xlpm.Scenario,H8, _xlpm.pre_scenario,H7, _xlpm.μ, _xlfn.XLOOKUP("Horizon", fundGrowth!$A$2:$A$4, INDEX(fundGrowth!$B$2:$J$4,0, MATCH(_xlpm.Scenario & " μ", fundGrowth!$B$1:$J$1, 0))), _xlpm.σ, _xlfn.XLOOKUP("Horizon", fundGrowth!$A$2:$A$4, INDEX(fundGrowth!$B$2:$J$4,0, MATCH(_xlpm.Scenario & " σ", fundGrowth!$B$1:$J$1, 0))), _xlpm.ρ, _xlfn.XLOOKUP("Horizon", fundGrowth!$A$2:$A$4, INDEX(fundGrowth!$B$2:$J$4,0, MATCH(_xlpm.Scenario & " ρ", fundGrowth!$B$1:$J$1, 0))), _xlpm.μ_prev, _xlfn.XLOOKUP("Horizon", fundGrowth!$A$2:$A$4, INDEX(fundGrowth!$B$2:$J$4,0, MATCH(_xlpm.pre_scenario & " μ", fundGrowth!$B$1:$J$1, 0))), _xlpm.μ + _xlpm.ρ*(MAX(J7, -0.05)-_xlpm.μ_prev) + _xlpm.σ * _xlpm.ε )} -> 0.031192976 | K8: {=_xlfn.LET( _xlpm.ε, (_xlfn.BETA.INV(RAND(), 5, 5) - 0.5) * 2, _xlpm.Scenario,H8, _xlpm.pre_scenario,H7, _xlpm.μ, _xlfn.XLOOKUP("SkyHigh", fundGrowth!$A$2:$A$4, INDEX(fundGrowth!$B$2:$J$4,0, MATCH(_xlpm.Scenario & " μ", fundGrowth!$B$1:$J$1, 0))), _xlpm.σ, _xlfn.XLOOKUP("SkyHigh", fundGrowth!$A$2:$A$4, INDEX(fundGrowth!$B$2:$J$4,0, MATCH(_xlpm.Scenario & " σ", fundGrowth!$B$1:$J$1, 0))), _xlpm.ρ, _xlfn.XLOOKUP("SkyHigh", fundGrowth!$A$2:$A$4, INDEX(fundGrowth!$B$2:$J$4,0, MATCH(_xlpm.Scenario & " ρ", fundGrowth!$B$1:$J$1, 0))), _xlpm.μ_prev, _xlfn.XLOOKUP("SkyHigh", fundGrowth!$A$2:$A$4, INDEX(fundGrowth!$B$2:$J$4,0, MATCH(_xlpm.pre_scenario & " μ", fundGrowth!$B$1:$J$1, 0))), _xlpm.μ + _xlpm.ρ*(MAX(K7, -0.07)-_xlpm.μ_prev) + _xlpm.σ * _xlpm.ε )} -> 0.015957727 | L8: =0.4*I8+0.3*J8+0.3*K8 -> 0.024029833 | M8: =(M7+G8)*(1+L8)*(1-28%) -> 12161.373 | N8: =M8*Q8 -> 10695.668 | O8: =N8+D8*Q8 -> 66699.513 | P8: {=_xlfn.LET( _xlpm.state, H8, _xlpm.last, P7, _xlpm.μ, IF(RAND() < 0.001, 6% + 1.5% * _xlfn.NORM.S.INV(RAND()), _xlfn.BETA.INV(RAND(), 1.19, 1.22, 0.003, 0.04) ), _xlpm.ρ_min, _xlfn.IFS(_xlpm.state="Boom", 0.61, _xlpm.state="Normal", 0.34, _xlpm.state="Recession", 0.2), _xlpm.ρ_max, _xlfn.IFS(_xlpm.state="Boom", 0.8, _xlpm.state="Normal", 0.6, _xlpm.state="Recession", 0.33), _xlpm.α, _xlfn.IFS(_xlpm.state="Boom", 3, _xlpm.state="Normal", 2, _xlpm.state="Recession", 2), _xlpm.β, _xlfn.IFS(_xlpm.state="Boom", 2, _xlpm.state="Normal", 2, _xlpm.state="Recession", 3), _xlpm.ρ, _xlfn.BETA.INV(RAND(), _xlpm.α, _xlpm.β, _xlpm.ρ_min, _xlpm.ρ_max), _xlpm.ε, _xlfn.NORM.S.INV(RAND()), _xlpm.μ + _xlpm.ρ * (_xlpm.last - _xlpm.μ) + 0 * _xlpm.ε + MAX(0,_xlfn.IFS(A7=49,-_xlfn.NORM.INV(RAND(), 0.01, 0.005), A7=57,ABS(_xlfn.NORM.INV(RAND(), 0.02, 0.01)),TRUE,0)) )} -> 0.028793922 | Q8: =Q7/(1+P8) -> 0.87947869 | S8: {=_xlfn.LET( _xlpm.KS_rate, $V$2 + 3%, _xlpm.ESCT_rate, 3%, _xlpm.W_HS, $V$3, _xlpm.W_HR, $V$4, _xlpm.W_SH, $V$5, _xlpm.salary, C8, _xlpm.salary_with_employer, _xlpm.salary + _xlpm.salary * _xlpm.ESCT_rate, _xlpm.esct, _xlpm.salary * _xlpm.ESCT_rate * _xlfn.IFS( _xlpm.salary_with_employer <= 18720, 10.5%, _xlpm.salary_with_employer <= 64200, 17.5%, _xlpm.salary_with_employer <= 93720, 30%, _xlpm.salary_with_employer <= 216000, 33%, _xlpm.salary_with_employer > 216000, 39% ), _xlpm.ks_contrib, _xlpm.salary * _xlpm.KS_rate - _xlpm.esct + 521.43, _xlpm.return_rate, _xlpm.W_HS * I8 + _xlpm.W_HR * J8 + _xlpm.W_SH * K8, _xlpm.net_growth, (1 + _xlpm.return_rate) * (1 - 28%), _xlpm.prev_value, S7, _xlpm.result, (_xlpm.prev_value + _xlpm.ks_contrib) * _xlpm.net_growth, _xlpm.result )} -> 26971.55 | T8: {=_xlfn.LET( _xlpm.KS_rate, $V$2 + 3%, _xlpm.ESCT_rate, 3%, _xlpm.W_HS, $V$3, _xlpm.W_HR, $V$4, _xlpm.W_SH, $V$5, _xlpm.salary, C8, _xlpm.salary_with_employer, _xlpm.salary + _xlpm.salary * _xlpm.ESCT_rate, _xlpm.esct, _xlpm.salary * _xlpm.ESCT_rate * _xlfn.IFS( _xlpm.salary_with_employer <= 18720, 10.5%, _xlpm.salary_with_employer <= 64200, 17.5%, _xlpm.salary_with_employer <= 93720, 30%, _xlpm.salary_with_employer <= 216000, 33%, _xlpm.salary_with_employer > 216000, 39% ), _xlpm.ks_contrib, _xlpm.salary * _xlpm.KS_rate - _xlpm.esct + 521.43, _xlpm.return_rate, _xlpm.W_HS * I8 + _xlpm.W_HR * J8 + _xlpm.W_SH * K8, _xlpm.net_growth, (1 + _xlpm.return_rate) * (1 - 28%), _xlpm.prev_value, IF(ROW()=2, 0, S7), _xlpm.base, IF(ROW()=2, _xlpm.ks_contrib, _xlpm.prev_value + _xlpm.ks_contrib ), _xlpm.current_value, _xlpm.base * _xlpm.net_growth, _xlpm.real_value, _xlpm.current_value * Q8, _xlpm.real_value )} -> 23720.903 | X8: {=_xlfn.LET( _xlpm.KS_rate, Dashboard!$Q$2 + 3%, _xlpm.ESCT_rate, 3%, _xlpm.W_HS, _xlfn.SWITCH(H7, "Recession", Dashboard!$Q$4, "Normal", Dashboard!$Q$8, "Boom", Dashboard!$Q$12 ), _xlpm.W_HR, _xlfn.SWITCH(H7, "Recession", Dashboard!$Q$5, "Normal", Dashboard!$Q$9, "Boom", Dashboard!$Q$13 ), _xlpm.W_SH, _xlfn.SWITCH(H7, "Recession", Dashboard!$Q$6, "Normal", Dashboard!$Q$10, "Boom", Dashboard!$Q$14 ), _xlpm.salary, C8, _xlpm.salary_with_employer, _xlpm.salary + _xlpm.salary * _xlpm.ESCT_rate, _xlpm.esct, _xlpm.salary * _xlpm.ESCT_rate * _xlfn.IFS( _xlpm.salary_with_employer <= 18720, 10.5%, _xlpm.salary_with_employer <= 64200, 17.5%, _xlpm.salary_with_employer <= 93720, 30%, _xlpm.salary_with_employer <= 216000, 33%, _xlpm.salary_with_employer > 216000, 39% ), _xlpm.ks_contrib, _xlpm.salary * _xlpm.KS_rate - _xlpm.esct + 521.43, _xlpm.return_rate, _xlpm.W_HS * I8 + _xlpm.W_HR * J8 + _xlpm.W_SH * K8, _xlpm.net_growth, (1 + _xlpm.return_rate) * (1 - 28%), _xlpm.prev_value, S7, _xlpm.result, (_xlpm.prev_value + _xlpm.ks_contrib) * _xlpm.net_growth, _xlpm.result )} -> 26758.941 | Y8: {=_xlfn.LET( _xlpm.KS_rate, Dashboard!$Q$2 + 3%, _xlpm.ESCT_rate, 3%, _xlpm.W_HS, _xlfn.SWITCH(H8, "Recession", Dashboard!$Q$4, "Normal", Dashboard!$Q$8, "Boom", Dashboard!$Q$12 ), _xlpm.W_HR, _xlfn.SWITCH(H8, "Recession", Dashboard!$Q$5, "Normal", Dashboard!$Q$9, "Boom", Dashboard!$Q$13 ), _xlpm.W_SH, _xlfn.SWITCH(H8, "Recession", Dashboard!$Q$6, "Normal", Dashboard!$Q$10, "Boom", Dashboard!$Q$14 ), _xlpm.salary, C8, _xlpm.salary_with_employer, _xlpm.salary + _xlpm.salary * _xlpm.ESCT_rate, _xlpm.esct, _xlpm.salary * _xlpm.ESCT_rate * _xlfn.IFS( _xlpm.salary_with_employer <= 18720, 10.5%, _xlpm.salary_with_employer <= 64200, 17.5%, _xlpm.salary_with_employer <= 93720, 30%, _xlpm.salary_with_employer <= 216000, 33%, _xlpm.salary_with_employer > 216000, 39% ), _xlpm.ks_contrib, _xlpm.salary * _xlpm.KS_rate - _xlpm.esct + 521.43, _xlpm.return_rate, _xlpm.W_HS * I8 + _xlpm.W_HR * J8 + _xlpm.W_SH * K8, _xlpm.net_growth, (1 + _xlpm.return_rate) * (1 - 28%), _xlpm.prev_value, IF(ROW()=2, 0, X7), _xlpm.base, IF(ROW()=2, _xlpm.ks_contrib, _xlpm.prev_value + _xlpm.ks_contrib), _xlpm.current_value, _xlpm.base * _xlpm.net_growth, _xlpm.real_value, _xlpm.current_value * Q8, _xlpm.real_value )} -> 23834.171 | Z8: 85923.241
A9: 37 | B9: =VLOOKUP(t4_salaryGrowthevent!J9,t4_salaryGrowthevent!J:J,1,FALSE) -> 0.03475 | C9: =VLOOKUP(t4_salaryGrowthevent!B9,t4_salaryGrowthevent!B:B,1,FALSE) -> 88909.074 | D9: {=_xlfn.LET( _xlpm.taxable, C9, _xlpm.kiwisaver,C9*0.03, _xlpm.incomeTax, _xlfn.IFS( _xlpm.taxable <= 15600, _xlpm.taxable * 10.5%, AND(_xlpm.taxable > 15600, _xlpm.taxable <= 53500), (_xlpm.taxable - 15600) * 17.5% + 15600 * 10.5%, AND(_xlpm.taxable > 53500, _xlpm.taxable <= 78100), (_xlpm.taxable - 53500) * 30% + (53500 - 15600) * 17.5% + 15600 * 10.5%, AND(_xlpm.taxable > 78100, _xlpm.taxable <= 180000), (_xlpm.taxable - 78100) * 33% + (78100 - 53500) * 30% + (53500 - 15600) * 17.5% + 15600 * 10.5%, _xlpm.taxable > 180000, (_xlpm.taxable - 180000) * 39% + (180000 - 78100) * 33% + (78100 - 53500) * 30% + (53500 - 15600) * 17.5% + 15600 * 10.5% ), _xlpm.acc, C9 * 0.0167, _xlpm.taxable - _xlpm.incomeTax - _xlpm.acc - _xlpm.kiwisaver )} -> 65539.526 | E9: =6%*C9 -> 5334.5444 | F9: {=C9 * 3% * _xlfn.IFS( C9 + C9 * 3% <= 18720, 10.5%, C9 + C9 * 3% <= 64200, 17.5%, C9 + C9 * 3% <= 93720, 30%, C9 + C9 * 3% <= 216000, 33%, C9 + C9 * 3% > 216000, 39% )} -> 800.18166 | G9: =E9-F9+521.43 -> 5055.7928 | H9: {=_xlfn.IFS( H8="Boom", CHOOSE(MATCH(RAND(), {0,0.67,1}, 1), "Normal", "Recession"), H8="Normal", CHOOSE(MATCH(RAND(), {0,0.18,0.82,1}, 1), "Boom", "Normal", "Recession"), H8="Recession", CHOOSE(MATCH(RAND(), {0,0.17,0.34,1}, 1), "Boom", "Normal", "Recession") )} -> Boom | I9: {=_xlfn.LET( _xlpm.ε, (_xlfn.BETA.INV(RAND(), 5, 5) - 0.5) * 2, _xlpm.Scenario,H9, _xlpm.pre_scenario,H8, _xlpm.μ, _xlfn.XLOOKUP("HarbourSafe", fundGrowth!$A$2:$A$4, INDEX(fundGrowth!$B$2:$J$4,0, MATCH(_xlpm.Scenario & " μ", fundGrowth!$B$1:$J$1, 0))), _xlpm.σ, _xlfn.XLOOKUP("HarbourSafe", fundGrowth!$A$2:$A$4, INDEX(fundGrowth!$B$2:$J$4,0, MATCH(_xlpm.Scenario & " σ", fundGrowth!$B$1:$J$1, 0))), _xlpm.ρ, _xlfn.XLOOKUP("HarbourSafe", fundGrowth!$A$2:$A$4, INDEX(fundGrowth!$B$2:$J$4,0, MATCH(_xlpm.Scenario & " ρ", fundGrowth!$B$1:$J$1, 0))), _xlpm.μ_prev, _xlfn.XLOOKUP("HarbourSafe", fundGrowth!$A$2:$A$4, INDEX(fundGrowth!$B$2:$J$4,0, MATCH(_xlpm.pre_scenario & " μ", fundGrowth!$B$1:$J$1, 0))), _xlpm.μ + _xlpm.ρ*(I8-_xlpm.μ_prev) + _xlpm.σ * _xlpm.ε )} -> 0.042525932 | J9: {=_xlfn.LET( _xlpm.ε, (_xlfn.BETA.INV(RAND(), 5, 5) - 0.5) * 2, _xlpm.Scenario,H9, _xlpm.pre_scenario,H8, _xlpm.μ, _xlfn.XLOOKUP("Horizon", fundGrowth!$A$2:$A$4, INDEX(fundGrowth!$B$2:$J$4,0, MATCH(_xlpm.Scenario & " μ", fundGrowth!$B$1:$J$1, 0))), _xlpm.σ, _xlfn.XLOOKUP("Horizon", fundGrowth!$A$2:$A$4, INDEX(fundGrowth!$B$2:$J$4,0, MATCH(_xlpm.Scenario & " σ", fundGrowth!$B$1:$J$1, 0))), _xlpm.ρ, _xlfn.XLOOKUP("Horizon", fundGrowth!$A$2:$A$4, INDEX(fundGrowth!$B$2:$J$4,0, MATCH(_xlpm.Scenario & " ρ", fundGrowth!$B$1:$J$1, 0))), _xlpm.μ_prev, _xlfn.XLOOKUP("Horizon", fundGrowth!$A$2:$A$4, INDEX(fundGrowth!$B$2:$J$4,0, MATCH(_xlpm.pre_scenario & " μ", fundGrowth!$B$1:$J$1, 0))), _xlpm.μ + _xlpm.ρ*(MAX(J8, -0.05)-_xlpm.μ_prev) + _xlpm.σ * _xlpm.ε )} -> -0.22709441 | K9: {=_xlfn.LET( _xlpm.ε, (_xlfn.BETA.INV(RAND(), 5, 5) - 0.5) * 2, _xlpm.Scenario,H9, _xlpm.pre_scenario,H8, _xlpm.μ, _xlfn.XLOOKUP("SkyHigh", fundGrowth!$A$2:$A$4, INDEX(fundGrowth!$B$2:$J$4,0, MATCH(_xlpm.Scenario & " μ", fundGrowth!$B$1:$J$1, 0))), _xlpm.σ, _xlfn.XLOOKUP("SkyHigh", fundGrowth!$A$2:$A$4, INDEX(fundGrowth!$B$2:$J$4,0, MATCH(_xlpm.Scenario & " σ", fundGrowth!$B$1:$J$1, 0))), _xlpm.ρ, _xlfn.XLOOKUP("SkyHigh", fundGrowth!$A$2:$A$4, INDEX(fundGrowth!$B$2:$J$4,0, MATCH(_xlpm.Scenario & " ρ", fundGrowth!$B$1:$J$1, 0))), _xlpm.μ_prev, _xlfn.XLOOKUP("SkyHigh", fundGrowth!$A$2:$A$4, INDEX(fundGrowth!$B$2:$J$4,0, MATCH(_xlpm.pre_scenario & " μ", fundGrowth!$B$1:$J$1, 0))), _xlpm.μ + _xlpm.ρ*(MAX(K8, -0.07)-_xlpm.μ_prev) + _xlpm.σ * _xlpm.ε )} -> 0.17926641 | L9: =0.4*I9+0.3*J9+0.3*K9 -> 0.0026619706 | M9: =(M8+G9)*(1+L9)*(1-28%) -> 12429.358 | N9: =M9*Q9 -> 10605.625 | O9: =N9+D9*Q9 -> 66528.675 | P9: {=_xlfn.LET( _xlpm.state, H9, _xlpm.last, P8, _xlpm.μ, IF(RAND() < 0.001, 6% + 1.5% * _xlfn.NORM.S.INV(RAND()), _xlfn.BETA.INV(RAND(), 1.19, 1.22, 0.003, 0.04) ), _xlpm.ρ_min, _xlfn.IFS(_xlpm.state="Boom", 0.61, _xlpm.state="Normal", 0.34, _xlpm.state="Recession", 0.2), _xlpm.ρ_max, _xlfn.IFS(_xlpm.state="Boom", 0.8, _xlpm.state="Normal", 0.6, _xlpm.state="Recession", 0.33), _xlpm.α, _xlfn.IFS(_xlpm.state="Boom", 3, _xlpm.state="Normal", 2, _xlpm.state="Recession", 2), _xlpm.β, _xlfn.IFS(_xlpm.state="Boom", 2, _xlpm.state="Normal", 2, _xlpm.state="Recession", 3), _xlpm.ρ, _xlfn.BETA.INV(RAND(), _xlpm.α, _xlpm.β, _xlpm.ρ_min, _xlpm.ρ_max), _xlpm.ε, _xlfn.NORM.S.INV(RAND()), _xlpm.μ + _xlpm.ρ * (_xlpm.last - _xlpm.μ) + 0 * _xlpm.ε + MAX(0,_xlfn.IFS(A8=49,-_xlfn.NORM.INV(RAND(), 0.01, 0.005), A8=57,ABS(_xlfn.NORM.INV(RAND(), 0.02, 0.01)),TRUE,0)) )} -> 0.03071302 | Q9: =Q8/(1+P9) -> 0.85327212 | S9: {=_xlfn.LET( _xlpm.KS_rate, $V$2 + 3%, _xlpm.ESCT_rate, 3%, _xlpm.W_HS, $V$3, _xlpm.W_HR, $V$4, _xlpm.W_SH, $V$5, _xlpm.salary, C9, _xlpm.salary_with_employer, _xlpm.salary + _xlpm.salary * _xlpm.ESCT_rate, _xlpm.esct, _xlpm.salary * _xlpm.ESCT_rate * _xlfn.IFS( _xlpm.salary_with_employer <= 18720, 10.5%, _xlpm.salary_with_employer <= 64200, 17.5%, _xlpm.salary_with_employer <= 93720, 30%, _xlpm.salary_with_employer <= 216000, 33%, _xlpm.salary_with_employer > 216000, 39% ), _xlpm.ks_contrib, _xlpm.salary * _xlpm.KS_rate - _xlpm.esct + 521.43, _xlpm.return_rate, _xlpm.W_HS * I9 + _xlpm.W_HR * J9 + _xlpm.W_SH * K9, _xlpm.net_growth, (1 + _xlpm.return_rate) * (1 - 28%), _xlpm.prev_value, S8, _xlpm.result, (_xlpm.prev_value + _xlpm.ks_contrib) * _xlpm.net_growth, _xlpm.result )} -> 27614.016 | T9: {=_xlfn.LET( _xlpm.KS_rate, $V$2 + 3%, _xlpm.ESCT_rate, 3%, _xlpm.W_HS, $V$3, _xlpm.W_HR, $V$4, _xlpm.W_SH, $V$5, _xlpm.salary, C9, _xlpm.salary_with_employer, _xlpm.salary + _xlpm.salary * _xlpm.ESCT_rate, _xlpm.esct, _xlpm.salary * _xlpm.ESCT_rate * _xlfn.IFS( _xlpm.salary_with_employer <= 18720, 10.5%, _xlpm.salary_with_employer <= 64200, 17.5%, _xlpm.salary_with_employer <= 93720, 30%, _xlpm.salary_with_employer <= 216000, 33%, _xlpm.salary_with_employer > 216000, 39% ), _xlpm.ks_contrib, _xlpm.salary * _xlpm.KS_rate - _xlpm.esct + 521.43, _xlpm.return_rate, _xlpm.W_HS * I9 + _xlpm.W_HR * J9 + _xlpm.W_SH * K9, _xlpm.net_growth, (1 + _xlpm.return_rate) * (1 - 28%), _xlpm.prev_value, IF(ROW()=2, 0, S8), _xlpm.base, IF(ROW()=2, _xlpm.ks_contrib, _xlpm.prev_value + _xlpm.ks_contrib ), _xlpm.current_value, _xlpm.base * _xlpm.net_growth, _xlpm.real_value, _xlpm.current_value * Q9, _xlpm.real_value )} -> 23562.27 | X9: {=_xlfn.LET( _xlpm.KS_rate, Dashboard!$Q$2 + 3%, _xlpm.ESCT_rate, 3%, _xlpm.W_HS, _xlfn.SWITCH(H8, "Recession", Dashboard!$Q$4, "Normal", Dashboard!$Q$8, "Boom", Dashboard!$Q$12 ), _xlpm.W_HR, _xlfn.SWITCH(H8, "Recession", Dashboard!$Q$5, "Normal", Dashboard!$Q$9, "Boom", Dashboard!$Q$13 ), _xlpm.W_SH, _xlfn.SWITCH(H8, "Recession", Dashboard!$Q$6, "Normal", Dashboard!$Q$10, "Boom", Dashboard!$Q$14 ), _xlpm.salary, C9, _xlpm.salary_with_employer, _xlpm.salary + _xlpm.salary * _xlpm.ESCT_rate, _xlpm.esct, _xlpm.salary * _xlpm.ESCT_rate * _xlfn.IFS( _xlpm.salary_with_employer <= 18720, 10.5%, _xlpm.salary_with_employer <= 64200, 17.5%, _xlpm.salary_with_employer <= 93720, 30%, _xlpm.salary_with_employer <= 216000, 33%, _xlpm.salary_with_employer > 216000, 39% ), _xlpm.ks_contrib, _xlpm.salary * _xlpm.KS_rate - _xlpm.esct + 521.43, _xlpm.return_rate, _xlpm.W_HS * I9 + _xlpm.W_HR * J9 + _xlpm.W_SH * K9, _xlpm.net_growth, (1 + _xlpm.return_rate) * (1 - 28%), _xlpm.prev_value, S8, _xlpm.result, (_xlpm.prev_value + _xlpm.ks_contrib) * _xlpm.net_growth, _xlpm.result )} -> 28711.898 | Y9: {=_xlfn.LET( _xlpm.KS_rate, Dashboard!$Q$2 + 3%, _xlpm.ESCT_rate, 3%, _xlpm.W_HS, _xlfn.SWITCH(H9, "Recession", Dashboard!$Q$4, "Normal", Dashboard!$Q$8, "Boom", Dashboard!$Q$12 ), _xlpm.W_HR, _xlfn.SWITCH(H9, "Recession", Dashboard!$Q$5, "Normal", Dashboard!$Q$9, "Boom", Dashboard!$Q$13 ), _xlpm.W_SH, _xlfn.SWITCH(H9, "Recession", Dashboard!$Q$6, "Normal", Dashboard!$Q$10, "Boom", Dashboard!$Q$14 ), _xlpm.salary, C9, _xlpm.salary_with_employer, _xlpm.salary + _xlpm.salary * _xlpm.ESCT_rate, _xlpm.esct, _xlpm.salary * _xlpm.ESCT_rate * _xlfn.IFS( _xlpm.salary_with_employer <= 18720, 10.5%, _xlpm.salary_with_employer <= 64200, 17.5%, _xlpm.salary_with_employer <= 93720, 30%, _xlpm.salary_with_employer <= 216000, 33%, _xlpm.salary_with_employer > 216000, 39% ), _xlpm.ks_contrib, _xlpm.salary * _xlpm.KS_rate - _xlpm.esct + 521.43, _xlpm.return_rate, _xlpm.W_HS * I9 + _xlpm.W_HR * J9 + _xlpm.W_SH * K9, _xlpm.net_growth, (1 + _xlpm.return_rate) * (1 - 28%), _xlpm.prev_value, IF(ROW()=2, 0, X8), _xlpm.base, IF(ROW()=2, _xlpm.ks_contrib, _xlpm.prev_value + _xlpm.ks_contrib), _xlpm.current_value, _xlpm.base * _xlpm.net_growth, _xlpm.real_value, _xlpm.current_value * Q9, _xlpm.real_value )} -> 27558.392 | Z9: 88909.074
A10: 38 | B10: =VLOOKUP(t4_salaryGrowthevent!J10,t4_salaryGrowthevent!J:J,1,FALSE) -> 0.03475 | C10: =VLOOKUP(t4_salaryGrowthevent!B10,t4_salaryGrowthevent!B:B,1,FALSE) -> 91998.664 | D10: {=_xlfn.LET( _xlpm.taxable, C10, _xlpm.kiwisaver,C10*0.03, _xlpm.incomeTax, _xlfn.IFS( _xlpm.taxable <= 15600, _xlpm.taxable * 10.5%, AND(_xlpm.taxable > 15600, _xlpm.taxable <= 53500), (_xlpm.taxable - 15600) * 17.5% + 15600 * 10.5%, AND(_xlpm.taxable > 53500, _xlpm.taxable <= 78100), (_xlpm.taxable - 53500) * 30% + (53500 - 15600) * 17.5% + 15600 * 10.5%, AND(_xlpm.taxable > 78100, _xlpm.taxable <= 180000), (_xlpm.taxable - 78100) * 33% + (78100 - 53500) * 30% + (53500 - 15600) * 17.5% + 15600 * 10.5%, _xlpm.taxable > 180000, (_xlpm.taxable - 180000) * 39% + (180000 - 78100) * 33% + (78100 - 53500) * 30% + (53500 - 15600) * 17.5% + 15600 * 10.5% ), _xlpm.acc, C10 * 0.0167, _xlpm.taxable - _xlpm.incomeTax - _xlpm.acc - _xlpm.kiwisaver )} -> 67465.267 | E10: =6%*C10 -> 5519.9198 | F10: {=C10 * 3% * _xlfn.IFS( C10 + C10 * 3% <= 18720, 10.5%, C10 + C10 * 3% <= 64200, 17.5%, C10 + C10 * 3% <= 93720, 30%, C10 + C10 * 3% <= 216000, 33%, C10 + C10 * 3% > 216000, 39% )} -> 910.78677 | G10: =E10-F10+521.43 -> 5130.5631 | H10: {=_xlfn.IFS( H9="Boom", CHOOSE(MATCH(RAND(), {0,0.67,1}, 1), "Normal", "Recession"), H9="Normal", CHOOSE(MATCH(RAND(), {0,0.18,0.82,1}, 1), "Boom", "Normal", "Recession"), H9="Recession", CHOOSE(MATCH(RAND(), {0,0.17,0.34,1}, 1), "Boom", "Normal", "Recession") )} -> Recession | I10: {=_xlfn.LET( _xlpm.ε, (_xlfn.BETA.INV(RAND(), 5, 5) - 0.5) * 2, _xlpm.Scenario,H10, _xlpm.pre_scenario,H9, _xlpm.μ, _xlfn.XLOOKUP("HarbourSafe", fundGrowth!$A$2:$A$4, INDEX(fundGrowth!$B$2:$J$4,0, MATCH(_xlpm.Scenario & " μ", fundGrowth!$B$1:$J$1, 0))), _xlpm.σ, _xlfn.XLOOKUP("HarbourSafe", fundGrowth!$A$2:$A$4, INDEX(fundGrowth!$B$2:$J$4,0, MATCH(_xlpm.Scenario & " σ", fundGrowth!$B$1:$J$1, 0))), _xlpm.ρ, _xlfn.XLOOKUP("HarbourSafe", fundGrowth!$A$2:$A$4, INDEX(fundGrowth!$B$2:$J$4,0, MATCH(_xlpm.Scenario & " ρ", fundGrowth!$B$1:$J$1, 0))), _xlpm.μ_prev, _xlfn.XLOOKUP("HarbourSafe", fundGrowth!$A$2:$A$4, INDEX(fundGrowth!$B$2:$J$4,0, MATCH(_xlpm.pre_scenario & " μ", fundGrowth!$B$1:$J$1, 0))), _xlpm.μ + _xlpm.ρ*(I9-_xlpm.μ_prev) + _xlpm.σ * _xlpm.ε )} -> 0.025460597 | J10: {=_xlfn.LET( _xlpm.ε, (_xlfn.BETA.INV(RAND(), 5, 5) - 0.5) * 2, _xlpm.Scenario,H10, _xlpm.pre_scenario,H9, _xlpm.μ, _xlfn.XLOOKUP("Horizon", fundGrowth!$A$2:$A$4, INDEX(fundGrowth!$B$2:$J$4,0, MATCH(_xlpm.Scenario & " μ", fundGrowth!$B$1:$J$1, 0))), _xlpm.σ, _xlfn.XLOOKUP("Horizon", fundGrowth!$A$2:$A$4, INDEX(fundGrowth!$B$2:$J$4,0, MATCH(_xlpm.Scenario & " σ", fundGrowth!$B$1:$J$1, 0))), _xlpm.ρ, _xlfn.XLOOKUP("Horizon", fundGrowth!$A$2:$A$4, INDEX(fundGrowth!$B$2:$J$4,0, MATCH(_xlpm.Scenario & " ρ", fundGrowth!$B$1:$J$1, 0))), _xlpm.μ_prev, _xlfn.XLOOKUP("Horizon", fundGrowth!$A$2:$A$4, INDEX(fundGrowth!$B$2:$J$4,0, MATCH(_xlpm.pre_scenario & " μ", fundGrowth!$B$1:$J$1, 0))), _xlpm.μ + _xlpm.ρ*(MAX(J9, -0.05)-_xlpm.μ_prev) + _xlpm.σ * _xlpm.ε )} -> -0.0055270243 | K10: {=_xlfn.LET( _xlpm.ε, (_xlfn.BETA.INV(RAND(), 5, 5) - 0.5) * 2, _xlpm.Scenario,H10, _xlpm.pre_scenario,H9, _xlpm.μ, _xlfn.XLOOKUP("SkyHigh", fundGrowth!$A$2:$A$4, INDEX(fundGrowth!$B$2:$J$4,0, MATCH(_xlpm.Scenario & " μ", fundGrowth!$B$1:$J$1, 0))), _xlpm.σ, _xlfn.XLOOKUP("SkyHigh", fundGrowth!$A$2:$A$4, INDEX(fundGrowth!$B$2:$J$4,0, MATCH(_xlpm.Scenario & " σ", fundGrowth!$B$1:$J$1, 0))), _xlpm.ρ, _xlfn.XLOOKUP("SkyHigh", fundGrowth!$A$2:$A$4, INDEX(fundGrowth!$B$2:$J$4,0, MATCH(_xlpm.Scenario & " ρ", fundGrowth!$B$1:$J$1, 0))), _xlpm.μ_prev, _xlfn.XLOOKUP("SkyHigh", fundGrowth!$A$2:$A$4, INDEX(fundGrowth!$B$2:$J$4,0, MATCH(_xlpm.pre_scenario & " μ", fundGrowth!$B$1:$J$1, 0))), _xlpm.μ + _xlpm.ρ*(MAX(K9, -0.07)-_xlpm.μ_prev) + _xlpm.σ * _xlpm.ε )} -> -0.10694804 | L10: =0.4*I10+0.3*J10+0.3*K10 -> -0.02355828 | M10: =(M9+G10)*(1+L10)*(1-28%) -> 12345.293 | N10: =M10*Q10 -> 10207.387 | O10: =N10+D10*Q10 -> 65989.306 | P10: {=_xlfn.LET( _xlpm.state, H10, _xlpm.last, P9, _xlpm.μ, IF(RAND() < 0.001, 6% + 1.5% * _xlfn.NORM.S.INV(RAND()), _xlfn.BETA.INV(RAND(), 1.19, 1.22, 0.003, 0.04) ), _xlpm.ρ_min, _xlfn.IFS(_xlpm.state="Boom", 0.61, _xlpm.state="Normal", 0.34, _xlpm.state="Recession", 0.2), _xlpm.ρ_max, _xlfn.IFS(_xlpm.state="Boom", 0.8, _xlpm.state="Normal", 0.6, _xlpm.state="Recession", 0.33), _xlpm.α, _xlfn.IFS(_xlpm.state="Boom", 3, _xlpm.state="Normal", 2, _xlpm.state="Recession", 2), _xlpm.β, _xlfn.IFS(_xlpm.state="Boom", 2, _xlpm.state="Normal", 2, _xlpm.state="Recession", 3), _xlpm.ρ, _xlfn.BETA.INV(RAND(), _xlpm.α, _xlpm.β, _xlpm.ρ_min, _xlpm.ρ_max), _xlpm.ε, _xlfn.NORM.S.INV(RAND()), _xlpm.μ + _xlpm.ρ * (_xlpm.last - _xlpm.μ) + 0 * _xlpm.ε + MAX(0,_xlfn.IFS(A9=49,-_xlfn.NORM.INV(RAND(), 0.01, 0.005), A9=57,ABS(_xlfn.NORM.INV(RAND(), 0.02, 0.01)),TRUE,0)) )} -> 0.031987301 | Q10: =Q9/(1+P10) -> 0.82682425 | S10: {=_xlfn.LET( _xlpm.KS_rate, $V$2 + 3%, _xlpm.ESCT_rate, 3%, _xlpm.W_HS, $V$3, _xlpm.W_HR, $V$4, _xlpm.W_SH, $V$5, _xlpm.salary, C10, _xlpm.salary_with_employer, _xlpm.salary + _xlpm.salary * _xlpm.ESCT_rate, _xlpm.esct, _xlpm.salary * _xlpm.ESCT_rate * _xlfn.IFS( _xlpm.salary_with_employer <= 18720, 10.5%, _xlpm.salary_with_employer <= 64200, 17.5%, _xlpm.salary_with_employer <= 93720, 30%, _xlpm.salary_with_employer <= 216000, 33%, _xlpm.salary_with_employer > 216000, 39% ), _xlpm.ks_contrib, _xlpm.salary * _xlpm.KS_rate - _xlpm.esct + 521.43, _xlpm.return_rate, _xlpm.W_HS * I10 + _xlpm.W_HR * J10 + _xlpm.W_SH * K10, _xlpm.net_growth, (1 + _xlpm.return_rate) * (1 - 28%), _xlpm.prev_value, S9, _xlpm.result, (_xlpm.prev_value + _xlpm.ks_contrib) * _xlpm.net_growth, _xlpm.result )} -> 27548.184 | T10: {=_xlfn.LET( _xlpm.KS_rate, $V$2 + 3%, _xlpm.ESCT_rate, 3%, _xlpm.W_HS, $V$3, _xlpm.W_HR, $V$4, _xlpm.W_SH, $V$5, _xlpm.salary, C10, _xlpm.salary_with_employer, _xlpm.salary + _xlpm.salary * _xlpm.ESCT_rate, _xlpm.esct, _xlpm.salary * _xlpm.ESCT_rate * _xlfn.IFS( _xlpm.salary_with_employer <= 18720, 10.5%, _xlpm.salary_with_employer <= 64200, 17.5%, _xlpm.salary_with_employer <= 93720, 30%, _xlpm.salary_with_employer <= 216000, 33%, _xlpm.salary_with_employer > 216000, 39% ), _xlpm.ks_contrib, _xlpm.salary * _xlpm.KS_rate - _xlpm.esct + 521.43, _xlpm.return_rate, _xlpm.W_HS * I10 + _xlpm.W_HR * J10 + _xlpm.W_SH * K10, _xlpm.net_growth, (1 + _xlpm.return_rate) * (1 - 28%), _xlpm.prev_value, IF(ROW()=2, 0, S9), _xlpm.base, IF(ROW()=2, _xlpm.ks_contrib, _xlpm.prev_value + _xlpm.ks_contrib ), _xlpm.current_value, _xlpm.base * _xlpm.net_growth, _xlpm.real_value, _xlpm.current_value * Q10, _xlpm.real_value )} -> 22777.507 | X10: {=_xlfn.LET( _xlpm.KS_rate, Dashboard!$Q$2 + 3%, _xlpm.ESCT_rate, 3%, _xlpm.W_HS, _xlfn.SWITCH(H9, "Recession", Dashboard!$Q$4, "Normal", Dashboard!$Q$8, "Boom", Dashboard!$Q$12 ), _xlpm.W_HR, _xlfn.SWITCH(H9, "Recession", Dashboard!$Q$5, "Normal", Dashboard!$Q$9, "Boom", Dashboard!$Q$13 ), _xlpm.W_SH, _xlfn.SWITCH(H9, "Recession", Dashboard!$Q$6, "Normal", Dashboard!$Q$10, "Boom", Dashboard!$Q$14 ), _xlpm.salary, C10, _xlpm.salary_with_employer, _xlpm.salary + _xlpm.salary * _xlpm.ESCT_rate, _xlpm.esct, _xlpm.salary * _xlpm.ESCT_rate * _xlfn.IFS( _xlpm.salary_with_employer <= 18720, 10.5%, _xlpm.salary_with_employer <= 64200, 17.5%, _xlpm.salary_with_employer <= 93720, 30%, _xlpm.salary_with_employer <= 216000, 33%, _xlpm.salary_with_employer > 216000, 39% ), _xlpm.ks_contrib, _xlpm.salary * _xlpm.KS_rate - _xlpm.esct + 521.43, _xlpm.return_rate, _xlpm.W_HS * I10 + _xlpm.W_HR * J10 + _xlpm.W_SH * K10, _xlpm.net_growth, (1 + _xlpm.return_rate) * (1 - 28%), _xlpm.prev_value, S9, _xlpm.result, (_xlpm.prev_value + _xlpm.ks_contrib) * _xlpm.net_growth, _xlpm.result )} -> 25195.523 | Y10: {=_xlfn.LET( _xlpm.KS_rate, Dashboard!$Q$2 + 3%, _xlpm.ESCT_rate, 3%, _xlpm.W_HS, _xlfn.SWITCH(H10, "Recession", Dashboard!$Q$4, "Normal", Dashboard!$Q$8, "Boom", Dashboard!$Q$12 ), _xlpm.W_HR, _xlfn.SWITCH(H10, "Recession", Dashboard!$Q$5, "Normal", Dashboard!$Q$9, "Boom", Dashboard!$Q$13 ), _xlpm.W_SH, _xlfn.SWITCH(H10, "Recession", Dashboard!$Q$6, "Normal", Dashboard!$Q$10, "Boom", Dashboard!$Q$14 ), _xlpm.salary, C10, _xlpm.salary_with_employer, _xlpm.salary + _xlpm.salary * _xlpm.ESCT_rate, _xlpm.esct, _xlpm.salary * _xlpm.ESCT_rate * _xlfn.IFS( _xlpm.salary_with_employer <= 18720, 10.5%, _xlpm.salary_with_employer <= 64200, 17.5%, _xlpm.salary_with_employer <= 93720, 30%, _xlpm.salary_with_employer <= 216000, 33%, _xlpm.salary_with_employer > 216000, 39% ), _xlpm.ks_contrib, _xlpm.salary * _xlpm.KS_rate - _xlpm.esct + 521.43, _xlpm.return_rate, _xlpm.W_HS * I10 + _xlpm.W_HR * J10 + _xlpm.W_SH * K10, _xlpm.net_growth, (1 + _xlpm.return_rate) * (1 - 28%), _xlpm.prev_value, IF(ROW()=2, 0, X9), _xlpm.base, IF(ROW()=2, _xlpm.ks_contrib, _xlpm.prev_value + _xlpm.ks_contrib), _xlpm.current_value, _xlpm.base * _xlpm.net_growth, _xlpm.real_value, _xlpm.current_value * Q10, _xlpm.real_value )} -> 24591.197 | Z10: 91998.664
A11: 39 | B11: =VLOOKUP(t4_salaryGrowthevent!J11,t4_salaryGrowthevent!J:J,1,FALSE) -> 0.03475 | C11: =VLOOKUP(t4_salaryGrowthevent!B11,t4_salaryGrowthevent!B:B,1,FALSE) -> 95195.618 | D11: {=_xlfn.LET( _xlpm.taxable, C11, _xlpm.kiwisaver,C11*0.03, _xlpm.incomeTax, _xlfn.IFS( _xlpm.taxable <= 15600, _xlpm.taxable * 10.5%, AND(_xlpm.taxable > 15600, _xlpm.taxable <= 53500), (_xlpm.taxable - 15600) * 17.5% + 15600 * 10.5%, AND(_xlpm.taxable > 53500, _xlpm.taxable <= 78100), (_xlpm.taxable - 53500) * 30% + (53500 - 15600) * 17.5% + 15600 * 10.5%, AND(_xlpm.taxable > 78100, _xlpm.taxable <= 180000), (_xlpm.taxable - 78100) * 33% + (78100 - 53500) * 30% + (53500 - 15600) * 17.5% + 15600 * 10.5%, _xlpm.taxable > 180000, (_xlpm.taxable - 180000) * 39% + (180000 - 78100) * 33% + (78100 - 53500) * 30% + (53500 - 15600) * 17.5% + 15600 * 10.5% ), _xlpm.acc, C11 * 0.0167, _xlpm.taxable - _xlpm.incomeTax - _xlpm.acc - _xlpm.kiwisaver )} -> 69457.928 | E11: =6%*C11 -> 5711.7371 | F11: {=C11 * 3% * _xlfn.IFS( C11 + C11 * 3% <= 18720, 10.5%, C11 + C11 * 3% <= 64200, 17.5%, C11 + C11 * 3% <= 93720, 30%, C11 + C11 * 3% <= 216000, 33%, C11 + C11 * 3% > 216000, 39% )} -> 942.43661 | G11: =E11-F11+521.43 -> 5290.7304 | H11: {=_xlfn.IFS( H10="Boom", CHOOSE(MATCH(RAND(), {0,0.67,1}, 1), "Normal", "Recession"), H10="Normal", CHOOSE(MATCH(RAND(), {0,0.18,0.82,1}, 1), "Boom", "Normal", "Recession"), H10="Recession", CHOOSE(MATCH(RAND(), {0,0.17,0.34,1}, 1), "Boom", "Normal", "Recession") )} -> Boom | I11: {=_xlfn.LET( _xlpm.ε, (_xlfn.BETA.INV(RAND(), 5, 5) - 0.5) * 2, _xlpm.Scenario,H11, _xlpm.pre_scenario,H10, _xlpm.μ, _xlfn.XLOOKUP("HarbourSafe", fundGrowth!$A$2:$A$4, INDEX(fundGrowth!$B$2:$J$4,0, MATCH(_xlpm.Scenario & " μ", fundGrowth!$B$1:$J$1, 0))), _xlpm.σ, _xlfn.XLOOKUP("HarbourSafe", fundGrowth!$A$2:$A$4, INDEX(fundGrowth!$B$2:$J$4,0, MATCH(_xlpm.Scenario & " σ", fundGrowth!$B$1:$J$1, 0))), _xlpm.ρ, _xlfn.XLOOKUP("HarbourSafe", fundGrowth!$A$2:$A$4, INDEX(fundGrowth!$B$2:$J$4,0, MATCH(_xlpm.Scenario & " ρ", fundGrowth!$B$1:$J$1, 0))), _xlpm.μ_prev, _xlfn.XLOOKUP("HarbourSafe", fundGrowth!$A$2:$A$4, INDEX(fundGrowth!$B$2:$J$4,0, MATCH(_xlpm.pre_scenario & " μ", fundGrowth!$B$1:$J$1, 0))), _xlpm.μ + _xlpm.ρ*(I10-_xlpm.μ_prev) + _xlpm.σ * _xlpm.ε )} -> 0.047499583 | J11: {=_xlfn.LET( _xlpm.ε, (_xlfn.BETA.INV(RAND(), 5, 5) - 0.5) * 2, _xlpm.Scenario,H11, _xlpm.pre_scenario,H10, _xlpm.μ, _xlfn.XLOOKUP("Horizon", fundGrowth!$A$2:$A$4, INDEX(fundGrowth!$B$2:$J$4,0, MATCH(_xlpm.Scenario & " μ", fundGrowth!$B$1:$J$1, 0))), _xlpm.σ, _xlfn.XLOOKUP("Horizon", fundGrowth!$A$2:$A$4, INDEX(fundGrowth!$B$2:$J$4,0, MATCH(_xlpm.Scenario & " σ", fundGrowth!$B$1:$J$1, 0))), _xlpm.ρ, _xlfn.XLOOKUP("Horizon", fundGrowth!$A$2:$A$4, INDEX(fundGrowth!$B$2:$J$4,0, MATCH(_xlpm.Scenario & " ρ", fundGrowth!$B$1:$J$1, 0))), _xlpm.μ_prev, _xlfn.XLOOKUP("Horizon", fundGrowth!$A$2:$A$4, INDEX(fundGrowth!$B$2:$J$4,0, MATCH(_xlpm.pre_scenario & " μ", fundGrowth!$B$1:$J$1, 0))), _xlpm.μ + _xlpm.ρ*(MAX(J10, -0.05)-_xlpm.μ_prev) + _xlpm.σ * _xlpm.ε )} -> 0.11544261 | K11: {=_xlfn.LET( _xlpm.ε, (_xlfn.BETA.INV(RAND(), 5, 5) - 0.5) * 2, _xlpm.Scenario,H11, _xlpm.pre_scenario,H10, _xlpm.μ, _xlfn.XLOOKUP("SkyHigh", fundGrowth!$A$2:$A$4, INDEX(fundGrowth!$B$2:$J$4,0, MATCH(_xlpm.Scenario & " μ", fundGrowth!$B$1:$J$1, 0))), _xlpm.σ, _xlfn.XLOOKUP("SkyHigh", fundGrowth!$A$2:$A$4, INDEX(fundGrowth!$B$2:$J$4,0, MATCH(_xlpm.Scenario & " σ", fundGrowth!$B$1:$J$1, 0))), _xlpm.ρ, _xlfn.XLOOKUP("SkyHigh", fundGrowth!$A$2:$A$4, INDEX(fundGrowth!$B$2:$J$4,0, MATCH(_xlpm.Scenario & " ρ", fundGrowth!$B$1:$J$1, 0))), _xlpm.μ_prev, _xlfn.XLOOKUP("SkyHigh", fundGrowth!$A$2:$A$4, INDEX(fundGrowth!$B$2:$J$4,0, MATCH(_xlpm.pre_scenario & " μ", fundGrowth!$B$1:$J$1, 0))), _xlpm.μ + _xlpm.ρ*(MAX(K10, -0.07)-_xlpm.μ_prev) + _xlpm.σ * _xlpm.ε )} -> 0.24450705 | L11: =0.4*I11+0.3*J11+0.3*K11 -> 0.12698473 | M11: =(M10+G11)*(1+L11)*(1-28%) -> 14310.381 | N11: =M11*Q11 -> 11492.701 | O11: =N11+D11*Q11 -> 67274.531 | P11: {=_xlfn.LET( _xlpm.state, H11, _xlpm.last, P10, _xlpm.μ, IF(RAND() < 0.001, 6% + 1.5% * _xlfn.NORM.S.INV(RAND()), _xlfn.BETA.INV(RAND(), 1.19, 1.22, 0.003, 0.04) ), _xlpm.ρ_min, _xlfn.IFS(_xlpm.state="Boom", 0.61, _xlpm.state="Normal", 0.34, _xlpm.state="Recession", 0.2), _xlpm.ρ_max, _xlfn.IFS(_xlpm.state="Boom", 0.8, _xlpm.state="Normal", 0.6, _xlpm.state="Recession", 0.33), _xlpm.α, _xlfn.IFS(_xlpm.state="Boom", 3, _xlpm.state="Normal", 2, _xlpm.state="Recession", 2), _xlpm.β, _xlfn.IFS(_xlpm.state="Boom", 2, _xlpm.state="Normal", 2, _xlpm.state="Recession", 3), _xlpm.ρ, _xlfn.BETA.INV(RAND(), _xlpm.α, _xlpm.β, _xlpm.ρ_min, _xlpm.ρ_max), _xlpm.ε, _xlfn.NORM.S.INV(RAND()), _xlpm.μ + _xlpm.ρ * (_xlpm.last - _xlpm.μ) + 0 * _xlpm.ε + MAX(0,_xlfn.IFS(A10=49,-_xlfn.NORM.INV(RAND(), 0.01, 0.005), A10=57,ABS(_xlfn.NORM.INV(RAND(), 0.02, 0.01)),TRUE,0)) )} -> 0.029537749 | Q11: =Q10/(1+P11) -> 0.80310241 | S11: {=_xlfn.LET( _xlpm.KS_rate, $V$2 + 3%, _xlpm.ESCT_rate, 3%, _xlpm.W_HS, $V$3, _xlpm.W_HR, $V$4, _xlpm.W_SH, $V$5, _xlpm.salary, C11, _xlpm.salary_with_employer, _xlpm.salary + _xlpm.salary * _xlpm.ESCT_rate, _xlpm.esct, _xlpm.salary * _xlpm.ESCT_rate * _xlfn.IFS( _xlpm.salary_with_employer <= 18720, 10.5%, _xlpm.salary_with_employer <= 64200, 17.5%, _xlpm.salary_with_employer <= 93720, 30%, _xlpm.salary_with_employer <= 216000, 33%, _xlpm.salary_with_employer > 216000, 39% ), _xlpm.ks_contrib, _xlpm.salary * _xlpm.KS_rate - _xlpm.esct + 521.43, _xlpm.return_rate, _xlpm.W_HS * I11 + _xlpm.W_HR * J11 + _xlpm.W_SH * K11, _xlpm.net_growth, (1 + _xlpm.return_rate) * (1 - 28%), _xlpm.prev_value, S10, _xlpm.result, (_xlpm.prev_value + _xlpm.ks_contrib) * _xlpm.net_growth, _xlpm.result )} -> 32053.562 | T11: {=_xlfn.LET( _xlpm.KS_rate, $V$2 + 3%, _xlpm.ESCT_rate, 3%, _xlpm.W_HS, $V$3, _xlpm.W_HR, $V$4, _xlpm.W_SH, $V$5, _xlpm.salary, C11, _xlpm.salary_with_employer, _xlpm.salary + _xlpm.salary * _xlpm.ESCT_rate, _xlpm.esct, _xlpm.salary * _xlpm.ESCT_rate * _xlfn.IFS( _xlpm.salary_with_employer <= 18720, 10.5%, _xlpm.salary_with_employer <= 64200, 17.5%, _xlpm.salary_with_employer <= 93720, 30%, _xlpm.salary_with_employer <= 216000, 33%, _xlpm.salary_with_employer > 216000, 39% ), _xlpm.ks_contrib, _xlpm.salary * _xlpm.KS_rate - _xlpm.esct + 521.43, _xlpm.return_rate, _xlpm.W_HS * I11 + _xlpm.W_HR * J11 + _xlpm.W_SH * K11, _xlpm.net_growth, (1 + _xlpm.return_rate) * (1 - 28%), _xlpm.prev_value, IF(ROW()=2, 0, S10), _xlpm.base, IF(ROW()=2, _xlpm.ks_contrib, _xlpm.prev_value + _xlpm.ks_contrib ), _xlpm.current_value, _xlpm.base * _xlpm.net_growth, _xlpm.real_value, _xlpm.current_value * Q11, _xlpm.real_value )} -> 25742.293 | X11: {=_xlfn.LET( _xlpm.KS_rate, Dashboard!$Q$2 + 3%, _xlpm.ESCT_rate, 3%, _xlpm.W_HS, _xlfn.SWITCH(H10, "Recession", Dashboard!$Q$4, "Normal", Dashboard!$Q$8, "Boom", Dashboard!$Q$12 ), _xlpm.W_HR, _xlfn.SWITCH(H10, "Recession", Dashboard!$Q$5, "Normal", Dashboard!$Q$9, "Boom", Dashboard!$Q$13 ), _xlpm.W_SH, _xlfn.SWITCH(H10, "Recession", Dashboard!$Q$6, "Normal", Dashboard!$Q$10, "Boom", Dashboard!$Q$14 ), _xlpm.salary, C11, _xlpm.salary_with_employer, _xlpm.salary + _xlpm.salary * _xlpm.ESCT_rate, _xlpm.esct, _xlpm.salary * _xlpm.ESCT_rate * _xlfn.IFS( _xlpm.salary_with_employer <= 18720, 10.5%, _xlpm.salary_with_employer <= 64200, 17.5%, _xlpm.salary_with_employer <= 93720, 30%, _xlpm.salary_with_employer <= 216000, 33%, _xlpm.salary_with_employer > 216000, 39% ), _xlpm.ks_contrib, _xlpm.salary * _xlpm.KS_rate - _xlpm.esct + 521.43, _xlpm.return_rate, _xlpm.W_HS * I11 + _xlpm.W_HR * J11 + _xlpm.W_SH * K11, _xlpm.net_growth, (1 + _xlpm.return_rate) * (1 - 28%), _xlpm.prev_value, S10, _xlpm.result, (_xlpm.prev_value + _xlpm.ks_contrib) * _xlpm.net_growth, _xlpm.result )} -> 29792.855 | Y11: {=_xlfn.LET( _xlpm.KS_rate, Dashboard!$Q$2 + 3%, _xlpm.ESCT_rate, 3%, _xlpm.W_HS, _xlfn.SWITCH(H11, "Recession", Dashboard!$Q$4, "Normal", Dashboard!$Q$8, "Boom", Dashboard!$Q$12 ), _xlpm.W_HR, _xlfn.SWITCH(H11, "Recession", Dashboard!$Q$5, "Normal", Dashboard!$Q$9, "Boom", Dashboard!$Q$13 ), _xlpm.W_SH, _xlfn.SWITCH(H11, "Recession", Dashboard!$Q$6, "Normal", Dashboard!$Q$10, "Boom", Dashboard!$Q$14 ), _xlpm.salary, C11, _xlpm.salary_with_employer, _xlpm.salary + _xlpm.salary * _xlpm.ESCT_rate, _xlpm.esct, _xlpm.salary * _xlpm.ESCT_rate * _xlfn.IFS( _xlpm.salary_with_employer <= 18720, 10.5%, _xlpm.salary_with_employer <= 64200, 17.5%, _xlpm.salary_with_employer <= 93720, 30%, _xlpm.salary_with_employer <= 216000, 33%, _xlpm.salary_with_employer > 216000, 39% ), _xlpm.ks_contrib, _xlpm.salary * _xlpm.KS_rate - _xlpm.esct + 521.43, _xlpm.return_rate, _xlpm.W_HS * I11 + _xlpm.W_HR * J11 + _xlpm.W_SH * K11, _xlpm.net_growth, (1 + _xlpm.return_rate) * (1 - 28%), _xlpm.prev_value, IF(ROW()=2, 0, X10), _xlpm.base, IF(ROW()=2, _xlpm.ks_contrib, _xlpm.prev_value + _xlpm.ks_contrib), _xlpm.current_value, _xlpm.base * _xlpm.net_growth, _xlpm.real_value, _xlpm.current_value * Q11, _xlpm.real_value )} -> 26733.695 | Z11: 95195.618
A12: 40 | B12: =VLOOKUP(t4_salaryGrowthevent!J12,t4_salaryGrowthevent!J:J,1,FALSE) -> 0.03475 | C12: =VLOOKUP(t4_salaryGrowthevent!B12,t4_salaryGrowthevent!B:B,1,FALSE) -> 98503.665 | D12: {=_xlfn.LET( _xlpm.taxable, C12, _xlpm.kiwisaver,C12*0.03, _xlpm.incomeTax, _xlfn.IFS( _xlpm.taxable <= 15600, _xlpm.taxable * 10.5%, AND(_xlpm.taxable > 15600, _xlpm.taxable <= 53500), (_xlpm.taxable - 15600) * 17.5% + 15600 * 10.5%, AND(_xlpm.taxable > 53500, _xlpm.taxable <= 78100), (_xlpm.taxable - 53500) * 30% + (53500 - 15600) * 17.5% + 15600 * 10.5%, AND(_xlpm.taxable > 78100, _xlpm.taxable <= 180000), (_xlpm.taxable - 78100) * 33% + (78100 - 53500) * 30% + (53500 - 15600) * 17.5% + 15600 * 10.5%, _xlpm.taxable > 180000, (_xlpm.taxable - 180000) * 39% + (180000 - 78100) * 33% + (78100 - 53500) * 30% + (53500 - 15600) * 17.5% + 15600 * 10.5% ), _xlpm.acc, C12 * 0.0167, _xlpm.taxable - _xlpm.incomeTax - _xlpm.acc - _xlpm.kiwisaver )} -> 71519.835 | E12: =6%*C12 -> 5910.2199 | F12: {=C12 * 3% * _xlfn.IFS( C12 + C12 * 3% <= 18720, 10.5%, C12 + C12 * 3% <= 64200, 17.5%, C12 + C12 * 3% <= 93720, 30%, C12 + C12 * 3% <= 216000, 33%, C12 + C12 * 3% > 216000, 39% )} -> 975.18629 | G12: =E12-F12+521.43 -> 5456.4636 | H12: {=_xlfn.IFS( H11="Boom", CHOOSE(MATCH(RAND(), {0,0.67,1}, 1), "Normal", "Recession"), H11="Normal", CHOOSE(MATCH(RAND(), {0,0.18,0.82,1}, 1), "Boom", "Normal", "Recession"), H11="Recession", CHOOSE(MATCH(RAND(), {0,0.17,0.34,1}, 1), "Boom", "Normal", "Recession") )} -> Recession | I12: {=_xlfn.LET( _xlpm.ε, (_xlfn.BETA.INV(RAND(), 5, 5) - 0.5) * 2, _xlpm.Scenario,H12, _xlpm.pre_scenario,H11, _xlpm.μ, _xlfn.XLOOKUP("HarbourSafe", fundGrowth!$A$2:$A$4, INDEX(fundGrowth!$B$2:$J$4,0, MATCH(_xlpm.Scenario & " μ", fundGrowth!$B$1:$J$1, 0))), _xlpm.σ, _xlfn.XLOOKUP("HarbourSafe", fundGrowth!$A$2:$A$4, INDEX(fundGrowth!$B$2:$J$4,0, MATCH(_xlpm.Scenario & " σ", fundGrowth!$B$1:$J$1, 0))), _xlpm.ρ, _xlfn.XLOOKUP("HarbourSafe", fundGrowth!$A$2:$A$4, INDEX(fundGrowth!$B$2:$J$4,0, MATCH(_xlpm.Scenario & " ρ", fundGrowth!$B$1:$J$1, 0))), _xlpm.μ_prev, _xlfn.XLOOKUP("HarbourSafe", fundGrowth!$A$2:$A$4, INDEX(fundGrowth!$B$2:$J$4,0, MATCH(_xlpm.pre_scenario & " μ", fundGrowth!$B$1:$J$1, 0))), _xlpm.μ + _xlpm.ρ*(I11-_xlpm.μ_prev) + _xlpm.σ * _xlpm.ε )} -> 0.021505288 | J12: {=_xlfn.LET( _xlpm.ε, (_xlfn.BETA.INV(RAND(), 5, 5) - 0.5) * 2, _xlpm.Scenario,H12, _xlpm.pre_scenario,H11, _xlpm.μ, _xlfn.XLOOKUP("Horizon", fundGrowth!$A$2:$A$4, INDEX(fundGrowth!$B$2:$J$4,0, MATCH(_xlpm.Scenario & " μ", fundGrowth!$B$1:$J$1, 0))), _xlpm.σ, _xlfn.XLOOKUP("Horizon", fundGrowth!$A$2:$A$4, INDEX(fundGrowth!$B$2:$J$4,0, MATCH(_xlpm.Scenario & " σ", fundGrowth!$B$1:$J$1, 0))), _xlpm.ρ, _xlfn.XLOOKUP("Horizon", fundGrowth!$A$2:$A$4, INDEX(fundGrowth!$B$2:$J$4,0, MATCH(_xlpm.Scenario & " ρ", fundGrowth!$B$1:$J$1, 0))), _xlpm.μ_prev, _xlfn.XLOOKUP("Horizon", fundGrowth!$A$2:$A$4, INDEX(fundGrowth!$B$2:$J$4,0, MATCH(_xlpm.pre_scenario & " μ", fundGrowth!$B$1:$J$1, 0))), _xlpm.μ + _xlpm.ρ*(MAX(J11, -0.05)-_xlpm.μ_prev) + _xlpm.σ * _xlpm.ε )} -> 0.061536999 | K12: {=_xlfn.LET( _xlpm.ε, (_xlfn.BETA.INV(RAND(), 5, 5) - 0.5) * 2, _xlpm.Scenario,H12, _xlpm.pre_scenario,H11, _xlpm.μ, _xlfn.XLOOKUP("SkyHigh", fundGrowth!$A$2:$A$4, INDEX(fundGrowth!$B$2:$J$4,0, MATCH(_xlpm.Scenario & " μ", fundGrowth!$B$1:$J$1, 0))), _xlpm.σ, _xlfn.XLOOKUP("SkyHigh", fundGrowth!$A$2:$A$4, INDEX(fundGrowth!$B$2:$J$4,0, MATCH(_xlpm.Scenario & " σ", fundGrowth!$B$1:$J$1, 0))), _xlpm.ρ, _xlfn.XLOOKUP("SkyHigh", fundGrowth!$A$2:$A$4, INDEX(fundGrowth!$B$2:$J$4,0, MATCH(_xlpm.Scenario & " ρ", fundGrowth!$B$1:$J$1, 0))), _xlpm.μ_prev, _xlfn.XLOOKUP("SkyHigh", fundGrowth!$A$2:$A$4, INDEX(fundGrowth!$B$2:$J$4,0, MATCH(_xlpm.pre_scenario & " μ", fundGrowth!$B$1:$J$1, 0))), _xlpm.μ + _xlpm.ρ*(MAX(K11, -0.07)-_xlpm.μ_prev) + _xlpm.σ * _xlpm.ε )} -> -0.007700678 | L12: =0.4*I12+0.3*J12+0.3*K12 -> 0.024753011 | M12: =(M11+G12)*(1+L12)*(1-28%) -> 14584.416 | N12: =M12*Q12 -> 11543.103 | O12: =N12+D12*Q12 -> 68148.783 | P12: {=_xlfn.LET( _xlpm.state, H12, _xlpm.last, P11, _xlpm.μ, IF(RAND() < 0.001, 6% + 1.5% * _xlfn.NORM.S.INV(RAND()), _xlfn.BETA.INV(RAND(), 1.19, 1.22, 0.003, 0.04) ), _xlpm.ρ_min, _xlfn.IFS(_xlpm.state="Boom", 0.61, _xlpm.state="Normal", 0.34, _xlpm.state="Recession", 0.2), _xlpm.ρ_max, _xlfn.IFS(_xlpm.state="Boom", 0.8, _xlpm.state="Normal", 0.6, _xlpm.state="Recession", 0.33), _xlpm.α, _xlfn.IFS(_xlpm.state="Boom", 3, _xlpm.state="Normal", 2, _xlpm.state="Recession", 2), _xlpm.β, _xlfn.IFS(_xlpm.state="Boom", 2, _xlpm.state="Normal", 2, _xlpm.state="Recession", 3), _xlpm.ρ, _xlfn.BETA.INV(RAND(), _xlpm.α, _xlpm.β, _xlpm.ρ_min, _xlpm.ρ_max), _xlpm.ε, _xlfn.NORM.S.INV(RAND()), _xlpm.μ + _xlpm.ρ * (_xlpm.last - _xlpm.μ) + 0 * _xlpm.ε + MAX(0,_xlfn.IFS(A11=49,-_xlfn.NORM.INV(RAND(), 0.01, 0.005), A11=57,ABS(_xlfn.NORM.INV(RAND(), 0.02, 0.01)),TRUE,0)) )} -> 0.014699418 | Q12: =Q11/(1+P12) -> 0.79146829 | S12: {=_xlfn.LET( _xlpm.KS_rate, $V$2 + 3%, _xlpm.ESCT_rate, 3%, _xlpm.W_HS, $V$3, _xlpm.W_HR, $V$4, _xlpm.W_SH, $V$5, _xlpm.salary, C12, _xlpm.salary_with_employer, _xlpm.salary + _xlpm.salary * _xlpm.ESCT_rate, _xlpm.esct, _xlpm.salary * _xlpm.ESCT_rate * _xlfn.IFS( _xlpm.salary_with_employer <= 18720, 10.5%, _xlpm.salary_with_employer <= 64200, 17.5%, _xlpm.salary_with_employer <= 93720, 30%, _xlpm.salary_with_employer <= 216000, 33%, _xlpm.salary_with_employer > 216000, 39% ), _xlpm.ks_contrib, _xlpm.salary * _xlpm.KS_rate - _xlpm.esct + 521.43, _xlpm.return_rate, _xlpm.W_HS * I12 + _xlpm.W_HR * J12 + _xlpm.W_SH * K12, _xlpm.net_growth, (1 + _xlpm.return_rate) * (1 - 28%), _xlpm.prev_value, S11, _xlpm.result, (_xlpm.prev_value + _xlpm.ks_contrib) * _xlpm.net_growth, _xlpm.result )} -> 32763.201 | T12: {=_xlfn.LET( _xlpm.KS_rate, $V$2 + 3%, _xlpm.ESCT_rate, 3%, _xlpm.W_HS, $V$3, _xlpm.W_HR, $V$4, _xlpm.W_SH, $V$5, _xlpm.salary, C12, _xlpm.salary_with_employer, _xlpm.salary + _xlpm.salary * _xlpm.ESCT_rate, _xlpm.esct, _xlpm.salary * _xlpm.ESCT_rate * _xlfn.IFS( _xlpm.salary_with_employer <= 18720, 10.5%, _xlpm.salary_with_employer <= 64200, 17.5%, _xlpm.salary_with_employer <= 93720, 30%, _xlpm.salary_with_employer <= 216000, 33%, _xlpm.salary_with_employer > 216000, 39% ), _xlpm.ks_contrib, _xlpm.salary * _xlpm.KS_rate - _xlpm.esct + 521.43, _xlpm.return_rate, _xlpm.W_HS * I12 + _xlpm.W_HR * J12 + _xlpm.W_SH * K12, _xlpm.net_growth, (1 + _xlpm.return_rate) * (1 - 28%), _xlpm.prev_value, IF(ROW()=2, 0, S11), _xlpm.base, IF(ROW()=2, _xlpm.ks_contrib, _xlpm.prev_value + _xlpm.ks_contrib ), _xlpm.current_value, _xlpm.base * _xlpm.net_growth, _xlpm.real_value, _xlpm.current_value * Q12, _xlpm.real_value )} -> 25931.035 | X12: {=_xlfn.LET( _xlpm.KS_rate, Dashboard!$Q$2 + 3%, _xlpm.ESCT_rate, 3%, _xlpm.W_HS, _xlfn.SWITCH(H11, "Recession", Dashboard!$Q$4, "Normal", Dashboard!$Q$8, "Boom", Dashboard!$Q$12 ), _xlpm.W_HR, _xlfn.SWITCH(H11, "Recession", Dashboard!$Q$5, "Normal", Dashboard!$Q$9, "Boom", Dashboard!$Q$13 ), _xlpm.W_SH, _xlfn.SWITCH(H11, "Recession", Dashboard!$Q$6, "Normal", Dashboard!$Q$10, "Boom", Dashboard!$Q$14 ), _xlpm.salary, C12, _xlpm.salary_with_employer, _xlpm.salary + _xlpm.salary * _xlpm.ESCT_rate, _xlpm.esct, _xlpm.salary * _xlpm.ESCT_rate * _xlfn.IFS( _xlpm.salary_with_employer <= 18720, 10.5%, _xlpm.salary_with_employer <= 64200, 17.5%, _xlpm.salary_with_employer <= 93720, 30%, _xlpm.salary_with_employer <= 216000, 33%, _xlpm.salary_with_employer > 216000, 39% ), _xlpm.ks_contrib, _xlpm.salary * _xlpm.KS_rate - _xlpm.esct + 521.43, _xlpm.return_rate, _xlpm.W_HS * I12 + _xlpm.W_HR * J12 + _xlpm.W_SH * K12, _xlpm.net_growth, (1 + _xlpm.return_rate) * (1 - 28%), _xlpm.prev_value, S11, _xlpm.result, (_xlpm.prev_value + _xlpm.ks_contrib) * _xlpm.net_growth, _xlpm.result )} -> 31725.598 | Y12: {=_xlfn.LET( _xlpm.KS_rate, Dashboard!$Q$2 + 3%, _xlpm.ESCT_rate, 3%, _xlpm.W_HS, _xlfn.SWITCH(H12, "Recession", Dashboard!$Q$4, "Normal", Dashboard!$Q$8, "Boom", Dashboard!$Q$12 ), _xlpm.W_HR, _xlfn.SWITCH(H12, "Recession", Dashboard!$Q$5, "Normal", Dashboard!$Q$9, "Boom", Dashboard!$Q$13 ), _xlpm.W_SH, _xlfn.SWITCH(H12, "Recession", Dashboard!$Q$6, "Normal", Dashboard!$Q$10, "Boom", Dashboard!$Q$14 ), _xlpm.salary, C12, _xlpm.salary_with_employer, _xlpm.salary + _xlpm.salary * _xlpm.ESCT_rate, _xlpm.esct, _xlpm.salary * _xlpm.ESCT_rate * _xlfn.IFS( _xlpm.salary_with_employer <= 18720, 10.5%, _xlpm.salary_with_employer <= 64200, 17.5%, _xlpm.salary_with_employer <= 93720, 30%, _xlpm.salary_with_employer <= 216000, 33%, _xlpm.salary_with_employer > 216000, 39% ), _xlpm.ks_contrib, _xlpm.salary * _xlpm.KS_rate - _xlpm.esct + 521.43, _xlpm.return_rate, _xlpm.W_HS * I12 + _xlpm.W_HR * J12 + _xlpm.W_SH * K12, _xlpm.net_growth, (1 + _xlpm.return_rate) * (1 - 28%), _xlpm.prev_value, IF(ROW()=2, 0, X11), _xlpm.base, IF(ROW()=2, _xlpm.ks_contrib, _xlpm.prev_value + _xlpm.ks_contrib), _xlpm.current_value, _xlpm.base * _xlpm.net_growth, _xlpm.real_value, _xlpm.current_value * Q12, _xlpm.real_value )} -> 24532.867 | Z12: 98503.665
A13: 41 | B13: =VLOOKUP(t4_salaryGrowthevent!J13,t4_salaryGrowthevent!J:J,1,FALSE) -> 0.03475 | C13: =VLOOKUP(t4_salaryGrowthevent!B13,t4_salaryGrowthevent!B:B,1,FALSE) -> 101926.67 | D13: {=_xlfn.LET( _xlpm.taxable, C13, _xlpm.kiwisaver,C13*0.03, _xlpm.incomeTax, _xlfn.IFS( _xlpm.taxable <= 15600, _xlpm.taxable * 10.5%, AND(_xlpm.taxable > 15600, _xlpm.taxable <= 53500), (_xlpm.taxable - 15600) * 17.5% + 15600 * 10.5%, AND(_xlpm.taxable > 53500, _xlpm.taxable <= 78100), (_xlpm.taxable - 53500) * 30% + (53500 - 15600) * 17.5% + 15600 * 10.5%, AND(_xlpm.taxable > 78100, _xlpm.taxable <= 180000), (_xlpm.taxable - 78100) * 33% + (78100 - 53500) * 30% + (53500 - 15600) * 17.5% + 15600 * 10.5%, _xlpm.taxable > 180000, (_xlpm.taxable - 180000) * 39% + (180000 - 78100) * 33% + (78100 - 53500) * 30% + (53500 - 15600) * 17.5% + 15600 * 10.5% ), _xlpm.acc, C13 * 0.0167, _xlpm.taxable - _xlpm.incomeTax - _xlpm.acc - _xlpm.kiwisaver )} -> 73653.392 | E13: =6%*C13 -> 6115.6001 | F13: {=C13 * 3% * _xlfn.IFS( C13 + C13 * 3% <= 18720, 10.5%, C13 + C13 * 3% <= 64200, 17.5%, C13 + C13 * 3% <= 93720, 30%, C13 + C13 * 3% <= 216000, 33%, C13 + C13 * 3% > 216000, 39% )} -> 1009.074 | G13: =E13-F13+521.43 -> 5627.956 | H13: {=_xlfn.IFS( H12="Boom", CHOOSE(MATCH(RAND(), {0,0.67,1}, 1), "Normal", "Recession"), H12="Normal", CHOOSE(MATCH(RAND(), {0,0.18,0.82,1}, 1), "Boom", "Normal", "Recession"), H12="Recession", CHOOSE(MATCH(RAND(), {0,0.17,0.34,1}, 1), "Boom", "Normal", "Recession") )} -> Normal | I13: {=_xlfn.LET( _xlpm.ε, (_xlfn.BETA.INV(RAND(), 5, 5) - 0.5) * 2, _xlpm.Scenario,H13, _xlpm.pre_scenario,H12, _xlpm.μ, _xlfn.XLOOKUP("HarbourSafe", fundGrowth!$A$2:$A$4, INDEX(fundGrowth!$B$2:$J$4,0, MATCH(_xlpm.Scenario & " μ", fundGrowth!$B$1:$J$1, 0))), _xlpm.σ, _xlfn.XLOOKUP("HarbourSafe", fundGrowth!$A$2:$A$4, INDEX(fundGrowth!$B$2:$J$4,0, MATCH(_xlpm.Scenario & " σ", fundGrowth!$B$1:$J$1, 0))), _xlpm.ρ, _xlfn.XLOOKUP("HarbourSafe", fundGrowth!$A$2:$A$4, INDEX(fundGrowth!$B$2:$J$4,0, MATCH(_xlpm.Scenario & " ρ", fundGrowth!$B$1:$J$1, 0))), _xlpm.μ_prev, _xlfn.XLOOKUP("HarbourSafe", fundGrowth!$A$2:$A$4, INDEX(fundGrowth!$B$2:$J$4,0, MATCH(_xlpm.pre_scenario & " μ", fundGrowth!$B$1:$J$1, 0))), _xlpm.μ + _xlpm.ρ*(I12-_xlpm.μ_prev) + _xlpm.σ * _xlpm.ε )} -> 0.024618251 | J13: {=_xlfn.LET( _xlpm.ε, (_xlfn.BETA.INV(RAND(), 5, 5) - 0.5) * 2, _xlpm.Scenario,H13, _xlpm.pre_scenario,H12, _xlpm.μ, _xlfn.XLOOKUP("Horizon", fundGrowth!$A$2:$A$4, INDEX(fundGrowth!$B$2:$J$4,0, MATCH(_xlpm.Scenario & " μ", fundGrowth!$B$1:$J$1, 0))), _xlpm.σ, _xlfn.XLOOKUP("Horizon", fundGrowth!$A$2:$A$4, INDEX(fundGrowth!$B$2:$J$4,0, MATCH(_xlpm.Scenario & " σ", fundGrowth!$B$1:$J$1, 0))), _xlpm.ρ, _xlfn.XLOOKUP("Horizon", fundGrowth!$A$2:$A$4, INDEX(fundGrowth!$B$2:$J$4,0, MATCH(_xlpm.Scenario & " ρ", fundGrowth!$B$1:$J$1, 0))), _xlpm.μ_prev, _xlfn.XLOOKUP("Horizon", fundGrowth!$A$2:$A$4, INDEX(fundGrowth!$B$2:$J$4,0, MATCH(_xlpm.pre_scenario & " μ", fundGrowth!$B$1:$J$1, 0))), _xlpm.μ + _xlpm.ρ*(MAX(J12, -0.05)-_xlpm.μ_prev) + _xlpm.σ * _xlpm.ε )} -> 0.15106087 | K13: {=_xlfn.LET( _xlpm.ε, (_xlfn.BETA.INV(RAND(), 5, 5) - 0.5) * 2, _xlpm.Scenario,H13, _xlpm.pre_scenario,H12, _xlpm.μ, _xlfn.XLOOKUP("SkyHigh", fundGrowth!$A$2:$A$4, INDEX(fundGrowth!$B$2:$J$4,0, MATCH(_xlpm.Scenario & " μ", fundGrowth!$B$1:$J$1, 0))), _xlpm.σ, _xlfn.XLOOKUP("SkyHigh", fundGrowth!$A$2:$A$4, INDEX(fundGrowth!$B$2:$J$4,0, MATCH(_xlpm.Scenario & " σ", fundGrowth!$B$1:$J$1, 0))), _xlpm.ρ, _xlfn.XLOOKUP("SkyHigh", fundGrowth!$A$2:$A$4, INDEX(fundGrowth!$B$2:$J$4,0, MATCH(_xlpm.Scenario & " ρ", fundGrowth!$B$1:$J$1, 0))), _xlpm.μ_prev, _xlfn.XLOOKUP("SkyHigh", fundGrowth!$A$2:$A$4, INDEX(fundGrowth!$B$2:$J$4,0, MATCH(_xlpm.pre_scenario & " μ", fundGrowth!$B$1:$J$1, 0))), _xlpm.μ + _xlpm.ρ*(MAX(K12, -0.07)-_xlpm.μ_prev) + _xlpm.σ * _xlpm.ε )} -> 0.074190865 | L13: =0.4*I13+0.3*J13+0.3*K13 -> 0.077422819 | M13: =(M12+G13)*(1+L13)*(1-28%) -> 15679.635 | N13: =M13*Q13 -> 12137.408 | O13: =N13+D13*Q13 -> 69151.574 | P13: {=_xlfn.LET( _xlpm.state, H13, _xlpm.last, P12, _xlpm.μ, IF(RAND() < 0.001, 6% + 1.5% * _xlfn.NORM.S.INV(RAND()), _xlfn.BETA.INV(RAND(), 1.19, 1.22, 0.003, 0.04) ), _xlpm.ρ_min, _xlfn.IFS(_xlpm.state="Boom", 0.61, _xlpm.state="Normal", 0.34, _xlpm.state="Recession", 0.2), _xlpm.ρ_max, _xlfn.IFS(_xlpm.state="Boom", 0.8, _xlpm.state="Normal", 0.6, _xlpm.state="Recession", 0.33), _xlpm.α, _xlfn.IFS(_xlpm.state="Boom", 3, _xlpm.state="Normal", 2, _xlpm.state="Recession", 2), _xlpm.β, _xlfn.IFS(_xlpm.state="Boom", 2, _xlpm.state="Normal", 2, _xlpm.state="Recession", 3), _xlpm.ρ, _xlfn.BETA.INV(RAND(), _xlpm.α, _xlpm.β, _xlpm.ρ_min, _xlpm.ρ_max), _xlpm.ε, _xlfn.NORM.S.INV(RAND()), _xlpm.μ + _xlpm.ρ * (_xlpm.last - _xlpm.μ) + 0 * _xlpm.ε + MAX(0,_xlfn.IFS(A12=49,-_xlfn.NORM.INV(RAND(), 0.01, 0.005), A12=57,ABS(_xlfn.NORM.INV(RAND(), 0.02, 0.01)),TRUE,0)) )} -> 0.022453337 | Q13: =Q12/(1+P13) -> 0.77408744 | S13: {=_xlfn.LET( _xlpm.KS_rate, $V$2 + 3%, _xlpm.ESCT_rate, 3%, _xlpm.W_HS, $V$3, _xlpm.W_HR, $V$4, _xlpm.W_SH, $V$5, _xlpm.salary, C13, _xlpm.salary_with_employer, _xlpm.salary + _xlpm.salary * _xlpm.ESCT_rate, _xlpm.esct, _xlpm.salary * _xlpm.ESCT_rate * _xlfn.IFS( _xlpm.salary_with_employer <= 18720, 10.5%, _xlpm.salary_with_employer <= 64200, 17.5%, _xlpm.salary_with_employer <= 93720, 30%, _xlpm.salary_with_employer <= 216000, 33%, _xlpm.salary_with_employer > 216000, 39% ), _xlpm.ks_contrib, _xlpm.salary * _xlpm.KS_rate - _xlpm.esct + 521.43, _xlpm.return_rate, _xlpm.W_HS * I13 + _xlpm.W_HR * J13 + _xlpm.W_SH * K13, _xlpm.net_growth, (1 + _xlpm.return_rate) * (1 - 28%), _xlpm.prev_value, S12, _xlpm.result, (_xlpm.prev_value + _xlpm.ks_contrib) * _xlpm.net_growth, _xlpm.result )} -> 35316.56 | T13: {=_xlfn.LET( _xlpm.KS_rate, $V$2 + 3%, _xlpm.ESCT_rate, 3%, _xlpm.W_HS, $V$3, _xlpm.W_HR, $V$4, _xlpm.W_SH, $V$5, _xlpm.salary, C13, _xlpm.salary_with_employer, _xlpm.salary + _xlpm.salary * _xlpm.ESCT_rate, _xlpm.esct, _xlpm.salary * _xlpm.ESCT_rate * _xlfn.IFS( _xlpm.salary_with_employer <= 18720, 10.5%, _xlpm.salary_with_employer <= 64200, 17.5%, _xlpm.salary_with_employer <= 93720, 30%, _xlpm.salary_with_employer <= 216000, 33%, _xlpm.salary_with_employer > 216000, 39% ), _xlpm.ks_contrib, _xlpm.salary * _xlpm.KS_rate - _xlpm.esct + 521.43, _xlpm.return_rate, _xlpm.W_HS * I13 + _xlpm.W_HR * J13 + _xlpm.W_SH * K13, _xlpm.net_growth, (1 + _xlpm.return_rate) * (1 - 28%), _xlpm.prev_value, IF(ROW()=2, 0, S12), _xlpm.base, IF(ROW()=2, _xlpm.ks_contrib, _xlpm.prev_value + _xlpm.ks_contrib ), _xlpm.current_value, _xlpm.base * _xlpm.net_growth, _xlpm.real_value, _xlpm.current_value * Q13, _xlpm.real_value )} -> 27338.105 | X13: {=_xlfn.LET( _xlpm.KS_rate, Dashboard!$Q$2 + 3%, _xlpm.ESCT_rate, 3%, _xlpm.W_HS, _xlfn.SWITCH(H12, "Recession", Dashboard!$Q$4, "Normal", Dashboard!$Q$8, "Boom", Dashboard!$Q$12 ), _xlpm.W_HR, _xlfn.SWITCH(H12, "Recession", Dashboard!$Q$5, "Normal", Dashboard!$Q$9, "Boom", Dashboard!$Q$13 ), _xlpm.W_SH, _xlfn.SWITCH(H12, "Recession", Dashboard!$Q$6, "Normal", Dashboard!$Q$10, "Boom", Dashboard!$Q$14 ), _xlpm.salary, C13, _xlpm.salary_with_employer, _xlpm.salary + _xlpm.salary * _xlpm.ESCT_rate, _xlpm.esct, _xlpm.salary * _xlpm.ESCT_rate * _xlfn.IFS( _xlpm.salary_with_employer <= 18720, 10.5%, _xlpm.salary_with_employer <= 64200, 17.5%, _xlpm.salary_with_employer <= 93720, 30%, _xlpm.salary_with_employer <= 216000, 33%, _xlpm.salary_with_employer > 216000, 39% ), _xlpm.ks_contrib, _xlpm.salary * _xlpm.KS_rate - _xlpm.esct + 521.43, _xlpm.return_rate, _xlpm.W_HS * I13 + _xlpm.W_HR * J13 + _xlpm.W_SH * K13, _xlpm.net_growth, (1 + _xlpm.return_rate) * (1 - 28%), _xlpm.prev_value, S12, _xlpm.result, (_xlpm.prev_value + _xlpm.ks_contrib) * _xlpm.net_growth, _xlpm.result )} -> 33585.693 | Y13: {=_xlfn.LET( _xlpm.KS_rate, Dashboard!$Q$2 + 3%, _xlpm.ESCT_rate, 3%, _xlpm.W_HS, _xlfn.SWITCH(H13, "Recession", Dashboard!$Q$4, "Normal", Dashboard!$Q$8, "Boom", Dashboard!$Q$12 ), _xlpm.W_HR, _xlfn.SWITCH(H13, "Recession", Dashboard!$Q$5, "Normal", Dashboard!$Q$9, "Boom", Dashboard!$Q$13 ), _xlpm.W_SH, _xlfn.SWITCH(H13, "Recession", Dashboard!$Q$6, "Normal", Dashboard!$Q$10, "Boom", Dashboard!$Q$14 ), _xlpm.salary, C13, _xlpm.salary_with_employer, _xlpm.salary + _xlpm.salary * _xlpm.ESCT_rate, _xlpm.esct, _xlpm.salary * _xlpm.ESCT_rate * _xlfn.IFS( _xlpm.salary_with_employer <= 18720, 10.5%, _xlpm.salary_with_employer <= 64200, 17.5%, _xlpm.salary_with_employer <= 93720, 30%, _xlpm.salary_with_employer <= 216000, 33%, _xlpm.salary_with_employer > 216000, 39% ), _xlpm.ks_contrib, _xlpm.salary * _xlpm.KS_rate - _xlpm.esct + 521.43, _xlpm.return_rate, _xlpm.W_HS * I13 + _xlpm.W_HR * J13 + _xlpm.W_SH * K13, _xlpm.net_growth, (1 + _xlpm.return_rate) * (1 - 28%), _xlpm.prev_value, IF(ROW()=2, 0, X12), _xlpm.base, IF(ROW()=2, _xlpm.ks_contrib, _xlpm.prev_value + _xlpm.ks_contrib), _xlpm.current_value, _xlpm.base * _xlpm.net_growth, _xlpm.real_value, _xlpm.current_value * Q13, _xlpm.real_value )} -> 27587.901 | Z13: 101926.67
A14: 42 | B14: =VLOOKUP(t4_salaryGrowthevent!J14,t4_salaryGrowthevent!J:J,1,FALSE) -> 0.03475 | C14: =VLOOKUP(t4_salaryGrowthevent!B14,t4_salaryGrowthevent!B:B,1,FALSE) -> 105468.62 | D14: {=_xlfn.LET( _xlpm.taxable, C14, _xlpm.kiwisaver,C14*0.03, _xlpm.incomeTax, _xlfn.IFS( _xlpm.taxable <= 15600, _xlpm.taxable * 10.5%, AND(_xlpm.taxable > 15600, _xlpm.taxable <= 53500), (_xlpm.taxable - 15600) * 17.5% + 15600 * 10.5%, AND(_xlpm.taxable > 53500, _xlpm.taxable <= 78100), (_xlpm.taxable - 53500) * 30% + (53500 - 15600) * 17.5% + 15600 * 10.5%, AND(_xlpm.taxable > 78100, _xlpm.taxable <= 180000), (_xlpm.taxable - 78100) * 33% + (78100 - 53500) * 30% + (53500 - 15600) * 17.5% + 15600 * 10.5%, _xlpm.taxable > 180000, (_xlpm.taxable - 180000) * 39% + (180000 - 78100) * 33% + (78100 - 53500) * 30% + (53500 - 15600) * 17.5% + 15600 * 10.5% ), _xlpm.acc, C14 * 0.0167, _xlpm.taxable - _xlpm.incomeTax - _xlpm.acc - _xlpm.kiwisaver )} -> 75861.09 | E14: =6%*C14 -> 6328.1172 | F14: {=C14 * 3% * _xlfn.IFS( C14 + C14 * 3% <= 18720, 10.5%, C14 + C14 * 3% <= 64200, 17.5%, C14 + C14 * 3% <= 93720, 30%, C14 + C14 * 3% <= 216000, 33%, C14 + C14 * 3% > 216000, 39% )} -> 1044.1393 | G14: =E14-F14+521.43 -> 5805.4078 | H14: {=_xlfn.IFS( H13="Boom", CHOOSE(MATCH(RAND(), {0,0.67,1}, 1), "Normal", "Recession"), H13="Normal", CHOOSE(MATCH(RAND(), {0,0.18,0.82,1}, 1), "Boom", "Normal", "Recession"), H13="Recession", CHOOSE(MATCH(RAND(), {0,0.17,0.34,1}, 1), "Boom", "Normal", "Recession") )} -> Normal | I14: {=_xlfn.LET( _xlpm.ε, (_xlfn.BETA.INV(RAND(), 5, 5) - 0.5) * 2, _xlpm.Scenario,H14, _xlpm.pre_scenario,H13, _xlpm.μ, _xlfn.XLOOKUP("HarbourSafe", fundGrowth!$A$2:$A$4, INDEX(fundGrowth!$B$2:$J$4,0, MATCH(_xlpm.Scenario & " μ", fundGrowth!$B$1:$J$1, 0))), _xlpm.σ, _xlfn.XLOOKUP("HarbourSafe", fundGrowth!$A$2:$A$4, INDEX(fundGrowth!$B$2:$J$4,0, MATCH(_xlpm.Scenario & " σ", fundGrowth!$B$1:$J$1, 0))), _xlpm.ρ, _xlfn.XLOOKUP("HarbourSafe", fundGrowth!$A$2:$A$4, INDEX(fundGrowth!$B$2:$J$4,0, MATCH(_xlpm.Scenario & " ρ", fundGrowth!$B$1:$J$1, 0))), _xlpm.μ_prev, _xlfn.XLOOKUP("HarbourSafe", fundGrowth!$A$2:$A$4, INDEX(fundGrowth!$B$2:$J$4,0, MATCH(_xlpm.pre_scenario & " μ", fundGrowth!$B$1:$J$1, 0))), _xlpm.μ + _xlpm.ρ*(I13-_xlpm.μ_prev) + _xlpm.σ * _xlpm.ε )} -> 0.042524731 | J14: {=_xlfn.LET( _xlpm.ε, (_xlfn.BETA.INV(RAND(), 5, 5) - 0.5) * 2, _xlpm.Scenario,H14, _xlpm.pre_scenario,H13, _xlpm.μ, _xlfn.XLOOKUP("Horizon", fundGrowth!$A$2:$A$4, INDEX(fundGrowth!$B$2:$J$4,0, MATCH(_xlpm.Scenario & " μ", fundGrowth!$B$1:$J$1, 0))), _xlpm.σ, _xlfn.XLOOKUP("Horizon", fundGrowth!$A$2:$A$4, INDEX(fundGrowth!$B$2:$J$4,0, MATCH(_xlpm.Scenario & " σ", fundGrowth!$B$1:$J$1, 0))), _xlpm.ρ, _xlfn.XLOOKUP("Horizon", fundGrowth!$A$2:$A$4, INDEX(fundGrowth!$B$2:$J$4,0, MATCH(_xlpm.Scenario & " ρ", fundGrowth!$B$1:$J$1, 0))), _xlpm.μ_prev, _xlfn.XLOOKUP("Horizon", fundGrowth!$A$2:$A$4, INDEX(fundGrowth!$B$2:$J$4,0, MATCH(_xlpm.pre_scenario & " μ", fundGrowth!$B$1:$J$1, 0))), _xlpm.μ + _xlpm.ρ*(MAX(J13, -0.05)-_xlpm.μ_prev) + _xlpm.σ * _xlpm.ε )} -> 0.18306416 | K14: {=_xlfn.LET( _xlpm.ε, (_xlfn.BETA.INV(RAND(), 5, 5) - 0.5) * 2, _xlpm.Scenario,H14, _xlpm.pre_scenario,H13, _xlpm.μ, _xlfn.XLOOKUP("SkyHigh", fundGrowth!$A$2:$A$4, INDEX(fundGrowth!$B$2:$J$4,0, MATCH(_xlpm.Scenario & " μ", fundGrowth!$B$1:$J$1, 0))), _xlpm.σ, _xlfn.XLOOKUP("SkyHigh", fundGrowth!$A$2:$A$4, INDEX(fundGrowth!$B$2:$J$4,0, MATCH(_xlpm.Scenario & " σ", fundGrowth!$B$1:$J$1, 0))), _xlpm.ρ, _xlfn.XLOOKUP("SkyHigh", fundGrowth!$A$2:$A$4, INDEX(fundGrowth!$B$2:$J$4,0, MATCH(_xlpm.Scenario & " ρ", fundGrowth!$B$1:$J$1, 0))), _xlpm.μ_prev, _xlfn.XLOOKUP("SkyHigh", fundGrowth!$A$2:$A$4, INDEX(fundGrowth!$B$2:$J$4,0, MATCH(_xlpm.pre_scenario & " μ", fundGrowth!$B$1:$J$1, 0))), _xlpm.μ + _xlpm.ρ*(MAX(K13, -0.07)-_xlpm.μ_prev) + _xlpm.σ * _xlpm.ε )} -> 0.15427497 | L14: =0.4*I14+0.3*J14+0.3*K14 -> 0.11821163 | M14: =(M13+G14)*(1+L14)*(1-28%) -> 17297.874 | N14: =M14*Q14 -> 13188.116 | O14: =N14+D14*Q14 -> 71025.564 | P14: {=_xlfn.LET( _xlpm.state, H14, _xlpm.last, P13, _xlpm.μ, IF(RAND() < 0.001, 6% + 1.5% * _xlfn.NORM.S.INV(RAND()), _xlfn.BETA.INV(RAND(), 1.19, 1.22, 0.003, 0.04) ), _xlpm.ρ_min, _xlfn.IFS(_xlpm.state="Boom", 0.61, _xlpm.state="Normal", 0.34, _xlpm.state="Recession", 0.2), _xlpm.ρ_max, _xlfn.IFS(_xlpm.state="Boom", 0.8, _xlpm.state="Normal", 0.6, _xlpm.state="Recession", 0.33), _xlpm.α, _xlfn.IFS(_xlpm.state="Boom", 3, _xlpm.state="Normal", 2, _xlpm.state="Recession", 2), _xlpm.β, _xlfn.IFS(_xlpm.state="Boom", 2, _xlpm.state="Normal", 2, _xlpm.state="Recession", 3), _xlpm.ρ, _xlfn.BETA.INV(RAND(), _xlpm.α, _xlpm.β, _xlpm.ρ_min, _xlpm.ρ_max), _xlpm.ε, _xlfn.NORM.S.INV(RAND()), _xlpm.μ + _xlpm.ρ * (_xlpm.last - _xlpm.μ) + 0 * _xlpm.ε + MAX(0,_xlfn.IFS(A13=49,-_xlfn.NORM.INV(RAND(), 0.01, 0.005), A13=57,ABS(_xlfn.NORM.INV(RAND(), 0.02, 0.01)),TRUE,0)) )} -> 0.015313079 | Q14: =Q13/(1+P14) -> 0.76241256 | S14: {=_xlfn.LET( _xlpm.KS_rate, $V$2 + 3%, _xlpm.ESCT_rate, 3%, _xlpm.W_HS, $V$3, _xlpm.W_HR, $V$4, _xlpm.W_SH, $V$5, _xlpm.salary, C14, _xlpm.salary_with_employer, _xlpm.salary + _xlpm.salary * _xlpm.ESCT_rate, _xlpm.esct, _xlpm.salary * _xlpm.ESCT_rate * _xlfn.IFS( _xlpm.salary_with_employer <= 18720, 10.5%, _xlpm.salary_with_employer <= 64200, 17.5%, _xlpm.salary_with_employer <= 93720, 30%, _xlpm.salary_with_employer <= 216000, 33%, _xlpm.salary_with_employer > 216000, 39% ), _xlpm.ks_contrib, _xlpm.salary * _xlpm.KS_rate - _xlpm.esct + 521.43, _xlpm.return_rate, _xlpm.W_HS * I14 + _xlpm.W_HR * J14 + _xlpm.W_SH * K14, _xlpm.net_growth, (1 + _xlpm.return_rate) * (1 - 28%), _xlpm.prev_value, S13, _xlpm.result, (_xlpm.prev_value + _xlpm.ks_contrib) * _xlpm.net_growth, _xlpm.result )} -> 39051.791 | T14: {=_xlfn.LET( _xlpm.KS_rate, $V$2 + 3%, _xlpm.ESCT_rate, 3%, _xlpm.W_HS, $V$3, _xlpm.W_HR, $V$4, _xlpm.W_SH, $V$5, _xlpm.salary, C14, _xlpm.salary_with_employer, _xlpm.salary + _xlpm.salary * _xlpm.ESCT_rate, _xlpm.esct, _xlpm.salary * _xlpm.ESCT_rate * _xlfn.IFS( _xlpm.salary_with_employer <= 18720, 10.5%, _xlpm.salary_with_employer <= 64200, 17.5%, _xlpm.salary_with_employer <= 93720, 30%, _xlpm.salary_with_employer <= 216000, 33%, _xlpm.salary_with_employer > 216000, 39% ), _xlpm.ks_contrib, _xlpm.salary * _xlpm.KS_rate - _xlpm.esct + 521.43, _xlpm.return_rate, _xlpm.W_HS * I14 + _xlpm.W_HR * J14 + _xlpm.W_SH * K14, _xlpm.net_growth, (1 + _xlpm.return_rate) * (1 - 28%), _xlpm.prev_value, IF(ROW()=2, 0, S13), _xlpm.base, IF(ROW()=2, _xlpm.ks_contrib, _xlpm.prev_value + _xlpm.ks_contrib ), _xlpm.current_value, _xlpm.base * _xlpm.net_growth, _xlpm.real_value, _xlpm.current_value * Q14, _xlpm.real_value )} -> 29773.576 | X14: {=_xlfn.LET( _xlpm.KS_rate, Dashboard!$Q$2 + 3%, _xlpm.ESCT_rate, 3%, _xlpm.W_HS, _xlfn.SWITCH(H13, "Recession", Dashboard!$Q$4, "Normal", Dashboard!$Q$8, "Boom", Dashboard!$Q$12 ), _xlpm.W_HR, _xlfn.SWITCH(H13, "Recession", Dashboard!$Q$5, "Normal", Dashboard!$Q$9, "Boom", Dashboard!$Q$13 ), _xlpm.W_SH, _xlfn.SWITCH(H13, "Recession", Dashboard!$Q$6, "Normal", Dashboard!$Q$10, "Boom", Dashboard!$Q$14 ), _xlpm.salary, C14, _xlpm.salary_with_employer, _xlpm.salary + _xlpm.salary * _xlpm.ESCT_rate, _xlpm.esct, _xlpm.salary * _xlpm.ESCT_rate * _xlfn.IFS( _xlpm.salary_with_employer <= 18720, 10.5%, _xlpm.salary_with_employer <= 64200, 17.5%, _xlpm.salary_with_employer <= 93720, 30%, _xlpm.salary_with_employer <= 216000, 33%, _xlpm.salary_with_employer > 216000, 39% ), _xlpm.ks_contrib, _xlpm.salary * _xlpm.KS_rate - _xlpm.esct + 521.43, _xlpm.return_rate, _xlpm.W_HS * I14 + _xlpm.W_HR * J14 + _xlpm.W_SH * K14, _xlpm.net_growth, (1 + _xlpm.return_rate) * (1 - 28%), _xlpm.prev_value, S13, _xlpm.result, (_xlpm.prev_value + _xlpm.ks_contrib) * _xlpm.net_growth, _xlpm.result )} -> 40813.956 | Y14: {=_xlfn.LET( _xlpm.KS_rate, Dashboard!$Q$2 + 3%, _xlpm.ESCT_rate, 3%, _xlpm.W_HS, _xlfn.SWITCH(H14, "Recession", Dashboard!$Q$4, "Normal", Dashboard!$Q$8, "Boom", Dashboard!$Q$12 ), _xlpm.W_HR, _xlfn.SWITCH(H14, "Recession", Dashboard!$Q$5, "Normal", Dashboard!$Q$9, "Boom", Dashboard!$Q$13 ), _xlpm.W_SH, _xlfn.SWITCH(H14, "Recession", Dashboard!$Q$6, "Normal", Dashboard!$Q$10, "Boom", Dashboard!$Q$14 ), _xlpm.salary, C14, _xlpm.salary_with_employer, _xlpm.salary + _xlpm.salary * _xlpm.ESCT_rate, _xlpm.esct, _xlpm.salary * _xlpm.ESCT_rate * _xlfn.IFS( _xlpm.salary_with_employer <= 18720, 10.5%, _xlpm.salary_with_employer <= 64200, 17.5%, _xlpm.salary_with_employer <= 93720, 30%, _xlpm.salary_with_employer <= 216000, 33%, _xlpm.salary_with_employer > 216000, 39% ), _xlpm.ks_contrib, _xlpm.salary * _xlpm.KS_rate - _xlpm.esct + 521.43, _xlpm.return_rate, _xlpm.W_HS * I14 + _xlpm.W_HR * J14 + _xlpm.W_SH * K14, _xlpm.net_growth, (1 + _xlpm.return_rate) * (1 - 28%), _xlpm.prev_value, IF(ROW()=2, 0, X13), _xlpm.base, IF(ROW()=2, _xlpm.ks_contrib, _xlpm.prev_value + _xlpm.ks_contrib), _xlpm.current_value, _xlpm.base * _xlpm.net_growth, _xlpm.real_value, _xlpm.current_value * Q14, _xlpm.real_value )} -> 30006.676 | Z14: 105468.62
A15: 43 | B15: =VLOOKUP(t4_salaryGrowthevent!J15,t4_salaryGrowthevent!J:J,1,FALSE) -> 0.03475 | C15: =VLOOKUP(t4_salaryGrowthevent!B15,t4_salaryGrowthevent!B:B,1,FALSE) -> 109133.65 | D15: {=_xlfn.LET( _xlpm.taxable, C15, _xlpm.kiwisaver,C15*0.03, _xlpm.incomeTax, _xlfn.IFS( _xlpm.taxable <= 15600, _xlpm.taxable * 10.5%, AND(_xlpm.taxable > 15600, _xlpm.taxable <= 53500), (_xlpm.taxable - 15600) * 17.5% + 15600 * 10.5%, AND(_xlpm.taxable > 53500, _xlpm.taxable <= 78100), (_xlpm.taxable - 53500) * 30% + (53500 - 15600) * 17.5% + 15600 * 10.5%, AND(_xlpm.taxable > 78100, _xlpm.taxable <= 180000), (_xlpm.taxable - 78100) * 33% + (78100 - 53500) * 30% + (53500 - 15600) * 17.5% + 15600 * 10.5%, _xlpm.taxable > 180000, (_xlpm.taxable - 180000) * 39% + (180000 - 78100) * 33% + (78100 - 53500) * 30% + (53500 - 15600) * 17.5% + 15600 * 10.5% ), _xlpm.acc, C15 * 0.0167, _xlpm.taxable - _xlpm.incomeTax - _xlpm.acc - _xlpm.kiwisaver )} -> 78145.506 | E15: =6%*C15 -> 6548.0192 | F15: {=C15 * 3% * _xlfn.IFS( C15 + C15 * 3% <= 18720, 10.5%, C15 + C15 * 3% <= 64200, 17.5%, C15 + C15 * 3% <= 93720, 30%, C15 + C15 * 3% <= 216000, 33%, C15 + C15 * 3% > 216000, 39% )} -> 1080.4232 | G15: =E15-F15+521.43 -> 5989.0261 | H15: {=_xlfn.IFS( H14="Boom", CHOOSE(MATCH(RAND(), {0,0.67,1}, 1), "Normal", "Recession"), H14="Normal", CHOOSE(MATCH(RAND(), {0,0.18,0.82,1}, 1), "Boom", "Normal", "Recession"), H14="Recession", CHOOSE(MATCH(RAND(), {0,0.17,0.34,1}, 1), "Boom", "Normal", "Recession") )} -> Normal | I15: {=_xlfn.LET( _xlpm.ε, (_xlfn.BETA.INV(RAND(), 5, 5) - 0.5) * 2, _xlpm.Scenario,H15, _xlpm.pre_scenario,H14, _xlpm.μ, _xlfn.XLOOKUP("HarbourSafe", fundGrowth!$A$2:$A$4, INDEX(fundGrowth!$B$2:$J$4,0, MATCH(_xlpm.Scenario & " μ", fundGrowth!$B$1:$J$1, 0))), _xlpm.σ, _xlfn.XLOOKUP("HarbourSafe", fundGrowth!$A$2:$A$4, INDEX(fundGrowth!$B$2:$J$4,0, MATCH(_xlpm.Scenario & " σ", fundGrowth!$B$1:$J$1, 0))), _xlpm.ρ, _xlfn.XLOOKUP("HarbourSafe", fundGrowth!$A$2:$A$4, INDEX(fundGrowth!$B$2:$J$4,0, MATCH(_xlpm.Scenario & " ρ", fundGrowth!$B$1:$J$1, 0))), _xlpm.μ_prev, _xlfn.XLOOKUP("HarbourSafe", fundGrowth!$A$2:$A$4, INDEX(fundGrowth!$B$2:$J$4,0, MATCH(_xlpm.pre_scenario & " μ", fundGrowth!$B$1:$J$1, 0))), _xlpm.μ + _xlpm.ρ*(I14-_xlpm.μ_prev) + _xlpm.σ * _xlpm.ε )} -> 0.045657936 | J15: {=_xlfn.LET( _xlpm.ε, (_xlfn.BETA.INV(RAND(), 5, 5) - 0.5) * 2, _xlpm.Scenario,H15, _xlpm.pre_scenario,H14, _xlpm.μ, _xlfn.XLOOKUP("Horizon", fundGrowth!$A$2:$A$4, INDEX(fundGrowth!$B$2:$J$4,0, MATCH(_xlpm.Scenario & " μ", fundGrowth!$B$1:$J$1, 0))), _xlpm.σ, _xlfn.XLOOKUP("Horizon", fundGrowth!$A$2:$A$4, INDEX(fundGrowth!$B$2:$J$4,0, MATCH(_xlpm.Scenario & " σ", fundGrowth!$B$1:$J$1, 0))), _xlpm.ρ, _xlfn.XLOOKUP("Horizon", fundGrowth!$A$2:$A$4, INDEX(fundGrowth!$B$2:$J$4,0, MATCH(_xlpm.Scenario & " ρ", fundGrowth!$B$1:$J$1, 0))), _xlpm.μ_prev, _xlfn.XLOOKUP("Horizon", fundGrowth!$A$2:$A$4, INDEX(fundGrowth!$B$2:$J$4,0, MATCH(_xlpm.pre_scenario & " μ", fundGrowth!$B$1:$J$1, 0))), _xlpm.μ + _xlpm.ρ*(MAX(J14, -0.05)-_xlpm.μ_prev) + _xlpm.σ * _xlpm.ε )} -> 0.11856165 | K15: {=_xlfn.LET( _xlpm.ε, (_xlfn.BETA.INV(RAND(), 5, 5) - 0.5) * 2, _xlpm.Scenario,H15, _xlpm.pre_scenario,H14, _xlpm.μ, _xlfn.XLOOKUP("SkyHigh", fundGrowth!$A$2:$A$4, INDEX(fundGrowth!$B$2:$J$4,0, MATCH(_xlpm.Scenario & " μ", fundGrowth!$B$1:$J$1, 0))), _xlpm.σ, _xlfn.XLOOKUP("SkyHigh", fundGrowth!$A$2:$A$4, INDEX(fundGrowth!$B$2:$J$4,0, MATCH(_xlpm.Scenario & " σ", fundGrowth!$B$1:$J$1, 0))), _xlpm.ρ, _xlfn.XLOOKUP("SkyHigh", fundGrowth!$A$2:$A$4, INDEX(fundGrowth!$B$2:$J$4,0, MATCH(_xlpm.Scenario & " ρ", fundGrowth!$B$1:$J$1, 0))), _xlpm.μ_prev, _xlfn.XLOOKUP("SkyHigh", fundGrowth!$A$2:$A$4, INDEX(fundGrowth!$B$2:$J$4,0, MATCH(_xlpm.pre_scenario & " μ", fundGrowth!$B$1:$J$1, 0))), _xlpm.μ + _xlpm.ρ*(MAX(K14, -0.07)-_xlpm.μ_prev) + _xlpm.σ * _xlpm.ε )} -> 0.1356451 | L15: =0.4*I15+0.3*J15+0.3*K15 -> 0.0945252 | M15: =(M14+G15)*(1+L15)*(1-28%) -> 18351.431 | N15: =M15*Q15 -> 13748.659 | O15: =N15+D15*Q15 -> 72294.277 | P15: {=_xlfn.LET( _xlpm.state, H15, _xlpm.last, P14, _xlpm.μ, IF(RAND() < 0.001, 6% + 1.5% * _xlfn.NORM.S.INV(RAND()), _xlfn.BETA.INV(RAND(), 1.19, 1.22, 0.003, 0.04) ), _xlpm.ρ_min, _xlfn.IFS(_xlpm.state="Boom", 0.61, _xlpm.state="Normal", 0.34, _xlpm.state="Recession", 0.2), _xlpm.ρ_max, _xlfn.IFS(_xlpm.state="Boom", 0.8, _xlpm.state="Normal", 0.6, _xlpm.state="Recession", 0.33), _xlpm.α, _xlfn.IFS(_xlpm.state="Boom", 3, _xlpm.state="Normal", 2, _xlpm.state="Recession", 2), _xlpm.β, _xlfn.IFS(_xlpm.state="Boom", 2, _xlpm.state="Normal", 2, _xlpm.state="Recession", 3), _xlpm.ρ, _xlfn.BETA.INV(RAND(), _xlpm.α, _xlpm.β, _xlpm.ρ_min, _xlpm.ρ_max), _xlpm.ε, _xlfn.NORM.S.INV(RAND()), _xlpm.μ + _xlpm.ρ * (_xlpm.last - _xlpm.μ) + 0 * _xlpm.ε + MAX(0,_xlfn.IFS(A14=49,-_xlfn.NORM.INV(RAND(), 0.01, 0.005), A14=57,ABS(_xlfn.NORM.INV(RAND(), 0.02, 0.01)),TRUE,0)) )} -> 0.017652844 | Q15: =Q14/(1+P15) -> 0.74918727 | S15: {=_xlfn.LET( _xlpm.KS_rate, $V$2 + 3%, _xlpm.ESCT_rate, 3%, _xlpm.W_HS, $V$3, _xlpm.W_HR, $V$4, _xlpm.W_SH, $V$5, _xlpm.salary, C15, _xlpm.salary_with_employer, _xlpm.salary + _xlpm.salary * _xlpm.ESCT_rate, _xlpm.esct, _xlpm.salary * _xlpm.ESCT_rate * _xlfn.IFS( _xlpm.salary_with_employer <= 18720, 10.5%, _xlpm.salary_with_employer <= 64200, 17.5%, _xlpm.salary_with_employer <= 93720, 30%, _xlpm.salary_with_employer <= 216000, 33%, _xlpm.salary_with_employer > 216000, 39% ), _xlpm.ks_contrib, _xlpm.salary * _xlpm.KS_rate - _xlpm.esct + 521.43, _xlpm.return_rate, _xlpm.W_HS * I15 + _xlpm.W_HR * J15 + _xlpm.W_SH * K15, _xlpm.net_growth, (1 + _xlpm.return_rate) * (1 - 28%), _xlpm.prev_value, S14, _xlpm.result, (_xlpm.prev_value + _xlpm.ks_contrib) * _xlpm.net_growth, _xlpm.result )} -> 41515.039 | T15: {=_xlfn.LET( _xlpm.KS_rate, $V$2 + 3%, _xlpm.ESCT_rate, 3%, _xlpm.W_HS, $V$3, _xlpm.W_HR, $V$4, _xlpm.W_SH, $V$5, _xlpm.salary, C15, _xlpm.salary_with_employer, _xlpm.salary + _xlpm.salary * _xlpm.ESCT_rate, _xlpm.esct, _xlpm.salary * _xlpm.ESCT_rate * _xlfn.IFS( _xlpm.salary_with_employer <= 18720, 10.5%, _xlpm.salary_with_employer <= 64200, 17.5%, _xlpm.salary_with_employer <= 93720, 30%, _xlpm.salary_with_employer <= 216000, 33%, _xlpm.salary_with_employer > 216000, 39% ), _xlpm.ks_contrib, _xlpm.salary * _xlpm.KS_rate - _xlpm.esct + 521.43, _xlpm.return_rate, _xlpm.W_HS * I15 + _xlpm.W_HR * J15 + _xlpm.W_SH * K15, _xlpm.net_growth, (1 + _xlpm.return_rate) * (1 - 28%), _xlpm.prev_value, IF(ROW()=2, 0, S14), _xlpm.base, IF(ROW()=2, _xlpm.ks_contrib, _xlpm.prev_value + _xlpm.ks_contrib ), _xlpm.current_value, _xlpm.base * _xlpm.net_growth, _xlpm.real_value, _xlpm.current_value * Q15, _xlpm.real_value )} -> 31102.539 | X15: {=_xlfn.LET( _xlpm.KS_rate, Dashboard!$Q$2 + 3%, _xlpm.ESCT_rate, 3%, _xlpm.W_HS, _xlfn.SWITCH(H14, "Recession", Dashboard!$Q$4, "Normal", Dashboard!$Q$8, "Boom", Dashboard!$Q$12 ), _xlpm.W_HR, _xlfn.SWITCH(H14, "Recession", Dashboard!$Q$5, "Normal", Dashboard!$Q$9, "Boom", Dashboard!$Q$13 ), _xlpm.W_SH, _xlfn.SWITCH(H14, "Recession", Dashboard!$Q$6, "Normal", Dashboard!$Q$10, "Boom", Dashboard!$Q$14 ), _xlpm.salary, C15, _xlpm.salary_with_employer, _xlpm.salary + _xlpm.salary * _xlpm.ESCT_rate, _xlpm.esct, _xlpm.salary * _xlpm.ESCT_rate * _xlfn.IFS( _xlpm.salary_with_employer <= 18720, 10.5%, _xlpm.salary_with_employer <= 64200, 17.5%, _xlpm.salary_with_employer <= 93720, 30%, _xlpm.salary_with_employer <= 216000, 33%, _xlpm.salary_with_employer > 216000, 39% ), _xlpm.ks_contrib, _xlpm.salary * _xlpm.KS_rate - _xlpm.esct + 521.43, _xlpm.return_rate, _xlpm.W_HS * I15 + _xlpm.W_HR * J15 + _xlpm.W_SH * K15, _xlpm.net_growth, (1 + _xlpm.return_rate) * (1 - 28%), _xlpm.prev_value, S14, _xlpm.result, (_xlpm.prev_value + _xlpm.ks_contrib) * _xlpm.net_growth, _xlpm.result )} -> 42750.721 | Y15: {=_xlfn.LET( _xlpm.KS_rate, Dashboard!$Q$2 + 3%, _xlpm.ESCT_rate, 3%, _xlpm.W_HS, _xlfn.SWITCH(H15, "Recession", Dashboard!$Q$4, "Normal", Dashboard!$Q$8, "Boom", Dashboard!$Q$12 ), _xlpm.W_HR, _xlfn.SWITCH(H15, "Recession", Dashboard!$Q$5, "Normal", Dashboard!$Q$9, "Boom", Dashboard!$Q$13 ), _xlpm.W_SH, _xlfn.SWITCH(H15, "Recession", Dashboard!$Q$6, "Normal", Dashboard!$Q$10, "Boom", Dashboard!$Q$14 ), _xlpm.salary, C15, _xlpm.salary_with_employer, _xlpm.salary + _xlpm.salary * _xlpm.ESCT_rate, _xlpm.esct, _xlpm.salary * _xlpm.ESCT_rate * _xlfn.IFS( _xlpm.salary_with_employer <= 18720, 10.5%, _xlpm.salary_with_employer <= 64200, 17.5%, _xlpm.salary_with_employer <= 93720, 30%, _xlpm.salary_with_employer <= 216000, 33%, _xlpm.salary_with_employer > 216000, 39% ), _xlpm.ks_contrib, _xlpm.salary * _xlpm.KS_rate - _xlpm.esct + 521.43, _xlpm.return_rate, _xlpm.W_HS * I15 + _xlpm.W_HR * J15 + _xlpm.W_SH * K15, _xlpm.net_growth, (1 + _xlpm.return_rate) * (1 - 28%), _xlpm.prev_value, IF(ROW()=2, 0, X14), _xlpm.base, IF(ROW()=2, _xlpm.ks_contrib, _xlpm.prev_value + _xlpm.ks_contrib), _xlpm.current_value, _xlpm.base * _xlpm.net_growth, _xlpm.real_value, _xlpm.current_value * Q15, _xlpm.real_value )} -> 33099.65 | Z15: 109133.65
A16: 44 | B16: =VLOOKUP(t4_salaryGrowthevent!J16,t4_salaryGrowthevent!J:J,1,FALSE) -> 0.03475 | C16: =VLOOKUP(t4_salaryGrowthevent!B16,t4_salaryGrowthevent!B:B,1,FALSE) -> 112926.05 | D16: {=_xlfn.LET( _xlpm.taxable, C16, _xlpm.kiwisaver,C16*0.03, _xlpm.incomeTax, _xlfn.IFS( _xlpm.taxable <= 15600, _xlpm.taxable * 10.5%, AND(_xlpm.taxable > 15600, _xlpm.taxable <= 53500), (_xlpm.taxable - 15600) * 17.5% + 15600 * 10.5%, AND(_xlpm.taxable > 53500, _xlpm.taxable <= 78100), (_xlpm.taxable - 53500) * 30% + (53500 - 15600) * 17.5% + 15600 * 10.5%, AND(_xlpm.taxable > 78100, _xlpm.taxable <= 180000), (_xlpm.taxable - 78100) * 33% + (78100 - 53500) * 30% + (53500 - 15600) * 17.5% + 15600 * 10.5%, _xlpm.taxable > 180000, (_xlpm.taxable - 180000) * 39% + (180000 - 78100) * 33% + (78100 - 53500) * 30% + (53500 - 15600) * 17.5% + 15600 * 10.5% ), _xlpm.acc, C16 * 0.0167, _xlpm.taxable - _xlpm.incomeTax - _xlpm.acc - _xlpm.kiwisaver )} -> 80509.306 | E16: =6%*C16 -> 6775.5629 | F16: {=C16 * 3% * _xlfn.IFS( C16 + C16 * 3% <= 18720, 10.5%, C16 + C16 * 3% <= 64200, 17.5%, C16 + C16 * 3% <= 93720, 30%, C16 + C16 * 3% <= 216000, 33%, C16 + C16 * 3% > 216000, 39% )} -> 1117.9679 | G16: =E16-F16+521.43 -> 6179.025 | H16: {=_xlfn.IFS( H15="Boom", CHOOSE(MATCH(RAND(), {0,0.67,1}, 1), "Normal", "Recession"), H15="Normal", CHOOSE(MATCH(RAND(), {0,0.18,0.82,1}, 1), "Boom", "Normal", "Recession"), H15="Recession", CHOOSE(MATCH(RAND(), {0,0.17,0.34,1}, 1), "Boom", "Normal", "Recession") )} -> Recession | I16: {=_xlfn.LET( _xlpm.ε, (_xlfn.BETA.INV(RAND(), 5, 5) - 0.5) * 2, _xlpm.Scenario,H16, _xlpm.pre_scenario,H15, _xlpm.μ, _xlfn.XLOOKUP("HarbourSafe", fundGrowth!$A$2:$A$4, INDEX(fundGrowth!$B$2:$J$4,0, MATCH(_xlpm.Scenario & " μ", fundGrowth!$B$1:$J$1, 0))), _xlpm.σ, _xlfn.XLOOKUP("HarbourSafe", fundGrowth!$A$2:$A$4, INDEX(fundGrowth!$B$2:$J$4,0, MATCH(_xlpm.Scenario & " σ", fundGrowth!$B$1:$J$1, 0))), _xlpm.ρ, _xlfn.XLOOKUP("HarbourSafe", fundGrowth!$A$2:$A$4, INDEX(fundGrowth!$B$2:$J$4,0, MATCH(_xlpm.Scenario & " ρ", fundGrowth!$B$1:$J$1, 0))), _xlpm.μ_prev, _xlfn.XLOOKUP("HarbourSafe", fundGrowth!$A$2:$A$4, INDEX(fundGrowth!$B$2:$J$4,0, MATCH(_xlpm.pre_scenario & " μ", fundGrowth!$B$1:$J$1, 0))), _xlpm.μ + _xlpm.ρ*(I15-_xlpm.μ_prev) + _xlpm.σ * _xlpm.ε )} -> 0.021815771 | J16: {=_xlfn.LET( _xlpm.ε, (_xlfn.BETA.INV(RAND(), 5, 5) - 0.5) * 2, _xlpm.Scenario,H16, _xlpm.pre_scenario,H15, _xlpm.μ, _xlfn.XLOOKUP("Horizon", fundGrowth!$A$2:$A$4, INDEX(fundGrowth!$B$2:$J$4,0, MATCH(_xlpm.Scenario & " μ", fundGrowth!$B$1:$J$1, 0))), _xlpm.σ, _xlfn.XLOOKUP("Horizon", fundGrowth!$A$2:$A$4, INDEX(fundGrowth!$B$2:$J$4,0, MATCH(_xlpm.Scenario & " σ", fundGrowth!$B$1:$J$1, 0))), _xlpm.ρ, _xlfn.XLOOKUP("Horizon", fundGrowth!$A$2:$A$4, INDEX(fundGrowth!$B$2:$J$4,0, MATCH(_xlpm.Scenario & " ρ", fundGrowth!$B$1:$J$1, 0))), _xlpm.μ_prev, _xlfn.XLOOKUP("Horizon", fundGrowth!$A$2:$A$4, INDEX(fundGrowth!$B$2:$J$4,0, MATCH(_xlpm.pre_scenario & " μ", fundGrowth!$B$1:$J$1, 0))), _xlpm.μ + _xlpm.ρ*(MAX(J15, -0.05)-_xlpm.μ_prev) + _xlpm.σ * _xlpm.ε )} -> 0.046723432 | K16: {=_xlfn.LET( _xlpm.ε, (_xlfn.BETA.INV(RAND(), 5, 5) - 0.5) * 2, _xlpm.Scenario,H16, _xlpm.pre_scenario,H15, _xlpm.μ, _xlfn.XLOOKUP("SkyHigh", fundGrowth!$A$2:$A$4, INDEX(fundGrowth!$B$2:$J$4,0, MATCH(_xlpm.Scenario & " μ", fundGrowth!$B$1:$J$1, 0))), _xlpm.σ, _xlfn.XLOOKUP("SkyHigh", fundGrowth!$A$2:$A$4, INDEX(fundGrowth!$B$2:$J$4,0, MATCH(_xlpm.Scenario & " σ", fundGrowth!$B$1:$J$1, 0))), _xlpm.ρ, _xlfn.XLOOKUP("SkyHigh", fundGrowth!$A$2:$A$4, INDEX(fundGrowth!$B$2:$J$4,0, MATCH(_xlpm.Scenario & " ρ", fundGrowth!$B$1:$J$1, 0))), _xlpm.μ_prev, _xlfn.XLOOKUP("SkyHigh", fundGrowth!$A$2:$A$4, INDEX(fundGrowth!$B$2:$J$4,0, MATCH(_xlpm.pre_scenario & " μ", fundGrowth!$B$1:$J$1, 0))), _xlpm.μ + _xlpm.ρ*(MAX(K15, -0.07)-_xlpm.μ_prev) + _xlpm.σ * _xlpm.ε )} -> 0.014321529 | L16: =0.4*I16+0.3*J16+0.3*K16 -> 0.027039797 | M16: =(M15+G16)*(1+L16)*(1-28%) -> 18139.503 | N16: =M16*Q16 -> 13455.647 | O16: =N16+D16*Q16 -> 73176.402 | P16: {=_xlfn.LET( _xlpm.state, H16, _xlpm.last, P15, _xlpm.μ, IF(RAND() < 0.001, 6% + 1.5% * _xlfn.NORM.S.INV(RAND()), _xlfn.BETA.INV(RAND(), 1.19, 1.22, 0.003, 0.04) ), _xlpm.ρ_min, _xlfn.IFS(_xlpm.state="Boom", 0.61, _xlpm.state="Normal", 0.34, _xlpm.state="Recession", 0.2), _xlpm.ρ_max, _xlfn.IFS(_xlpm.state="Boom", 0.8, _xlpm.state="Normal", 0.6, _xlpm.state="Recession", 0.33), _xlpm.α, _xlfn.IFS(_xlpm.state="Boom", 3, _xlpm.state="Normal", 2, _xlpm.state="Recession", 2), _xlpm.β, _xlfn.IFS(_xlpm.state="Boom", 2, _xlpm.state="Normal", 2, _xlpm.state="Recession", 3), _xlpm.ρ, _xlfn.BETA.INV(RAND(), _xlpm.α, _xlpm.β, _xlpm.ρ_min, _xlpm.ρ_max), _xlpm.ε, _xlfn.NORM.S.INV(RAND()), _xlpm.μ + _xlpm.ρ * (_xlpm.last - _xlpm.μ) + 0 * _xlpm.ε + MAX(0,_xlfn.IFS(A15=49,-_xlfn.NORM.INV(RAND(), 0.01, 0.005), A15=57,ABS(_xlfn.NORM.INV(RAND(), 0.02, 0.01)),TRUE,0)) )} -> 0.009976301 | Q16: =Q15/(1+P16) -> 0.74178698 | S16: {=_xlfn.LET( _xlpm.KS_rate, $V$2 + 3%, _xlpm.ESCT_rate, 3%, _xlpm.W_HS, $V$3, _xlpm.W_HR, $V$4, _xlpm.W_SH, $V$5, _xlpm.salary, C16, _xlpm.salary_with_employer, _xlpm.salary + _xlpm.salary * _xlpm.ESCT_rate, _xlpm.esct, _xlpm.salary * _xlpm.ESCT_rate * _xlfn.IFS( _xlpm.salary_with_employer <= 18720, 10.5%, _xlpm.salary_with_employer <= 64200, 17.5%, _xlpm.salary_with_employer <= 93720, 30%, _xlpm.salary_with_employer <= 216000, 33%, _xlpm.salary_with_employer > 216000, 39% ), _xlpm.ks_contrib, _xlpm.salary * _xlpm.KS_rate - _xlpm.esct + 521.43, _xlpm.return_rate, _xlpm.W_HS * I16 + _xlpm.W_HR * J16 + _xlpm.W_SH * K16, _xlpm.net_growth, (1 + _xlpm.return_rate) * (1 - 28%), _xlpm.prev_value, S15, _xlpm.result, (_xlpm.prev_value + _xlpm.ks_contrib) * _xlpm.net_growth, _xlpm.result )} -> 41113.635 | T16: {=_xlfn.LET( _xlpm.KS_rate, $V$2 + 3%, _xlpm.ESCT_rate, 3%, _xlpm.W_HS, $V$3, _xlpm.W_HR, $V$4, _xlpm.W_SH, $V$5, _xlpm.salary, C16, _xlpm.salary_with_employer, _xlpm.salary + _xlpm.salary * _xlpm.ESCT_rate, _xlpm.esct, _xlpm.salary * _xlpm.ESCT_rate * _xlfn.IFS( _xlpm.salary_with_employer <= 18720, 10.5%, _xlpm.salary_with_employer <= 64200, 17.5%, _xlpm.salary_with_employer <= 93720, 30%, _xlpm.salary_with_employer <= 216000, 33%, _xlpm.salary_with_employer > 216000, 39% ), _xlpm.ks_contrib, _xlpm.salary * _xlpm.KS_rate - _xlpm.esct + 521.43, _xlpm.return_rate, _xlpm.W_HS * I16 + _xlpm.W_HR * J16 + _xlpm.W_SH * K16, _xlpm.net_growth, (1 + _xlpm.return_rate) * (1 - 28%), _xlpm.prev_value, IF(ROW()=2, 0, S15), _xlpm.base, IF(ROW()=2, _xlpm.ks_contrib, _xlpm.prev_value + _xlpm.ks_contrib ), _xlpm.current_value, _xlpm.base * _xlpm.net_growth, _xlpm.real_value, _xlpm.current_value * Q16, _xlpm.real_value )} -> 30497.559 | X16: {=_xlfn.LET( _xlpm.KS_rate, Dashboard!$Q$2 + 3%, _xlpm.ESCT_rate, 3%, _xlpm.W_HS, _xlfn.SWITCH(H15, "Recession", Dashboard!$Q$4, "Normal", Dashboard!$Q$8, "Boom", Dashboard!$Q$12 ), _xlpm.W_HR, _xlfn.SWITCH(H15, "Recession", Dashboard!$Q$5, "Normal", Dashboard!$Q$9, "Boom", Dashboard!$Q$13 ), _xlpm.W_SH, _xlfn.SWITCH(H15, "Recession", Dashboard!$Q$6, "Normal", Dashboard!$Q$10, "Boom", Dashboard!$Q$14 ), _xlpm.salary, C16, _xlpm.salary_with_employer, _xlpm.salary + _xlpm.salary * _xlpm.ESCT_rate, _xlpm.esct, _xlpm.salary * _xlpm.ESCT_rate * _xlfn.IFS( _xlpm.salary_with_employer <= 18720, 10.5%, _xlpm.salary_with_employer <= 64200, 17.5%, _xlpm.salary_with_employer <= 93720, 30%, _xlpm.salary_with_employer <= 216000, 33%, _xlpm.salary_with_employer > 216000, 39% ), _xlpm.ks_contrib, _xlpm.salary * _xlpm.KS_rate - _xlpm.esct + 521.43, _xlpm.return_rate, _xlpm.W_HS * I16 + _xlpm.W_HR * J16 + _xlpm.W_SH * K16, _xlpm.net_growth, (1 + _xlpm.return_rate) * (1 - 28%), _xlpm.prev_value, S15, _xlpm.result, (_xlpm.prev_value + _xlpm.ks_contrib) * _xlpm.net_growth, _xlpm.result )} -> 41253.051 | Y16: {=_xlfn.LET( _xlpm.KS_rate, Dashboard!$Q$2 + 3%, _xlpm.ESCT_rate, 3%, _xlpm.W_HS, _xlfn.SWITCH(H16, "Recession", Dashboard!$Q$4, "Normal", Dashboard!$Q$8, "Boom", Dashboard!$Q$12 ), _xlpm.W_HR, _xlfn.SWITCH(H16, "Recession", Dashboard!$Q$5, "Normal", Dashboard!$Q$9, "Boom", Dashboard!$Q$13 ), _xlpm.W_SH, _xlfn.SWITCH(H16, "Recession", Dashboard!$Q$6, "Normal", Dashboard!$Q$10, "Boom", Dashboard!$Q$14 ), _xlpm.salary, C16, _xlpm.salary_with_employer, _xlpm.salary + _xlpm.salary * _xlpm.ESCT_rate, _xlpm.esct, _xlpm.salary * _xlpm.ESCT_rate * _xlfn.IFS( _xlpm.salary_with_employer <= 18720, 10.5%, _xlpm.salary_with_employer <= 64200, 17.5%, _xlpm.salary_with_employer <= 93720, 30%, _xlpm.salary_with_employer <= 216000, 33%, _xlpm.salary_with_employer > 216000, 39% ), _xlpm.ks_contrib, _xlpm.salary * _xlpm.KS_rate - _xlpm.esct + 521.43, _xlpm.return_rate, _xlpm.W_HS * I16 + _xlpm.W_HR * J16 + _xlpm.W_SH * K16, _xlpm.net_growth, (1 + _xlpm.return_rate) * (1 - 28%), _xlpm.prev_value, IF(ROW()=2, 0, X15), _xlpm.base, IF(ROW()=2, _xlpm.ks_contrib, _xlpm.prev_value + _xlpm.ks_contrib), _xlpm.current_value, _xlpm.base * _xlpm.net_growth, _xlpm.real_value, _xlpm.current_value * Q16, _xlpm.real_value )} -> 31016.792 | Z16: 112926.05
A17: 45 | B17: =VLOOKUP(t4_salaryGrowthevent!J17,t4_salaryGrowthevent!J:J,1,FALSE) -> 0.03475 | C17: =VLOOKUP(t4_salaryGrowthevent!B17,t4_salaryGrowthevent!B:B,1,FALSE) -> 116850.23 | D17: {=_xlfn.LET( _xlpm.taxable, C17, _xlpm.kiwisaver,C17*0.03, _xlpm.incomeTax, _xlfn.IFS( _xlpm.taxable <= 15600, _xlpm.taxable * 10.5%, AND(_xlpm.taxable > 15600, _xlpm.taxable <= 53500), (_xlpm.taxable - 15600) * 17.5% + 15600 * 10.5%, AND(_xlpm.taxable > 53500, _xlpm.taxable <= 78100), (_xlpm.taxable - 53500) * 30% + (53500 - 15600) * 17.5% + 15600 * 10.5%, AND(_xlpm.taxable > 78100, _xlpm.taxable <= 180000), (_xlpm.taxable - 78100) * 33% + (78100 - 53500) * 30% + (53500 - 15600) * 17.5% + 15600 * 10.5%, _xlpm.taxable > 180000, (_xlpm.taxable - 180000) * 39% + (180000 - 78100) * 33% + (78100 - 53500) * 30% + (53500 - 15600) * 17.5% + 15600 * 10.5% ), _xlpm.acc, C17 * 0.0167, _xlpm.taxable - _xlpm.incomeTax - _xlpm.acc - _xlpm.kiwisaver )} -> 82955.247 | E17: =6%*C17 -> 7011.0137 | F17: {=C17 * 3% * _xlfn.IFS( C17 + C17 * 3% <= 18720, 10.5%, C17 + C17 * 3% <= 64200, 17.5%, C17 + C17 * 3% <= 93720, 30%, C17 + C17 * 3% <= 216000, 33%, C17 + C17 * 3% > 216000, 39% )} -> 1156.8173 | G17: =E17-F17+521.43 -> 6375.6264 | H17: {=_xlfn.IFS( H16="Boom", CHOOSE(MATCH(RAND(), {0,0.67,1}, 1), "Normal", "Recession"), H16="Normal", CHOOSE(MATCH(RAND(), {0,0.18,0.82,1}, 1), "Boom", "Normal", "Recession"), H16="Recession", CHOOSE(MATCH(RAND(), {0,0.17,0.34,1}, 1), "Boom", "Normal", "Recession") )} -> Recession | I17: {=_xlfn.LET( _xlpm.ε, (_xlfn.BETA.INV(RAND(), 5, 5) - 0.5) * 2, _xlpm.Scenario,H17, _xlpm.pre_scenario,H16, _xlpm.μ, _xlfn.XLOOKUP("HarbourSafe", fundGrowth!$A$2:$A$4, INDEX(fundGrowth!$B$2:$J$4,0, MATCH(_xlpm.Scenario & " μ", fundGrowth!$B$1:$J$1, 0))), _xlpm.σ, _xlfn.XLOOKUP("HarbourSafe", fundGrowth!$A$2:$A$4, INDEX(fundGrowth!$B$2:$J$4,0, MATCH(_xlpm.Scenario & " σ", fundGrowth!$B$1:$J$1, 0))), _xlpm.ρ, _xlfn.XLOOKUP("HarbourSafe", fundGrowth!$A$2:$A$4, INDEX(fundGrowth!$B$2:$J$4,0, MATCH(_xlpm.Scenario & " ρ", fundGrowth!$B$1:$J$1, 0))), _xlpm.μ_prev, _xlfn.XLOOKUP("HarbourSafe", fundGrowth!$A$2:$A$4, INDEX(fundGrowth!$B$2:$J$4,0, MATCH(_xlpm.pre_scenario & " μ", fundGrowth!$B$1:$J$1, 0))), _xlpm.μ + _xlpm.ρ*(I16-_xlpm.μ_prev) + _xlpm.σ * _xlpm.ε )} -> 0.020312707 | J17: {=_xlfn.LET( _xlpm.ε, (_xlfn.BETA.INV(RAND(), 5, 5) - 0.5) * 2, _xlpm.Scenario,H17, _xlpm.pre_scenario,H16, _xlpm.μ, _xlfn.XLOOKUP("Horizon", fundGrowth!$A$2:$A$4, INDEX(fundGrowth!$B$2:$J$4,0, MATCH(_xlpm.Scenario & " μ", fundGrowth!$B$1:$J$1, 0))), _xlpm.σ, _xlfn.XLOOKUP("Horizon", fundGrowth!$A$2:$A$4, INDEX(fundGrowth!$B$2:$J$4,0, MATCH(_xlpm.Scenario & " σ", fundGrowth!$B$1:$J$1, 0))), _xlpm.ρ, _xlfn.XLOOKUP("Horizon", fundGrowth!$A$2:$A$4, INDEX(fundGrowth!$B$2:$J$4,0, MATCH(_xlpm.Scenario & " ρ", fundGrowth!$B$1:$J$1, 0))), _xlpm.μ_prev, _xlfn.XLOOKUP("Horizon", fundGrowth!$A$2:$A$4, INDEX(fundGrowth!$B$2:$J$4,0, MATCH(_xlpm.pre_scenario & " μ", fundGrowth!$B$1:$J$1, 0))), _xlpm.μ + _xlpm.ρ*(MAX(J16, -0.05)-_xlpm.μ_prev) + _xlpm.σ * _xlpm.ε )} -> 0.032999111 | K17: {=_xlfn.LET( _xlpm.ε, (_xlfn.BETA.INV(RAND(), 5, 5) - 0.5) * 2, _xlpm.Scenario,H17, _xlpm.pre_scenario,H16, _xlpm.μ, _xlfn.XLOOKUP("SkyHigh", fundGrowth!$A$2:$A$4, INDEX(fundGrowth!$B$2:$J$4,0, MATCH(_xlpm.Scenario & " μ", fundGrowth!$B$1:$J$1, 0))), _xlpm.σ, _xlfn.XLOOKUP("SkyHigh", fundGrowth!$A$2:$A$4, INDEX(fundGrowth!$B$2:$J$4,0, MATCH(_xlpm.Scenario & " σ", fundGrowth!$B$1:$J$1, 0))), _xlpm.ρ, _xlfn.XLOOKUP("SkyHigh", fundGrowth!$A$2:$A$4, INDEX(fundGrowth!$B$2:$J$4,0, MATCH(_xlpm.Scenario & " ρ", fundGrowth!$B$1:$J$1, 0))), _xlpm.μ_prev, _xlfn.XLOOKUP("SkyHigh", fundGrowth!$A$2:$A$4, INDEX(fundGrowth!$B$2:$J$4,0, MATCH(_xlpm.pre_scenario & " μ", fundGrowth!$B$1:$J$1, 0))), _xlpm.μ + _xlpm.ρ*(MAX(K16, -0.07)-_xlpm.μ_prev) + _xlpm.σ * _xlpm.ε )} -> -0.01178464 | L17: =0.4*I17+0.3*J17+0.3*K17 -> 0.014489424 | M17: =(M16+G17)*(1+L17)*(1-28%) -> 17906.645 | N17: =M17*Q17 -> 13047.102 | O17: =N17+D17*Q17 -> 73489.781 | P17: {=_xlfn.LET( _xlpm.state, H17, _xlpm.last, P16, _xlpm.μ, IF(RAND() < 0.001, 6% + 1.5% * _xlfn.NORM.S.INV(RAND()), _xlfn.BETA.INV(RAND(), 1.19, 1.22, 0.003, 0.04) ), _xlpm.ρ_min, _xlfn.IFS(_xlpm.state="Boom", 0.61, _xlpm.state="Normal", 0.34, _xlpm.state="Recession", 0.2), _xlpm.ρ_max, _xlfn.IFS(_xlpm.state="Boom", 0.8, _xlpm.state="Normal", 0.6, _xlpm.state="Recession", 0.33), _xlpm.α, _xlfn.IFS(_xlpm.state="Boom", 3, _xlpm.state="Normal", 2, _xlpm.state="Recession", 2), _xlpm.β, _xlfn.IFS(_xlpm.state="Boom", 2, _xlpm.state="Normal", 2, _xlpm.state="Recession", 3), _xlpm.ρ, _xlfn.BETA.INV(RAND(), _xlpm.α, _xlpm.β, _xlpm.ρ_min, _xlpm.ρ_max), _xlpm.ε, _xlfn.NORM.S.INV(RAND()), _xlpm.μ + _xlpm.ρ * (_xlpm.last - _xlpm.μ) + 0 * _xlpm.ε + MAX(0,_xlfn.IFS(A16=49,-_xlfn.NORM.INV(RAND(), 0.01, 0.005), A16=57,ABS(_xlfn.NORM.INV(RAND(), 0.02, 0.01)),TRUE,0)) )} -> 0.018074043 | Q17: =Q16/(1+P17) -> 0.72861791 | S17: {=_xlfn.LET( _xlpm.KS_rate, $V$2 + 3%, _xlpm.ESCT_rate, 3%, _xlpm.W_HS, $V$3, _xlpm.W_HR, $V$4, _xlpm.W_SH, $V$5, _xlpm.salary, C17, _xlpm.salary_with_employer, _xlpm.salary + _xlpm.salary * _xlpm.ESCT_rate, _xlpm.esct, _xlpm.salary * _xlpm.ESCT_rate * _xlfn.IFS( _xlpm.salary_with_employer <= 18720, 10.5%, _xlpm.salary_with_employer <= 64200, 17.5%, _xlpm.salary_with_employer <= 93720, 30%, _xlpm.salary_with_employer <= 216000, 33%, _xlpm.salary_with_employer > 216000, 39% ), _xlpm.ks_contrib, _xlpm.salary * _xlpm.KS_rate - _xlpm.esct + 521.43, _xlpm.return_rate, _xlpm.W_HS * I17 + _xlpm.W_HR * J17 + _xlpm.W_SH * K17, _xlpm.net_growth, (1 + _xlpm.return_rate) * (1 - 28%), _xlpm.prev_value, S16, _xlpm.result, (_xlpm.prev_value + _xlpm.ks_contrib) * _xlpm.net_growth, _xlpm.result )} -> 40662.278 | T17: {=_xlfn.LET( _xlpm.KS_rate, $V$2 + 3%, _xlpm.ESCT_rate, 3%, _xlpm.W_HS, $V$3, _xlpm.W_HR, $V$4, _xlpm.W_SH, $V$5, _xlpm.salary, C17, _xlpm.salary_with_employer, _xlpm.salary + _xlpm.salary * _xlpm.ESCT_rate, _xlpm.esct, _xlpm.salary * _xlpm.ESCT_rate * _xlfn.IFS( _xlpm.salary_with_employer <= 18720, 10.5%, _xlpm.salary_with_employer <= 64200, 17.5%, _xlpm.salary_with_employer <= 93720, 30%, _xlpm.salary_with_employer <= 216000, 33%, _xlpm.salary_with_employer > 216000, 39% ), _xlpm.ks_contrib, _xlpm.salary * _xlpm.KS_rate - _xlpm.esct + 521.43, _xlpm.return_rate, _xlpm.W_HS * I17 + _xlpm.W_HR * J17 + _xlpm.W_SH * K17, _xlpm.net_growth, (1 + _xlpm.return_rate) * (1 - 28%), _xlpm.prev_value, IF(ROW()=2, 0, S16), _xlpm.base, IF(ROW()=2, _xlpm.ks_contrib, _xlpm.prev_value + _xlpm.ks_contrib ), _xlpm.current_value, _xlpm.base * _xlpm.net_growth, _xlpm.real_value, _xlpm.current_value * Q17, _xlpm.real_value )} -> 29627.264 | X17: {=_xlfn.LET( _xlpm.KS_rate, Dashboard!$Q$2 + 3%, _xlpm.ESCT_rate, 3%, _xlpm.W_HS, _xlfn.SWITCH(H16, "Recession", Dashboard!$Q$4, "Normal", Dashboard!$Q$8, "Boom", Dashboard!$Q$12 ), _xlpm.W_HR, _xlfn.SWITCH(H16, "Recession", Dashboard!$Q$5, "Normal", Dashboard!$Q$9, "Boom", Dashboard!$Q$13 ), _xlpm.W_SH, _xlfn.SWITCH(H16, "Recession", Dashboard!$Q$6, "Normal", Dashboard!$Q$10, "Boom", Dashboard!$Q$14 ), _xlpm.salary, C17, _xlpm.salary_with_employer, _xlpm.salary + _xlpm.salary * _xlpm.ESCT_rate, _xlpm.esct, _xlpm.salary * _xlpm.ESCT_rate * _xlfn.IFS( _xlpm.salary_with_employer <= 18720, 10.5%, _xlpm.salary_with_employer <= 64200, 17.5%, _xlpm.salary_with_employer <= 93720, 30%, _xlpm.salary_with_employer <= 216000, 33%, _xlpm.salary_with_employer > 216000, 39% ), _xlpm.ks_contrib, _xlpm.salary * _xlpm.KS_rate - _xlpm.esct + 521.43, _xlpm.return_rate, _xlpm.W_HS * I17 + _xlpm.W_HR * J17 + _xlpm.W_SH * K17, _xlpm.net_growth, (1 + _xlpm.return_rate) * (1 - 28%), _xlpm.prev_value, S16, _xlpm.result, (_xlpm.prev_value + _xlpm.ks_contrib) * _xlpm.net_growth, _xlpm.result )} -> 40895.684 | Y17: {=_xlfn.LET( _xlpm.KS_rate, Dashboard!$Q$2 + 3%, _xlpm.ESCT_rate, 3%, _xlpm.W_HS, _xlfn.SWITCH(H17, "Recession", Dashboard!$Q$4, "Normal", Dashboard!$Q$8, "Boom", Dashboard!$Q$12 ), _xlpm.W_HR, _xlfn.SWITCH(H17, "Recession", Dashboard!$Q$5, "Normal", Dashboard!$Q$9, "Boom", Dashboard!$Q$13 ), _xlpm.W_SH, _xlfn.SWITCH(H17, "Recession", Dashboard!$Q$6, "Normal", Dashboard!$Q$10, "Boom", Dashboard!$Q$14 ), _xlpm.salary, C17, _xlpm.salary_with_employer, _xlpm.salary + _xlpm.salary * _xlpm.ESCT_rate, _xlpm.esct, _xlpm.salary * _xlpm.ESCT_rate * _xlfn.IFS( _xlpm.salary_with_employer <= 18720, 10.5%, _xlpm.salary_with_employer <= 64200, 17.5%, _xlpm.salary_with_employer <= 93720, 30%, _xlpm.salary_with_employer <= 216000, 33%, _xlpm.salary_with_employer > 216000, 39% ), _xlpm.ks_contrib, _xlpm.salary * _xlpm.KS_rate - _xlpm.esct + 521.43, _xlpm.return_rate, _xlpm.W_HS * I17 + _xlpm.W_HR * J17 + _xlpm.W_SH * K17, _xlpm.net_growth, (1 + _xlpm.return_rate) * (1 - 28%), _xlpm.prev_value, IF(ROW()=2, 0, X16), _xlpm.base, IF(ROW()=2, _xlpm.ks_contrib, _xlpm.prev_value + _xlpm.ks_contrib), _xlpm.current_value, _xlpm.base * _xlpm.net_growth, _xlpm.real_value, _xlpm.current_value * Q17, _xlpm.real_value )} -> 29871.951 | Z17: 116850.23
A18: 46 | B18: =VLOOKUP(t4_salaryGrowthevent!J18,t4_salaryGrowthevent!J:J,1,FALSE) -> 0.019226497 | C18: =VLOOKUP(t4_salaryGrowthevent!B18,t4_salaryGrowthevent!B:B,1,FALSE) -> 119096.85 | D18: {=_xlfn.LET( _xlpm.taxable, C18, _xlpm.kiwisaver,C18*0.03, _xlpm.incomeTax, _xlfn.IFS( _xlpm.taxable <= 15600, _xlpm.taxable * 10.5%, AND(_xlpm.taxable > 15600, _xlpm.taxable <= 53500), (_xlpm.taxable - 15600) * 17.5% + 15600 * 10.5%, AND(_xlpm.taxable > 53500, _xlpm.taxable <= 78100), (_xlpm.taxable - 53500) * 30% + (53500 - 15600) * 17.5% + 15600 * 10.5%, AND(_xlpm.taxable > 78100, _xlpm.taxable <= 180000), (_xlpm.taxable - 78100) * 33% + (78100 - 53500) * 30% + (53500 - 15600) * 17.5% + 15600 * 10.5%, _xlpm.taxable > 180000, (_xlpm.taxable - 180000) * 39% + (180000 - 78100) * 33% + (78100 - 53500) * 30% + (53500 - 15600) * 17.5% + 15600 * 10.5% ), _xlpm.acc, C18 * 0.0167, _xlpm.taxable - _xlpm.incomeTax - _xlpm.acc - _xlpm.kiwisaver )} -> 84355.566 | E18: =6%*C18 -> 7145.8109 | F18: {=C18 * 3% * _xlfn.IFS( C18 + C18 * 3% <= 18720, 10.5%, C18 + C18 * 3% <= 64200, 17.5%, C18 + C18 * 3% <= 93720, 30%, C18 + C18 * 3% <= 216000, 33%, C18 + C18 * 3% > 216000, 39% )} -> 1179.0588 | G18: =E18-F18+521.43 -> 6488.1821 | H18: {=_xlfn.IFS( H17="Boom", CHOOSE(MATCH(RAND(), {0,0.67,1}, 1), "Normal", "Recession"), H17="Normal", CHOOSE(MATCH(RAND(), {0,0.18,0.82,1}, 1), "Boom", "Normal", "Recession"), H17="Recession", CHOOSE(MATCH(RAND(), {0,0.17,0.34,1}, 1), "Boom", "Normal", "Recession") )} -> Recession | I18: {=_xlfn.LET( _xlpm.ε, (_xlfn.BETA.INV(RAND(), 5, 5) - 0.5) * 2, _xlpm.Scenario,H18, _xlpm.pre_scenario,H17, _xlpm.μ, _xlfn.XLOOKUP("HarbourSafe", fundGrowth!$A$2:$A$4, INDEX(fundGrowth!$B$2:$J$4,0, MATCH(_xlpm.Scenario & " μ", fundGrowth!$B$1:$J$1, 0))), _xlpm.σ, _xlfn.XLOOKUP("HarbourSafe", fundGrowth!$A$2:$A$4, INDEX(fundGrowth!$B$2:$J$4,0, MATCH(_xlpm.Scenario & " σ", fundGrowth!$B$1:$J$1, 0))), _xlpm.ρ, _xlfn.XLOOKUP("HarbourSafe", fundGrowth!$A$2:$A$4, INDEX(fundGrowth!$B$2:$J$4,0, MATCH(_xlpm.Scenario & " ρ", fundGrowth!$B$1:$J$1, 0))), _xlpm.μ_prev, _xlfn.XLOOKUP("HarbourSafe", fundGrowth!$A$2:$A$4, INDEX(fundGrowth!$B$2:$J$4,0, MATCH(_xlpm.pre_scenario & " μ", fundGrowth!$B$1:$J$1, 0))), _xlpm.μ + _xlpm.ρ*(I17-_xlpm.μ_prev) + _xlpm.σ * _xlpm.ε )} -> 0.023295217 | J18: {=_xlfn.LET( _xlpm.ε, (_xlfn.BETA.INV(RAND(), 5, 5) - 0.5) * 2, _xlpm.Scenario,H18, _xlpm.pre_scenario,H17, _xlpm.μ, _xlfn.XLOOKUP("Horizon", fundGrowth!$A$2:$A$4, INDEX(fundGrowth!$B$2:$J$4,0, MATCH(_xlpm.Scenario & " μ", fundGrowth!$B$1:$J$1, 0))), _xlpm.σ, _xlfn.XLOOKUP("Horizon", fundGrowth!$A$2:$A$4, INDEX(fundGrowth!$B$2:$J$4,0, MATCH(_xlpm.Scenario & " σ", fundGrowth!$B$1:$J$1, 0))), _xlpm.ρ, _xlfn.XLOOKUP("Horizon", fundGrowth!$A$2:$A$4, INDEX(fundGrowth!$B$2:$J$4,0, MATCH(_xlpm.Scenario & " ρ", fundGrowth!$B$1:$J$1, 0))), _xlpm.μ_prev, _xlfn.XLOOKUP("Horizon", fundGrowth!$A$2:$A$4, INDEX(fundGrowth!$B$2:$J$4,0, MATCH(_xlpm.pre_scenario & " μ", fundGrowth!$B$1:$J$1, 0))), _xlpm.μ + _xlpm.ρ*(MAX(J17, -0.05)-_xlpm.μ_prev) + _xlpm.σ * _xlpm.ε )} -> 0.036492694 | K18: {=_xlfn.LET( _xlpm.ε, (_xlfn.BETA.INV(RAND(), 5, 5) - 0.5) * 2, _xlpm.Scenario,H18, _xlpm.pre_scenario,H17, _xlpm.μ, _xlfn.XLOOKUP("SkyHigh", fundGrowth!$A$2:$A$4, INDEX(fundGrowth!$B$2:$J$4,0, MATCH(_xlpm.Scenario & " μ", fundGrowth!$B$1:$J$1, 0))), _xlpm.σ, _xlfn.XLOOKUP("SkyHigh", fundGrowth!$A$2:$A$4, INDEX(fundGrowth!$B$2:$J$4,0, MATCH(_xlpm.Scenario & " σ", fundGrowth!$B$1:$J$1, 0))), _xlpm.ρ, _xlfn.XLOOKUP("SkyHigh", fundGrowth!$A$2:$A$4, INDEX(fundGrowth!$B$2:$J$4,0, MATCH(_xlpm.Scenario & " ρ", fundGrowth!$B$1:$J$1, 0))), _xlpm.μ_prev, _xlfn.XLOOKUP("SkyHigh", fundGrowth!$A$2:$A$4, INDEX(fundGrowth!$B$2:$J$4,0, MATCH(_xlpm.pre_scenario & " μ", fundGrowth!$B$1:$J$1, 0))), _xlpm.μ + _xlpm.ρ*(MAX(K17, -0.07)-_xlpm.μ_prev) + _xlpm.σ * _xlpm.ε )} -> 0.041624559 | L18: =0.4*I18+0.3*J18+0.3*K18 -> 0.032753262 | M18: =(M17+G18)*(1+L18)*(1-28%) -> 18139.563 | N18: =M18*Q18 -> 13080.689 | O18: =N18+D18*Q18 -> 73910.651 | P18: {=_xlfn.LET( _xlpm.state, H18, _xlpm.last, P17, _xlpm.μ, IF(RAND() < 0.001, 6% + 1.5% * _xlfn.NORM.S.INV(RAND()), _xlfn.BETA.INV(RAND(), 1.19, 1.22, 0.003, 0.04) ), _xlpm.ρ_min, _xlfn.IFS(_xlpm.state="Boom", 0.61, _xlpm.state="Normal", 0.34, _xlpm.state="Recession", 0.2), _xlpm.ρ_max, _xlfn.IFS(_xlpm.state="Boom", 0.8, _xlpm.state="Normal", 0.6, _xlpm.state="Recession", 0.33), _xlpm.α, _xlfn.IFS(_xlpm.state="Boom", 3, _xlpm.state="Normal", 2, _xlpm.state="Recession", 2), _xlpm.β, _xlfn.IFS(_xlpm.state="Boom", 2, _xlpm.state="Normal", 2, _xlpm.state="Recession", 3), _xlpm.ρ, _xlfn.BETA.INV(RAND(), _xlpm.α, _xlpm.β, _xlpm.ρ_min, _xlpm.ρ_max), _xlpm.ε, _xlfn.NORM.S.INV(RAND()), _xlpm.μ + _xlpm.ρ * (_xlpm.last - _xlpm.μ) + 0 * _xlpm.ε + MAX(0,_xlfn.IFS(A17=49,-_xlfn.NORM.INV(RAND(), 0.01, 0.005), A17=57,ABS(_xlfn.NORM.INV(RAND(), 0.02, 0.01)),TRUE,0)) )} -> 0.010406286 | Q18: =Q17/(1+P18) -> 0.72111379 | S18: {=_xlfn.LET( _xlpm.KS_rate, $V$2 + 3%, _xlpm.ESCT_rate, 3%, _xlpm.W_HS, $V$3, _xlpm.W_HR, $V$4, _xlpm.W_SH, $V$5, _xlpm.salary, C18, _xlpm.salary_with_employer, _xlpm.salary + _xlpm.salary * _xlpm.ESCT_rate, _xlpm.esct, _xlpm.salary * _xlpm.ESCT_rate * _xlfn.IFS( _xlpm.salary_with_employer <= 18720, 10.5%, _xlpm.salary_with_employer <= 64200, 17.5%, _xlpm.salary_with_employer <= 93720, 30%, _xlpm.salary_with_employer <= 216000, 33%, _xlpm.salary_with_employer > 216000, 39% ), _xlpm.ks_contrib, _xlpm.salary * _xlpm.KS_rate - _xlpm.esct + 521.43, _xlpm.return_rate, _xlpm.W_HS * I18 + _xlpm.W_HR * J18 + _xlpm.W_SH * K18, _xlpm.net_growth, (1 + _xlpm.return_rate) * (1 - 28%), _xlpm.prev_value, S17, _xlpm.result, (_xlpm.prev_value + _xlpm.ks_contrib) * _xlpm.net_growth, _xlpm.result )} -> 41259.332 | T18: {=_xlfn.LET( _xlpm.KS_rate, $V$2 + 3%, _xlpm.ESCT_rate, 3%, _xlpm.W_HS, $V$3, _xlpm.W_HR, $V$4, _xlpm.W_SH, $V$5, _xlpm.salary, C18, _xlpm.salary_with_employer, _xlpm.salary + _xlpm.salary * _xlpm.ESCT_rate, _xlpm.esct, _xlpm.salary * _xlpm.ESCT_rate * _xlfn.IFS( _xlpm.salary_with_employer <= 18720, 10.5%, _xlpm.salary_with_employer <= 64200, 17.5%, _xlpm.salary_with_employer <= 93720, 30%, _xlpm.salary_with_employer <= 216000, 33%, _xlpm.salary_with_employer > 216000, 39% ), _xlpm.ks_contrib, _xlpm.salary * _xlpm.KS_rate - _xlpm.esct + 521.43, _xlpm.return_rate, _xlpm.W_HS * I18 + _xlpm.W_HR * J18 + _xlpm.W_SH * K18, _xlpm.net_growth, (1 + _xlpm.return_rate) * (1 - 28%), _xlpm.prev_value, IF(ROW()=2, 0, S17), _xlpm.base, IF(ROW()=2, _xlpm.ks_contrib, _xlpm.prev_value + _xlpm.ks_contrib ), _xlpm.current_value, _xlpm.base * _xlpm.net_growth, _xlpm.real_value, _xlpm.current_value * Q18, _xlpm.real_value )} -> 29752.673 | X18: {=_xlfn.LET( _xlpm.KS_rate, Dashboard!$Q$2 + 3%, _xlpm.ESCT_rate, 3%, _xlpm.W_HS, _xlfn.SWITCH(H17, "Recession", Dashboard!$Q$4, "Normal", Dashboard!$Q$8, "Boom", Dashboard!$Q$12 ), _xlpm.W_HR, _xlfn.SWITCH(H17, "Recession", Dashboard!$Q$5, "Normal", Dashboard!$Q$9, "Boom", Dashboard!$Q$13 ), _xlpm.W_SH, _xlfn.SWITCH(H17, "Recession", Dashboard!$Q$6, "Normal", Dashboard!$Q$10, "Boom", Dashboard!$Q$14 ), _xlpm.salary, C18, _xlpm.salary_with_employer, _xlpm.salary + _xlpm.salary * _xlpm.ESCT_rate, _xlpm.esct, _xlpm.salary * _xlpm.ESCT_rate * _xlfn.IFS( _xlpm.salary_with_employer <= 18720, 10.5%, _xlpm.salary_with_employer <= 64200, 17.5%, _xlpm.salary_with_employer <= 93720, 30%, _xlpm.salary_with_employer <= 216000, 33%, _xlpm.salary_with_employer > 216000, 39% ), _xlpm.ks_contrib, _xlpm.salary * _xlpm.KS_rate - _xlpm.esct + 521.43, _xlpm.return_rate, _xlpm.W_HS * I18 + _xlpm.W_HR * J18 + _xlpm.W_SH * K18, _xlpm.net_growth, (1 + _xlpm.return_rate) * (1 - 28%), _xlpm.prev_value, S17, _xlpm.result, (_xlpm.prev_value + _xlpm.ks_contrib) * _xlpm.net_growth, _xlpm.result )} -> 40881.475 | Y18: {=_xlfn.LET( _xlpm.KS_rate, Dashboard!$Q$2 + 3%, _xlpm.ESCT_rate, 3%, _xlpm.W_HS, _xlfn.SWITCH(H18, "Recession", Dashboard!$Q$4, "Normal", Dashboard!$Q$8, "Boom", Dashboard!$Q$12 ), _xlpm.W_HR, _xlfn.SWITCH(H18, "Recession", Dashboard!$Q$5, "Normal", Dashboard!$Q$9, "Boom", Dashboard!$Q$13 ), _xlpm.W_SH, _xlfn.SWITCH(H18, "Recession", Dashboard!$Q$6, "Normal", Dashboard!$Q$10, "Boom", Dashboard!$Q$14 ), _xlpm.salary, C18, _xlpm.salary_with_employer, _xlpm.salary + _xlpm.salary * _xlpm.ESCT_rate, _xlpm.esct, _xlpm.salary * _xlpm.ESCT_rate * _xlfn.IFS( _xlpm.salary_with_employer <= 18720, 10.5%, _xlpm.salary_with_employer <= 64200, 17.5%, _xlpm.salary_with_employer <= 93720, 30%, _xlpm.salary_with_employer <= 216000, 33%, _xlpm.salary_with_employer > 216000, 39% ), _xlpm.ks_contrib, _xlpm.salary * _xlpm.KS_rate - _xlpm.esct + 521.43, _xlpm.return_rate, _xlpm.W_HS * I18 + _xlpm.W_HR * J18 + _xlpm.W_SH * K18, _xlpm.net_growth, (1 + _xlpm.return_rate) * (1 - 28%), _xlpm.prev_value, IF(ROW()=2, 0, X17), _xlpm.base, IF(ROW()=2, _xlpm.ks_contrib, _xlpm.prev_value + _xlpm.ks_contrib), _xlpm.current_value, _xlpm.base * _xlpm.net_growth, _xlpm.real_value, _xlpm.current_value * Q18, _xlpm.real_value )} -> 29604.203 | Z18: 117799.14
... A36: 64 | B36: =VLOOKUP(t4_salaryGrowthevent!J36,t4_salaryGrowthevent!J:J,1,FALSE) -> 0 | C36: =VLOOKUP(t4_salaryGrowthevent!B36,t4_salaryGrowthevent!B:B,1,FALSE) -> 142023.3 | D36: {=_xlfn.LET( _xlpm.taxable, C36, _xlpm.kiwisaver,C36*0.03, _xlpm.incomeTax, _xlfn.IFS( _xlpm.taxable <= 15600, _xlpm.taxable * 10.5%, AND(_xlpm.taxable > 15600, _xlpm.taxable <= 53500), (_xlpm.taxable - 15600) * 17.5% + 15600 * 10.5%, AND(_xlpm.taxable > 53500, _xlpm.taxable <= 78100), (_xlpm.taxable - 53500) * 30% + (53500 - 15600) * 17.5% + 15600 * 10.5%, AND(_xlpm.taxable > 78100, _xlpm.taxable <= 180000), (_xlpm.taxable - 78100) * 33% + (78100 - 53500) * 30% + (53500 - 15600) * 17.5% + 15600 * 10.5%, _xlpm.taxable > 180000, (_xlpm.taxable - 180000) * 39% + (180000 - 78100) * 33% + (78100 - 53500) * 30% + (53500 - 15600) * 17.5% + 15600 * 10.5% ), _xlpm.acc, C36 * 0.0167, _xlpm.taxable - _xlpm.incomeTax - _xlpm.acc - _xlpm.kiwisaver )} -> 98645.62 | E36: =6%*C36 -> 8521.3977 | F36: {=C36 * 3% * _xlfn.IFS( C36 + C36 * 3% <= 18720, 10.5%, C36 + C36 * 3% <= 64200, 17.5%, C36 + C36 * 3% <= 93720, 30%, C36 + C36 * 3% <= 216000, 33%, C36 + C36 * 3% > 216000, 39% )} -> 1406.0306 | G36: =E36-F36+521.43 -> 7636.7971 | H36: {=_xlfn.IFS( H35="Boom", CHOOSE(MATCH(RAND(), {0,0.67,1}, 1), "Normal", "Recession"), H35="Normal", CHOOSE(MATCH(RAND(), {0,0.18,0.82,1}, 1), "Boom", "Normal", "Recession"), H35="Recession", CHOOSE(MATCH(RAND(), {0,0.17,0.34,1}, 1), "Boom", "Normal", "Recession") )} -> Normal | I36: {=_xlfn.LET( _xlpm.ε, (_xlfn.BETA.INV(RAND(), 5, 5) - 0.5) * 2, _xlpm.Scenario,H36, _xlpm.pre_scenario,H35, _xlpm.μ, _xlfn.XLOOKUP("HarbourSafe", fundGrowth!$A$2:$A$4, INDEX(fundGrowth!$B$2:$J$4,0, MATCH(_xlpm.Scenario & " μ", fundGrowth!$B$1:$J$1, 0))), _xlpm.σ, _xlfn.XLOOKUP("HarbourSafe", fundGrowth!$A$2:$A$4, INDEX(fundGrowth!$B$2:$J$4,0, MATCH(_xlpm.Scenario & " σ", fundGrowth!$B$1:$J$1, 0))), _xlpm.ρ, _xlfn.XLOOKUP("HarbourSafe", fundGrowth!$A$2:$A$4, INDEX(fundGrowth!$B$2:$J$4,0, MATCH(_xlpm.Scenario & " ρ", fundGrowth!$B$1:$J$1, 0))), _xlpm.μ_prev, _xlfn.XLOOKUP("HarbourSafe", fundGrowth!$A$2:$A$4, INDEX(fundGrowth!$B$2:$J$4,0, MATCH(_xlpm.pre_scenario & " μ", fundGrowth!$B$1:$J$1, 0))), _xlpm.μ + _xlpm.ρ*(I35-_xlpm.μ_prev) + _xlpm.σ * _xlpm.ε )} -> 0.052107234 | J36: {=_xlfn.LET( _xlpm.ε, (_xlfn.BETA.INV(RAND(), 5, 5) - 0.5) * 2, _xlpm.Scenario,H36, _xlpm.pre_scenario,H35, _xlpm.μ, _xlfn.XLOOKUP("Horizon", fundGrowth!$A$2:$A$4, INDEX(fundGrowth!$B$2:$J$4,0, MATCH(_xlpm.Scenario & " μ", fundGrowth!$B$1:$J$1, 0))), _xlpm.σ, _xlfn.XLOOKUP("Horizon", fundGrowth!$A$2:$A$4, INDEX(fundGrowth!$B$2:$J$4,0, MATCH(_xlpm.Scenario & " σ", fundGrowth!$B$1:$J$1, 0))), _xlpm.ρ, _xlfn.XLOOKUP("Horizon", fundGrowth!$A$2:$A$4, INDEX(fundGrowth!$B$2:$J$4,0, MATCH(_xlpm.Scenario & " ρ", fundGrowth!$B$1:$J$1, 0))), _xlpm.μ_prev, _xlfn.XLOOKUP("Horizon", fundGrowth!$A$2:$A$4, INDEX(fundGrowth!$B$2:$J$4,0, MATCH(_xlpm.pre_scenario & " μ", fundGrowth!$B$1:$J$1, 0))), _xlpm.μ + _xlpm.ρ*(MAX(J35, -0.05)-_xlpm.μ_prev) + _xlpm.σ * _xlpm.ε )} -> 0.081145323 | K36: {=_xlfn.LET( _xlpm.ε, (_xlfn.BETA.INV(RAND(), 5, 5) - 0.5) * 2, _xlpm.Scenario,H36, _xlpm.pre_scenario,H35, _xlpm.μ, _xlfn.XLOOKUP("SkyHigh", fundGrowth!$A$2:$A$4, INDEX(fundGrowth!$B$2:$J$4,0, MATCH(_xlpm.Scenario & " μ", fundGrowth!$B$1:$J$1, 0))), _xlpm.σ, _xlfn.XLOOKUP("SkyHigh", fundGrowth!$A$2:$A$4, INDEX(fundGrowth!$B$2:$J$4,0, MATCH(_xlpm.Scenario & " σ", fundGrowth!$B$1:$J$1, 0))), _xlpm.ρ, _xlfn.XLOOKUP("SkyHigh", fundGrowth!$A$2:$A$4, INDEX(fundGrowth!$B$2:$J$4,0, MATCH(_xlpm.Scenario & " ρ", fundGrowth!$B$1:$J$1, 0))), _xlpm.μ_prev, _xlfn.XLOOKUP("SkyHigh", fundGrowth!$A$2:$A$4, INDEX(fundGrowth!$B$2:$J$4,0, MATCH(_xlpm.pre_scenario & " μ", fundGrowth!$B$1:$J$1, 0))), _xlpm.μ + _xlpm.ρ*(MAX(K35, -0.07)-_xlpm.μ_prev) + _xlpm.σ * _xlpm.ε )} -> 0.12562305 | L36: =0.4*I36+0.3*J36+0.3*K36 -> 0.082873407 | M36: =(M35+G36)*(1+L36)*(1-28%) -> 24716.745 | N36: =M36*Q36 -> 11571.589 | O36: =N36+D36*Q36 -> 57754.31 | P36: {=_xlfn.LET( _xlpm.state, H36, _xlpm.last, P35, _xlpm.μ, IF(RAND() < 0.001, 6% + 1.5% * _xlfn.NORM.S.INV(RAND()), _xlfn.BETA.INV(RAND(), 1.19, 1.22, 0.003, 0.04) ), _xlpm.ρ_min, _xlfn.IFS(_xlpm.state="Boom", 0.61, _xlpm.state="Normal", 0.34, _xlpm.state="Recession", 0.2), _xlpm.ρ_max, _xlfn.IFS(_xlpm.state="Boom", 0.8, _xlpm.state="Normal", 0.6, _xlpm.state="Recession", 0.33), _xlpm.α, _xlfn.IFS(_xlpm.state="Boom", 3, _xlpm.state="Normal", 2, _xlpm.state="Recession", 2), _xlpm.β, _xlfn.IFS(_xlpm.state="Boom", 2, _xlpm.state="Normal", 2, _xlpm.state="Recession", 3), _xlpm.ρ, _xlfn.BETA.INV(RAND(), _xlpm.α, _xlpm.β, _xlpm.ρ_min, _xlpm.ρ_max), _xlpm.ε, _xlfn.NORM.S.INV(RAND()), _xlpm.μ + _xlpm.ρ * (_xlpm.last - _xlpm.μ) + 0 * _xlpm.ε + MAX(0,_xlfn.IFS(A35=49,-_xlfn.NORM.INV(RAND(), 0.01, 0.005), A35=57,ABS(_xlfn.NORM.INV(RAND(), 0.02, 0.01)),TRUE,0)) )} -> 0.01400908 | Q36: =Q35/(1+P36) -> 0.46816799 | S36: {=_xlfn.LET( _xlpm.KS_rate, $V$2 + 3%, _xlpm.ESCT_rate, 3%, _xlpm.W_HS, $V$3, _xlpm.W_HR, $V$4, _xlpm.W_SH, $V$5, _xlpm.salary, C36, _xlpm.salary_with_employer, _xlpm.salary + _xlpm.salary * _xlpm.ESCT_rate, _xlpm.esct, _xlpm.salary * _xlpm.ESCT_rate * _xlfn.IFS( _xlpm.salary_with_employer <= 18720, 10.5%, _xlpm.salary_with_employer <= 64200, 17.5%, _xlpm.salary_with_employer <= 93720, 30%, _xlpm.salary_with_employer <= 216000, 33%, _xlpm.salary_with_employer > 216000, 39% ), _xlpm.ks_contrib, _xlpm.salary * _xlpm.KS_rate - _xlpm.esct + 521.43, _xlpm.return_rate, _xlpm.W_HS * I36 + _xlpm.W_HR * J36 + _xlpm.W_SH * K36, _xlpm.net_growth, (1 + _xlpm.return_rate) * (1 - 28%), _xlpm.prev_value, S35, _xlpm.result, (_xlpm.prev_value + _xlpm.ks_contrib) * _xlpm.net_growth, _xlpm.result )} -> 56874.606 | T36: {=_xlfn.LET( _xlpm.KS_rate, $V$2 + 3%, _xlpm.ESCT_rate, 3%, _xlpm.W_HS, $V$3, _xlpm.W_HR, $V$4, _xlpm.W_SH, $V$5, _xlpm.salary, C36, _xlpm.salary_with_employer, _xlpm.salary + _xlpm.salary * _xlpm.ESCT_rate, _xlpm.esct, _xlpm.salary * _xlpm.ESCT_rate * _xlfn.IFS( _xlpm.salary_with_employer <= 18720, 10.5%, _xlpm.salary_with_employer <= 64200, 17.5%, _xlpm.salary_with_employer <= 93720, 30%, _xlpm.salary_with_employer <= 216000, 33%, _xlpm.salary_with_employer > 216000, 39% ), _xlpm.ks_contrib, _xlpm.salary * _xlpm.KS_rate - _xlpm.esct + 521.43, _xlpm.return_rate, _xlpm.W_HS * I36 + _xlpm.W_HR * J36 + _xlpm.W_SH * K36, _xlpm.net_growth, (1 + _xlpm.return_rate) * (1 - 28%), _xlpm.prev_value, IF(ROW()=2, 0, S35), _xlpm.base, IF(ROW()=2, _xlpm.ks_contrib, _xlpm.prev_value + _xlpm.ks_contrib ), _xlpm.current_value, _xlpm.base * _xlpm.net_growth, _xlpm.real_value, _xlpm.current_value * Q36, _xlpm.real_value )} -> 26626.87 | X36: {=_xlfn.LET( _xlpm.KS_rate, Dashboard!$Q$2 + 3%, _xlpm.ESCT_rate, 3%, _xlpm.W_HS, _xlfn.SWITCH(H35, "Recession", Dashboard!$Q$4, "Normal", Dashboard!$Q$8, "Boom", Dashboard!$Q$12 ), _xlpm.W_HR, _xlfn.SWITCH(H35, "Recession", Dashboard!$Q$5, "Normal", Dashboard!$Q$9, "Boom", Dashboard!$Q$13 ), _xlpm.W_SH, _xlfn.SWITCH(H35, "Recession", Dashboard!$Q$6, "Normal", Dashboard!$Q$10, "Boom", Dashboard!$Q$14 ), _xlpm.salary, C36, _xlpm.salary_with_employer, _xlpm.salary + _xlpm.salary * _xlpm.ESCT_rate, _xlpm.esct, _xlpm.salary * _xlpm.ESCT_rate * _xlfn.IFS( _xlpm.salary_with_employer <= 18720, 10.5%, _xlpm.salary_with_employer <= 64200, 17.5%, _xlpm.salary_with_employer <= 93720, 30%, _xlpm.salary_with_employer <= 216000, 33%, _xlpm.salary_with_employer > 216000, 39% ), _xlpm.ks_contrib, _xlpm.salary * _xlpm.KS_rate - _xlpm.esct + 521.43, _xlpm.return_rate, _xlpm.W_HS * I36 + _xlpm.W_HR * J36 + _xlpm.W_SH * K36, _xlpm.net_growth, (1 + _xlpm.return_rate) * (1 - 28%), _xlpm.prev_value, S35, _xlpm.result, (_xlpm.prev_value + _xlpm.ks_contrib) * _xlpm.net_growth, _xlpm.result )} -> 57951.872 | Y36: {=_xlfn.LET( _xlpm.KS_rate, Dashboard!$Q$2 + 3%, _xlpm.ESCT_rate, 3%, _xlpm.W_HS, _xlfn.SWITCH(H36, "Recession", Dashboard!$Q$4, "Normal", Dashboard!$Q$8, "Boom", Dashboard!$Q$12 ), _xlpm.W_HR, _xlfn.SWITCH(H36, "Recession", Dashboard!$Q$5, "Normal", Dashboard!$Q$9, "Boom", Dashboard!$Q$13 ), _xlpm.W_SH, _xlfn.SWITCH(H36, "Recession", Dashboard!$Q$6, "Normal", Dashboard!$Q$10, "Boom", Dashboard!$Q$14 ), _xlpm.salary, C36, _xlpm.salary_with_employer, _xlpm.salary + _xlpm.salary * _xlpm.ESCT_rate, _xlpm.esct, _xlpm.salary * _xlpm.ESCT_rate * _xlfn.IFS( _xlpm.salary_with_employer <= 18720, 10.5%, _xlpm.salary_with_employer <= 64200, 17.5%, _xlpm.salary_with_employer <= 93720, 30%, _xlpm.salary_with_employer <= 216000, 33%, _xlpm.salary_with_employer > 216000, 39% ), _xlpm.ks_contrib, _xlpm.salary * _xlpm.KS_rate - _xlpm.esct + 521.43, _xlpm.return_rate, _xlpm.W_HS * I36 + _xlpm.W_HR * J36 + _xlpm.W_SH * K36, _xlpm.net_growth, (1 + _xlpm.return_rate) * (1 - 28%), _xlpm.prev_value, IF(ROW()=2, 0, X35), _xlpm.base, IF(ROW()=2, _xlpm.ks_contrib, _xlpm.prev_value + _xlpm.ks_contrib), _xlpm.current_value, _xlpm.base * _xlpm.net_growth, _xlpm.real_value, _xlpm.current_value * Q36, _xlpm.real_value )} -> 27299.984 | Z36: 142620.6
T37: =SUM(T2:T36) -> 930999.09 | Y37: =SUM(Y2:Y36) -> 971637.44
T38: Use default fund weights | Y38: Use optimized fund weights

Sheet t4_salaryGrowthevent
A1: Age | B1: Salary | C1: Economic Scenario | D1: Mean value of salary growth under different scenarios | E1: Standard deviation of salary growth under different scenarios | F1: Dependency coefficient | G1: Growth rate-AR(1) | H1: Growth rate-Beta 30-45 | I1: Total growth rate | J1: Total growth rate (career events included) | K1: Event | L1: Random probability of event | M1: Total salary growth rate BACKUP | P1: Event | Q1: Δμ | R1: Δσ | S1: Δρ | T1: Description | U1: Trigger Probability (Year≤45) | V1: Trigger Probability (Year≤46-59) | W1: Trigger Probability (Year≥60)
A2: {=_xlfn.SEQUENCE(35,1,30,1)} -> 30 | B2: =IF(A2=30, 70000, B1 * (1 + J2)) -> 70000 | C2: Normal | D2: {=_xlfn.IFS( A2<=45, _xlfn.SWITCH(C2, "Boom", salaryParameters!$E$24, "Normal", salaryParameters!$E$25, "Recession", salaryParameters!$E$26 ), A2>=46, _xlfn.SWITCH(C2, "Boom", salaryParameters!$E$27, "Normal", salaryParameters!$E$28, "Recession", salaryParameters!$E$29 ) )} -> 0.034999985 | E2: {=_xlfn.IFS( A2<=45, _xlfn.SWITCH(C2, "Boom", salaryParameters!$F$24, "Normal", salaryParameters!$F$25, "Recession", salaryParameters!$F$26 ), A2>=46, _xlfn.SWITCH(C2, "Boom", salaryParameters!$F$27, "Normal", salaryParameters!$F$28, "Recession", salaryParameters!$F$29 ) )} -> 0.0069999942 | F2: {=_xlfn.SWITCH(C2, "Boom", IF(A2<=45, _xlfn.RANDARRAY(1,1,0.3,0.4,FALSE), _xlfn.RANDARRAY(1,1,0.7,0.8,FALSE)), "Normal", IF(A2<=45, _xlfn.RANDARRAY(1,1,0.4,0.5,FALSE), _xlfn.RANDARRAY(1,1,0.7,0.8,FALSE)), "Recession", IF(A2<=45, _xlfn.RANDARRAY(1,1,0.5,0.6,FALSE), _xlfn.RANDARRAY(1,1,0.8,0.9,FALSE)) )} -> 0.42394927 | G2: =IF(A2=30, 0.035, IF(AND(A2>=31, A2<=45), D2 + MAX(0, F2 * (G1 - D2) + E2 * _xlfn.NORM.S.INV(RAND())), IF(A2=46, D2 + MAX(0, E2 * _xlfn.NORM.S.INV(RAND())), D2 + MAX(0, F2 * (G1 - D2) + E2 * _xlfn.NORM.S.INV(RAND())) ) ) ) -> 0.035 | H2: 0.035 | I2: =IF(A2<=45,0.5*G2+0.5*H2,G2) -> 0.035 | J2: {=_xlfn.LET( _xlpm.age, A2, _xlpm.scenario, C2, _xlpm.r, L2, _xlpm.event, K2, _xlpm.μ_base, D2, _xlpm.σ_base, E2, _xlpm.ρ_base, F2, _xlpm.Δμ, _xlfn.XLOOKUP(_xlpm.event, $P$2:$P$9, INDEX($Q$2:$S$9,, MATCH("Δμ", $Q$1:$S$1, 0))), _xlpm.Δσ, _xlfn.XLOOKUP(_xlpm.event, $P$2:$P$9, INDEX($Q$2:$S$9,, MATCH("Δσ", $Q$1:$S$1, 0))), _xlpm.Δρ, _xlfn.XLOOKUP(_xlpm.event, $P$2:$P$9, INDEX($Q$2:$S$9,, MATCH("Δρ", $Q$1:$S$1, 0))), _xlpm.μ, _xlpm.μ_base + _xlpm.Δμ, _xlpm.σ, _xlpm.σ_base + _xlpm.Δσ, _xlpm.ρ, MAX(0, MIN(1, _xlpm.ρ_base + _xlpm.Δρ)), _xlpm.prevGrowth, G1, _xlpm.ε, _xlfn.NORM.S.INV(_xlpm.r), _xlpm.arGrowth, IF(_xlpm.age=30, 0.035, IF(AND(_xlpm.age>=31, _xlpm.age<=45), _xlpm.μ + MAX(0, _xlpm.ρ * (_xlpm.prevGrowth - _xlpm.μ) + _xlpm.σ * _xlpm.ε), IF(_xlpm.age=46, _xlpm.μ + MAX(0, _xlpm.σ * _xlpm.ε), _xlpm.μ + MAX(0, _xlpm.ρ * (_xlpm.prevGrowth - _xlpm.μ) + _xlpm.σ * _xlpm.ε) ) ) ), _xlpm.betaGrowth, IF(_xlpm.age=30, 0.0345, IF(_xlpm.age<=45, _xlfn.SWITCH(_xlpm.scenario, "Boom", _xlfn.BETA.INV(_xlpm.r, 2, 1.5, 0.03, 0.05), "Normal", _xlfn.BETA.INV(_xlpm.r, 1.364706192, 1, 0.02, 0.045991351), "Recession", _xlfn.BETA.INV(_xlpm.r, 2.699989178, 1.5, 0.01, 0.038) ), 0 ) ), _xlpm.totalGrowth, IF(_xlpm.age<=45, 0.5 * _xlpm.arGrowth + 0.5 * _xlpm.betaGrowth, _xlpm.arGrowth), _xlpm.totalGrowth )} -> 0.03475 | K2: - | L2: 0.8555311 | M2: {=_xlfn.LET( _xlpm.age, A2, _xlpm.scenario, C2, _xlpm.r, L2, _xlpm.event, K2, _xlpm.μ_base, D2, _xlpm.σ_base, E2, _xlpm.ρ_base, F2, _xlpm.Δμ, _xlfn.XLOOKUP(_xlpm.event, $P$2:$P$9, INDEX($Q$2:$S$9,, MATCH("Δμ", $Q$1:$S$1, 0))), _xlpm.Δσ, _xlfn.XLOOKUP(_xlpm.event, $P$2:$P$9, INDEX($Q$2:$S$9,, MATCH("Δσ", $Q$1:$S$1, 0))), _xlpm.Δρ, _xlfn.XLOOKUP(_xlpm.event, $P$2:$P$9, INDEX($Q$2:$S$9,, MATCH("Δρ", $Q$1:$S$1, 0))), _xlpm.μ, _xlpm.μ_base + _xlpm.Δμ, _xlpm.σ, _xlpm.σ_base + _xlpm.Δσ, _xlpm.ρ, MAX(0, MIN(1, _xlpm.ρ_base + _xlpm.Δρ)), _xlpm.prevGrowth, G1, _xlpm.ε, _xlfn.NORM.S.INV(_xlpm.r), _xlpm.arGrowth, IF(_xlpm.age=30, 0.035, IF(AND(_xlpm.age>=31, _xlpm.age<=45), _xlpm.μ + MAX(0, _xlpm.ρ * (_xlpm.prevGrowth - _xlpm.μ) + _xlpm.σ * _xlpm.ε), IF(_xlpm.age=46, _xlpm.μ + MAX(0, _xlpm.σ * _xlpm.ε), _xlpm.μ + MAX(0, _xlpm.ρ * (_xlpm.prevGrowth - _xlpm.μ) + _xlpm.σ * _xlpm.ε) ) ) ), _xlpm.betaGrowth, IF(_xlpm.age=30, 0.0345, IF(_xlpm.age<=45, _xlfn.SWITCH(_xlpm.scenario, "Boom", _xlfn.BETA.INV(_xlpm.r, 2, 1.5, 0.03, 0.05), "Normal", _xlfn.BETA.INV(_xlpm.r, 1.364706192, 1, 0.02, 0.045991351), "Recession", _xlfn.BETA.INV(_xlpm.r, 2.699989178, 1.5, 0.01, 0.038) ), 0 ) ), _xlpm.totalGrowth, IF(_xlpm.age<=45, 0.5 * _xlpm.arGrowth + 0.5 * _xlpm.betaGrowth, _xlpm.arGrowth), _xlpm.totalGrowth )} -> 0.03475 | P2: Promotion | Q2: 0.01 | R2: 0.01 | S2: 0.2 | T2: Stronger upward trend in salary | U2: 0.00 – 0.06 | V2: 0.00 – 0.02 | W2: 0.00 – 0.00
A3: 31 | B3: =IF(A3=30, 70000, B2 * (1 + J3)) -> 72432.5 | C3: {=_xlfn.IFS( C2="Boom", CHOOSE(MATCH(RAND(), {0,0.67,1}, 1), "Normal", "Recession"), C2="Normal", CHOOSE(MATCH(RAND(), {0,0.18,0.82,1}, 1), "Boom", "Normal", "Recession"), C2="Recession", CHOOSE(MATCH(RAND(), {0,0.17,0.34,1}, 1), "Boom", "Normal", "Recession") )} -> Normal | D3: {=_xlfn.IFS( A3<=45, _xlfn.SWITCH(C3, "Boom", salaryParameters!$E$24, "Normal", salaryParameters!$E$25, "Recession", salaryParameters!$E$26 ), A3>=46, _xlfn.SWITCH(C3, "Boom", salaryParameters!$E$27, "Normal", salaryParameters!$E$28, "Recession", salaryParameters!$E$29 ) )} -> 0.034999985 | E3: {=_xlfn.IFS( A3<=45, _xlfn.SWITCH(C3, "Boom", salaryParameters!$F$24, "Normal", salaryParameters!$F$25, "Recession", salaryParameters!$F$26 ), A3>=46, _xlfn.SWITCH(C3, "Boom", salaryParameters!$F$27, "Normal", salaryParameters!$F$28, "Recession", salaryParameters!$F$29 ) )} -> 0.0069999942 | F3: {=_xlfn.SWITCH(C3, "Boom", IF(A3<=45, _xlfn.RANDARRAY(1,1,0.3,0.4,FALSE), _xlfn.RANDARRAY(1,1,0.7,0.8,FALSE)), "Normal", IF(A3<=45, _xlfn.RANDARRAY(1,1,0.4,0.5,FALSE), _xlfn.RANDARRAY(1,1,0.7,0.8,FALSE)), "Recession", IF(A3<=45, _xlfn.RANDARRAY(1,1,0.5,0.6,FALSE), _xlfn.RANDARRAY(1,1,0.8,0.9,FALSE)) )} -> 0.45588555 | G3: =IF(A3=30, 0.035, IF(AND(A3>=31, A3<=45), D3 + MAX(0, F3 * (G2 - D3) + E3 * _xlfn.NORM.S.INV(RAND())), IF(A3=46, D3 + MAX(0, E3 * _xlfn.NORM.S.INV(RAND())), D3 + MAX(0, F3 * (G2 - D3) + E3 * _xlfn.NORM.S.INV(RAND())) ) ) ) -> 0.034999985 | H3: {=_xlfn.SWITCH(C3, "Boom", _xlfn.BETA.INV(RAND(), 2, 1.5, 0.03, 0.05), "Normal", _xlfn.BETA.INV(RAND(), 1.364706192, 1, 0.02, 0.045991351), "Recession", _xlfn.BETA.INV(RAND(), 2.699989178, 1.5, 0.01, 0.038) )} -> 0.036271074 | I3: =IF(A3<=45,0.5*G3+0.5*H3,G3) -> 0.03563553 | J3: 0.03475 | K3: Promotion | L3: 0.025062621 | M3: {=_xlfn.LET( _xlpm.age, A3, _xlpm.scenario, C3, _xlpm.r, L3, _xlpm.event, K3, _xlpm.μ_base, D3, _xlpm.σ_base, E3, _xlpm.ρ_base, F3, _xlpm.Δμ, _xlfn.XLOOKUP(_xlpm.event, $P$2:$P$9, INDEX($Q$2:$S$9,, MATCH("Δμ", $Q$1:$S$1, 0))), _xlpm.Δσ, _xlfn.XLOOKUP(_xlpm.event, $P$2:$P$9, INDEX($Q$2:$S$9,, MATCH("Δσ", $Q$1:$S$1, 0))), _xlpm.Δρ, _xlfn.XLOOKUP(_xlpm.event, $P$2:$P$9, INDEX($Q$2:$S$9,, MATCH("Δρ", $Q$1:$S$1, 0))), _xlpm.μ, _xlpm.μ_base + _xlpm.Δμ, _xlpm.σ, _xlpm.σ_base + _xlpm.Δσ, _xlpm.ρ, MAX(0, MIN(1, _xlpm.ρ_base + _xlpm.Δρ)), _xlpm.prevGrowth, G2, _xlpm.ε, _xlfn.NORM.S.INV(_xlpm.r), _xlpm.arGrowth, IF(_xlpm.age=30, 0.035, IF(AND(_xlpm.age>=31, _xlpm.age<=45), _xlpm.μ + MAX(0, _xlpm.ρ * (_xlpm.prevGrowth - _xlpm.μ) + _xlpm.σ * _xlpm.ε), IF(_xlpm.age=46, _xlpm.μ + MAX(0, _xlpm.σ * _xlpm.ε), _xlpm.μ + MAX(0, _xlpm.ρ * (_xlpm.prevGrowth - _xlpm.μ) + _xlpm.σ * _xlpm.ε) ) ) ), _xlpm.betaGrowth, IF(_xlpm.age=30, 0.0345, IF(_xlpm.age<=45, _xlfn.SWITCH(_xlpm.scenario, "Boom", _xlfn.BETA.INV(_xlpm.r, 2, 1.5, 0.03, 0.05), "Normal", _xlfn.BETA.INV(_xlpm.r, 1.364706192, 1, 0.02, 0.045991351), "Recession", _xlfn.BETA.INV(_xlpm.r, 2.699989178, 1.5, 0.01, 0.038) ), 0 ) ), _xlpm.totalGrowth, IF(_xlpm.age<=45, 0.5 * _xlpm.arGrowth + 0.5 * _xlpm.betaGrowth, _xlpm.arGrowth), _xlpm.totalGrowth )} -> 0.033372305 | P3: Job Change | Q3: -0.005 | R3: 0.015 | S3: -0.1 | T3: Reset of trajectory with more short-term noise | U3: 0.06 – 0.12 | V3: 0.02 – 0.06 | W3: 0.00 – 0.01
A4: 32 | B4: =IF(A4=30, 70000, B3 * (1 + J4)) -> 74949.529 | C4: {=_xlfn.IFS( C3="Boom", CHOOSE(MATCH(RAND(), {0,0.67,1}, 1), "Normal", "Recession"), C3="Normal", CHOOSE(MATCH(RAND(), {0,0.18,0.82,1}, 1), "Boom", "Normal", "Recession"), C3="Recession", CHOOSE(MATCH(RAND(), {0,0.17,0.34,1}, 1), "Boom", "Normal", "Recession") )} -> Normal | D4: {=_xlfn.IFS( A4<=45, _xlfn.SWITCH(C4, "Boom", salaryParameters!$E$24, "Normal", salaryParameters!$E$25, "Recession", salaryParameters!$E$26 ), A4>=46, _xlfn.SWITCH(C4, "Boom", salaryParameters!$E$27, "Normal", salaryParameters!$E$28, "Recession", salaryParameters!$E$29 ) )} -> 0.034999985 | E4: {=_xlfn.IFS( A4<=45, _xlfn.SWITCH(C4, "Boom", salaryParameters!$F$24, "Normal", salaryParameters!$F$25, "Recession", salaryParameters!$F$26 ), A4>=46, _xlfn.SWITCH(C4, "Boom", salaryParameters!$F$27, "Normal", salaryParameters!$F$28, "Recession", salaryParameters!$F$29 ) )} -> 0.0069999942 | F4: {=_xlfn.SWITCH(C4, "Boom", IF(A4<=45, _xlfn.RANDARRAY(1,1,0.3,0.4,FALSE), _xlfn.RANDARRAY(1,1,0.7,0.8,FALSE)), "Normal", IF(A4<=45, _xlfn.RANDARRAY(1,1,0.4,0.5,FALSE), _xlfn.RANDARRAY(1,1,0.7,0.8,FALSE)), "Recession", IF(A4<=45, _xlfn.RANDARRAY(1,1,0.5,0.6,FALSE), _xlfn.RANDARRAY(1,1,0.8,0.9,FALSE)) )} -> 0.49269833 | G4: =IF(A4=30, 0.035, IF(AND(A4>=31, A4<=45), D4 + MAX(0, F4 * (G3 - D4) + E4 * _xlfn.NORM.S.INV(RAND())), IF(A4=46, D4 + MAX(0, E4 * _xlfn.NORM.S.INV(RAND())), D4 + MAX(0, F4 * (G3 - D4) + E4 * _xlfn.NORM.S.INV(RAND())) ) ) ) -> 0.034999985 | H4: {=_xlfn.SWITCH(C4, "Boom", _xlfn.BETA.INV(RAND(), 2, 1.5, 0.03, 0.05), "Normal", _xlfn.BETA.INV(RAND(), 1.364706192, 1, 0.02, 0.045991351), "Recession", _xlfn.BETA.INV(RAND(), 2.699989178, 1.5, 0.01, 0.038) )} -> 0.045326008 | I4: =IF(A4<=45,0.5*G4+0.5*H4,G4) -> 0.040162997 | J4: 0.03475 | K4: - | L4: 0.46733475 | M4: {=_xlfn.LET( _xlpm.age, A4, _xlpm.scenario, C4, _xlpm.r, L4, _xlpm.event, K4, _xlpm.μ_base, D4, _xlpm.σ_base, E4, _xlpm.ρ_base, F4, _xlpm.Δμ, _xlfn.XLOOKUP(_xlpm.event, $P$2:$P$9, INDEX($Q$2:$S$9,, MATCH("Δμ", $Q$1:$S$1, 0))), _xlpm.Δσ, _xlfn.XLOOKUP(_xlpm.event, $P$2:$P$9, INDEX($Q$2:$S$9,, MATCH("Δσ", $Q$1:$S$1, 0))), _xlpm.Δρ, _xlfn.XLOOKUP(_xlpm.event, $P$2:$P$9, INDEX($Q$2:$S$9,, MATCH("Δρ", $Q$1:$S$1, 0))), _xlpm.μ, _xlpm.μ_base + _xlpm.Δμ, _xlpm.σ, _xlpm.σ_base + _xlpm.Δσ, _xlpm.ρ, MAX(0, MIN(1, _xlpm.ρ_base + _xlpm.Δρ)), _xlpm.prevGrowth, G3, _xlpm.ε, _xlfn.NORM.S.INV(_xlpm.r), _xlpm.arGrowth, IF(_xlpm.age=30, 0.035, IF(AND(_xlpm.age>=31, _xlpm.age<=45), _xlpm.μ + MAX(0, _xlpm.ρ * (_xlpm.prevGrowth - _xlpm.μ) + _xlpm.σ * _xlpm.ε), IF(_xlpm.age=46, _xlpm.μ + MAX(0, _xlpm.σ * _xlpm.ε), _xlpm.μ + MAX(0, _xlpm.ρ * (_xlpm.prevGrowth - _xlpm.μ) + _xlpm.σ * _xlpm.ε) ) ) ), _xlpm.betaGrowth, IF(_xlpm.age=30, 0.0345, IF(_xlpm.age<=45, _xlfn.SWITCH(_xlpm.scenario, "Boom", _xlfn.BETA.INV(_xlpm.r, 2, 1.5, 0.03, 0.05), "Normal", _xlfn.BETA.INV(_xlpm.r, 1.364706192, 1, 0.02, 0.045991351), "Recession", _xlfn.BETA.INV(_xlpm.r, 2.699989178, 1.5, 0.01, 0.038) ), 0 ) ), _xlpm.totalGrowth, IF(_xlpm.age<=45, 0.5 * _xlpm.arGrowth + 0.5 * _xlpm.betaGrowth, _xlpm.arGrowth), _xlpm.totalGrowth )} -> 0.034942445 | P4: Layoff | Q4: -0.02 | R4: 0.02 | S4: -0.3 | T4: Salary drop and disruption | U4: 0.12 – 0.15 | V4: 0.06 – 0.10 | W4: 0.01 – 0.03
A5: 33 | B5: =IF(A5=30, 70000, B4 * (1 + J5)) -> 77554.026 | C5: {=_xlfn.IFS( C4="Boom", CHOOSE(MATCH(RAND(), {0,0.67,1}, 1), "Normal", "Recession"), C4="Normal", CHOOSE(MATCH(RAND(), {0,0.18,0.82,1}, 1), "Boom", "Normal", "Recession"), C4="Recession", CHOOSE(MATCH(RAND(), {0,0.17,0.34,1}, 1), "Boom", "Normal", "Recession") )} -> Normal | D5: {=_xlfn.IFS( A5<=45, _xlfn.SWITCH(C5, "Boom", salaryParameters!$E$24, "Normal", salaryParameters!$E$25, "Recession", salaryParameters!$E$26 ), A5>=46, _xlfn.SWITCH(C5, "Boom", salaryParameters!$E$27, "Normal", salaryParameters!$E$28, "Recession", salaryParameters!$E$29 ) )} -> 0.034999985 | E5: {=_xlfn.IFS( A5<=45, _xlfn.SWITCH(C5, "Boom", salaryParameters!$F$24, "Normal", salaryParameters!$F$25, "Recession", salaryParameters!$F$26 ), A5>=46, _xlfn.SWITCH(C5, "Boom", salaryParameters!$F$27, "Normal", salaryParameters!$F$28, "Recession", salaryParameters!$F$29 ) )} -> 0.0069999942 | F5: {=_xlfn.SWITCH(C5, "Boom", IF(A5<=45, _xlfn.RANDARRAY(1,1,0.3,0.4,FALSE), _xlfn.RANDARRAY(1,1,0.7,0.8,FALSE)), "Normal", IF(A5<=45, _xlfn.RANDARRAY(1,1,0.4,0.5,FALSE), _xlfn.RANDARRAY(1,1,0.7,0.8,FALSE)), "Recession", IF(A5<=45, _xlfn.RANDARRAY(1,1,0.5,0.6,FALSE), _xlfn.RANDARRAY(1,1,0.8,0.9,FALSE)) )} -> 0.44776943 | G5: =IF(A5=30, 0.035, IF(AND(A5>=31, A5<=45), D5 + MAX(0, F5 * (G4 - D5) + E5 * _xlfn.NORM.S.INV(RAND())), IF(A5=46, D5 + MAX(0, E5 * _xlfn.NORM.S.INV(RAND())), D5 + MAX(0, F5 * (G4 - D5) + E5 * _xlfn.NORM.S.INV(RAND())) ) ) ) -> 0.034999985 | H5: {=_xlfn.SWITCH(C5, "Boom", _xlfn.BETA.INV(RAND(), 2, 1.5, 0.03, 0.05), "Normal", _xlfn.BETA.INV(RAND(), 1.364706192, 1, 0.02, 0.045991351), "Recession", _xlfn.BETA.INV(RAND(), 2.699989178, 1.5, 0.01, 0.038) )} -> 0.02950755 | I5: =IF(A5<=45,0.5*G5+0.5*H5,G5) -> 0.032253768 | J5: 0.03475 | K5: - | L5: 0.97541827 | M5: {=_xlfn.LET( _xlpm.age, A5, _xlpm.scenario, C5, _xlpm.r, L5, _xlpm.event, K5, _xlpm.μ_base, D5, _xlpm.σ_base, E5, _xlpm.ρ_base, F5, _xlpm.Δμ, _xlfn.XLOOKUP(_xlpm.event, $P$2:$P$9, INDEX($Q$2:$S$9,, MATCH("Δμ", $Q$1:$S$1, 0))), _xlpm.Δσ, _xlfn.XLOOKUP(_xlpm.event, $P$2:$P$9, INDEX($Q$2:$S$9,, MATCH("Δσ", $Q$1:$S$1, 0))), _xlpm.Δρ, _xlfn.XLOOKUP(_xlpm.event, $P$2:$P$9, INDEX($Q$2:$S$9,, MATCH("Δρ", $Q$1:$S$1, 0))), _xlpm.μ, _xlpm.μ_base + _xlpm.Δμ, _xlpm.σ, _xlpm.σ_base + _xlpm.Δσ, _xlpm.ρ, MAX(0, MIN(1, _xlpm.ρ_base + _xlpm.Δρ)), _xlpm.prevGrowth, G4, _xlpm.ε, _xlfn.NORM.S.INV(_xlpm.r), _xlpm.arGrowth, IF(_xlpm.age=30, 0.035, IF(AND(_xlpm.age>=31, _xlpm.age<=45), _xlpm.μ + MAX(0, _xlpm.ρ * (_xlpm.prevGrowth - _xlpm.μ) + _xlpm.σ * _xlpm.ε), IF(_xlpm.age=46, _xlpm.μ + MAX(0, _xlpm.σ * _xlpm.ε), _xlpm.μ + MAX(0, _xlpm.ρ * (_xlpm.prevGrowth - _xlpm.μ) + _xlpm.σ * _xlpm.ε) ) ) ), _xlpm.betaGrowth, IF(_xlpm.age=30, 0.0345, IF(_xlpm.age<=45, _xlfn.SWITCH(_xlpm.scenario, "Boom", _xlfn.BETA.INV(_xlpm.r, 2, 1.5, 0.03, 0.05), "Normal", _xlfn.BETA.INV(_xlpm.r, 1.364706192, 1, 0.02, 0.045991351), "Recession", _xlfn.BETA.INV(_xlpm.r, 2.699989178, 1.5, 0.01, 0.038) ), 0 ) ), _xlpm.totalGrowth, IF(_xlpm.age<=45, 0.5 * _xlpm.arGrowth + 0.5 * _xlpm.betaGrowth, _xlpm.arGrowth), _xlpm.totalGrowth )} -> 0.047145901 | P5: Pay Cut | Q5: -0.015 | R5: 0.01 | S5: -0.2 | T5: Income reduction with lower trend persistence | U5: 0.15 – 0.17 | V5: 0.10 – 0.13 | W5: 0.03 – 0.06
A6: 34 | B6: =IF(A6=30, 70000, B5 * (1 + J6)) -> 80249.028 | C6: {=_xlfn.IFS( C5="Boom", CHOOSE(MATCH(RAND(), {0,0.67,1}, 1), "Normal", "Recession"), C5="Normal", CHOOSE(MATCH(RAND(), {0,0.18,0.82,1}, 1), "Boom", "Normal", "Recession"), C5="Recession", CHOOSE(MATCH(RAND(), {0,0.17,0.34,1}, 1), "Boom", "Normal", "Recession") )} -> Recession | D6: {=_xlfn.IFS( A6<=45, _xlfn.SWITCH(C6, "Boom", salaryParameters!$E$24, "Normal", salaryParameters!$E$25, "Recession", salaryParameters!$E$26 ), A6>=46, _xlfn.SWITCH(C6, "Boom", salaryParameters!$E$27, "Normal", salaryParameters!$E$28, "Recession", salaryParameters!$E$29 ) )} -> 0.027999974 | E6: {=_xlfn.IFS( A6<=45, _xlfn.SWITCH(C6, "Boom", salaryParameters!$F$24, "Normal", salaryParameters!$F$25, "Recession", salaryParameters!$F$26 ), A6>=46, _xlfn.SWITCH(C6, "Boom", salaryParameters!$F$27, "Normal", salaryParameters!$F$28, "Recession", salaryParameters!$F$29 ) )} -> 0.0058834935 | F6: {=_xlfn.SWITCH(C6, "Boom", IF(A6<=45, _xlfn.RANDARRAY(1,1,0.3,0.4,FALSE), _xlfn.RANDARRAY(1,1,0.7,0.8,FALSE)), "Normal", IF(A6<=45, _xlfn.RANDARRAY(1,1,0.4,0.5,FALSE), _xlfn.RANDARRAY(1,1,0.7,0.8,FALSE)), "Recession", IF(A6<=45, _xlfn.RANDARRAY(1,1,0.5,0.6,FALSE), _xlfn.RANDARRAY(1,1,0.8,0.9,FALSE)) )} -> 0.50068774 | G6: =IF(A6=30, 0.035, IF(AND(A6>=31, A6<=45), D6 + MAX(0, F6 * (G5 - D6) + E6 * _xlfn.NORM.S.INV(RAND())), IF(A6=46, D6 + MAX(0, E6 * _xlfn.NORM.S.INV(RAND())), D6 + MAX(0, F6 * (G5 - D6) + E6 * _xlfn.NORM.S.INV(RAND())) ) ) ) -> 0.038687744 | H6: {=_xlfn.SWITCH(C6, "Boom", _xlfn.BETA.INV(RAND(), 2, 1.5, 0.03, 0.05), "Normal", _xlfn.BETA.INV(RAND(), 1.364706192, 1, 0.02, 0.045991351), "Recession", _xlfn.BETA.INV(RAND(), 2.699989178, 1.5, 0.01, 0.038) )} -> 0.029268632 | I6: =IF(A6<=45,0.5*G6+0.5*H6,G6) -> 0.033978188 | J6: 0.03475 | K6: - | L6: 0.883968 | M6: {=_xlfn.LET( _xlpm.age, A6, _xlpm.scenario, C6, _xlpm.r, L6, _xlpm.event, K6, _xlpm.μ_base, D6, _xlpm.σ_base, E6, _xlpm.ρ_base, F6, _xlpm.Δμ, _xlfn.XLOOKUP(_xlpm.event, $P$2:$P$9, INDEX($Q$2:$S$9,, MATCH("Δμ", $Q$1:$S$1, 0))), _xlpm.Δσ, _xlfn.XLOOKUP(_xlpm.event, $P$2:$P$9, INDEX($Q$2:$S$9,, MATCH("Δσ", $Q$1:$S$1, 0))), _xlpm.Δρ, _xlfn.XLOOKUP(_xlpm.event, $P$2:$P$9, INDEX($Q$2:$S$9,, MATCH("Δρ", $Q$1:$S$1, 0))), _xlpm.μ, _xlpm.μ_base + _xlpm.Δμ, _xlpm.σ, _xlpm.σ_base + _xlpm.Δσ, _xlpm.ρ, MAX(0, MIN(1, _xlpm.ρ_base + _xlpm.Δρ)), _xlpm.prevGrowth, G5, _xlpm.ε, _xlfn.NORM.S.INV(_xlpm.r), _xlpm.arGrowth, IF(_xlpm.age=30, 0.035, IF(AND(_xlpm.age>=31, _xlpm.age<=45), _xlpm.μ + MAX(0, _xlpm.ρ * (_xlpm.prevGrowth - _xlpm.μ) + _xlpm.σ * _xlpm.ε), IF(_xlpm.age=46, _xlpm.μ + MAX(0, _xlpm.σ * _xlpm.ε), _xlpm.μ + MAX(0, _xlpm.ρ * (_xlpm.prevGrowth - _xlpm.μ) + _xlpm.σ * _xlpm.ε) ) ) ), _xlpm.betaGrowth, IF(_xlpm.age=30, 0.0345, IF(_xlpm.age<=45, _xlfn.SWITCH(_xlpm.scenario, "Boom", _xlfn.BETA.INV(_xlpm.r, 2, 1.5, 0.03, 0.05), "Normal", _xlfn.BETA.INV(_xlpm.r, 1.364706192, 1, 0.02, 0.045991351), "Recession", _xlfn.BETA.INV(_xlpm.r, 2.699989178, 1.5, 0.01, 0.038) ), 0 ) ), _xlpm.totalGrowth, IF(_xlpm.age<=45, 0.5 * _xlpm.arGrowth + 0.5 * _xlpm.betaGrowth, _xlpm.arGrowth), _xlpm.totalGrowth )} -> 0.036789593 | P6: Career Shift | Q6: -0.01 | R6: 0.015 | S6: -0.2 | T6: Change in career track, less predictable growth | U6: 0.17 – 0.18 | V6: 0.13 – 0.15 | W6: 0.06 – 0.07
A7: 35 | B7: =IF(A7=30, 70000, B6 * (1 + J7)) -> 83037.682 | C7: {=_xlfn.IFS( C6="Boom", CHOOSE(MATCH(RAND(), {0,0.67,1}, 1), "Normal", "Recession"), C6="Normal", CHOOSE(MATCH(RAND(), {0,0.18,0.82,1}, 1), "Boom", "Normal", "Recession"), C6="Recession", CHOOSE(MATCH(RAND(), {0,0.17,0.34,1}, 1), "Boom", "Normal", "Recession") )} -> Boom | D7: {=_xlfn.IFS( A7<=45, _xlfn.SWITCH(C7, "Boom", salaryParameters!$E$24, "Normal", salaryParameters!$E$25, "Recession", salaryParameters!$E$26 ), A7>=46, _xlfn.SWITCH(C7, "Boom", salaryParameters!$E$27, "Normal", salaryParameters!$E$28, "Recession", salaryParameters!$E$29 ) )} -> 0.041428571 | E7: {=_xlfn.IFS( A7<=45, _xlfn.SWITCH(C7, "Boom", salaryParameters!$F$24, "Normal", salaryParameters!$F$25, "Recession", salaryParameters!$F$26 ), A7>=46, _xlfn.SWITCH(C7, "Boom", salaryParameters!$F$27, "Normal", salaryParameters!$F$28, "Recession", salaryParameters!$F$29 ) )} -> 0.0046656947 | F7: {=_xlfn.SWITCH(C7, "Boom", IF(A7<=45, _xlfn.RANDARRAY(1,1,0.3,0.4,FALSE), _xlfn.RANDARRAY(1,1,0.7,0.8,FALSE)), "Normal", IF(A7<=45, _xlfn.RANDARRAY(1,1,0.4,0.5,FALSE), _xlfn.RANDARRAY(1,1,0.7,0.8,FALSE)), "Recession", IF(A7<=45, _xlfn.RANDARRAY(1,1,0.5,0.6,FALSE), _xlfn.RANDARRAY(1,1,0.8,0.9,FALSE)) )} -> 0.30685801 | G7: =IF(A7=30, 0.035, IF(AND(A7>=31, A7<=45), D7 + MAX(0, F7 * (G6 - D7) + E7 * _xlfn.NORM.S.INV(RAND())), IF(A7=46, D7 + MAX(0, E7 * _xlfn.NORM.S.INV(RAND())), D7 + MAX(0, F7 * (G6 - D7) + E7 * _xlfn.NORM.S.INV(RAND())) ) ) ) -> 0.05014652 | H7: {=_xlfn.SWITCH(C7, "Boom", _xlfn.BETA.INV(RAND(), 2, 1.5, 0.03, 0.05), "Normal", _xlfn.BETA.INV(RAND(), 1.364706192, 1, 0.02, 0.045991351), "Recession", _xlfn.BETA.INV(RAND(), 2.699989178, 1.5, 0.01, 0.038) )} -> 0.039052702 | I7: =IF(A7<=45,0.5*G7+0.5*H7,G7) -> 0.044599611 | J7: 0.03475 | K7: Promotion | L7: 0.047417939 | M7: {=_xlfn.LET( _xlpm.age, A7, _xlpm.scenario, C7, _xlpm.r, L7, _xlpm.event, K7, _xlpm.μ_base, D7, _xlpm.σ_base, E7, _xlpm.ρ_base, F7, _xlpm.Δμ, _xlfn.XLOOKUP(_xlpm.event, $P$2:$P$9, INDEX($Q$2:$S$9,, MATCH("Δμ", $Q$1:$S$1, 0))), _xlpm.Δσ, _xlfn.XLOOKUP(_xlpm.event, $P$2:$P$9, INDEX($Q$2:$S$9,, MATCH("Δσ", $Q$1:$S$1, 0))), _xlpm.Δρ, _xlfn.XLOOKUP(_xlpm.event, $P$2:$P$9, INDEX($Q$2:$S$9,, MATCH("Δρ", $Q$1:$S$1, 0))), _xlpm.μ, _xlpm.μ_base + _xlpm.Δμ, _xlpm.σ, _xlpm.σ_base + _xlpm.Δσ, _xlpm.ρ, MAX(0, MIN(1, _xlpm.ρ_base + _xlpm.Δρ)), _xlpm.prevGrowth, G6, _xlpm.ε, _xlfn.NORM.S.INV(_xlpm.r), _xlpm.arGrowth, IF(_xlpm.age=30, 0.035, IF(AND(_xlpm.age>=31, _xlpm.age<=45), _xlpm.μ + MAX(0, _xlpm.ρ * (_xlpm.prevGrowth - _xlpm.μ) + _xlpm.σ * _xlpm.ε), IF(_xlpm.age=46, _xlpm.μ + MAX(0, _xlpm.σ * _xlpm.ε), _xlpm.μ + MAX(0, _xlpm.ρ * (_xlpm.prevGrowth - _xlpm.μ) + _xlpm.σ * _xlpm.ε) ) ) ), _xlpm.betaGrowth, IF(_xlpm.age=30, 0.0345, IF(_xlpm.age<=45, _xlfn.SWITCH(_xlpm.scenario, "Boom", _xlfn.BETA.INV(_xlpm.r, 2, 1.5, 0.03, 0.05), "Normal", _xlfn.BETA.INV(_xlpm.r, 1.364706192, 1, 0.02, 0.045991351), "Recession", _xlfn.BETA.INV(_xlpm.r, 2.699989178, 1.5, 0.01, 0.038) ), 0 ) ), _xlpm.totalGrowth, IF(_xlpm.age<=45, 0.5 * _xlpm.arGrowth + 0.5 * _xlpm.betaGrowth, _xlpm.arGrowth), _xlpm.totalGrowth )} -> 0.04235136 | P7: Parental Leave | Q7: 0 | R7: 0 | S7: 0 | T7: Salary growth pauses for a year (set gₜ = 0) | U7: 0.18 – 0.22 | V7: 0.00 – 0.00 | W7: 0.00 – 0.00
A8: 36 | B8: =IF(A8=30, 70000, B7 * (1 + J8)) -> 85923.241 | C8: {=_xlfn.IFS( C7="Boom", CHOOSE(MATCH(RAND(), {0,0.67,1}, 1), "Normal", "Recession"), C7="Normal", CHOOSE(MATCH(RAND(), {0,0.18,0.82,1}, 1), "Boom", "Normal", "Recession"), C7="Recession", CHOOSE(MATCH(RAND(), {0,0.17,0.34,1}, 1), "Boom", "Normal", "Recession") )} -> Recession | D8: {=_xlfn.IFS( A8<=45, _xlfn.SWITCH(C8, "Boom", salaryParameters!$E$24, "Normal", salaryParameters!$E$25, "Recession", salaryParameters!$E$26 ), A8>=46, _xlfn.SWITCH(C8, "Boom", salaryParameters!$E$27, "Normal", salaryParameters!$E$28, "Recession", salaryParameters!$E$29 ) )} -> 0.027999974 | E8: {=_xlfn.IFS( A8<=45, _xlfn.SWITCH(C8, "Boom", salaryParameters!$F$24, "Normal", salaryParameters!$F$25, "Recession", salaryParameters!$F$26 ), A8>=46, _xlfn.SWITCH(C8, "Boom", salaryParameters!$F$27, "Normal", salaryParameters!$F$28, "Recession", salaryParameters!$F$29 ) )} -> 0.0058834935 | F8: {=_xlfn.SWITCH(C8, "Boom", IF(A8<=45, _xlfn.RANDARRAY(1,1,0.3,0.4,FALSE), _xlfn.RANDARRAY(1,1,0.7,0.8,FALSE)), "Normal", IF(A8<=45, _xlfn.RANDARRAY(1,1,0.4,0.5,FALSE), _xlfn.RANDARRAY(1,1,0.7,0.8,FALSE)), "Recession", IF(A8<=45, _xlfn.RANDARRAY(1,1,0.5,0.6,FALSE), _xlfn.RANDARRAY(1,1,0.8,0.9,FALSE)) )} -> 0.5084069 | G8: =IF(A8=30, 0.035, IF(AND(A8>=31, A8<=45), D8 + MAX(0, F8 * (G7 - D8) + E8 * _xlfn.NORM.S.INV(RAND())), IF(A8=46, D8 + MAX(0, E8 * _xlfn.NORM.S.INV(RAND())), D8 + MAX(0, F8 * (G7 - D8) + E8 * _xlfn.NORM.S.INV(RAND())) ) ) ) -> 0.034739554 | H8: {=_xlfn.SWITCH(C8, "Boom", _xlfn.BETA.INV(RAND(), 2, 1.5, 0.03, 0.05), "Normal", _xlfn.BETA.INV(RAND(), 1.364706192, 1, 0.02, 0.045991351), "Recession", _xlfn.BETA.INV(RAND(), 2.699989178, 1.5, 0.01, 0.038) )} -> 0.016190636 | I8: =IF(A8<=45,0.5*G8+0.5*H8,G8) -> 0.025465095 | J8: 0.03475 | K8: - | L8: 0.32727075 | M8: {=_xlfn.LET( _xlpm.age, A8, _xlpm.scenario, C8, _xlpm.r, L8, _xlpm.event, K8, _xlpm.μ_base, D8, _xlpm.σ_base, E8, _xlpm.ρ_base, F8, _xlpm.Δμ, _xlfn.XLOOKUP(_xlpm.event, $P$2:$P$9, INDEX($Q$2:$S$9,, MATCH("Δμ", $Q$1:$S$1, 0))), _xlpm.Δσ, _xlfn.XLOOKUP(_xlpm.event, $P$2:$P$9, INDEX($Q$2:$S$9,, MATCH("Δσ", $Q$1:$S$1, 0))), _xlpm.Δρ, _xlfn.XLOOKUP(_xlpm.event, $P$2:$P$9, INDEX($Q$2:$S$9,, MATCH("Δρ", $Q$1:$S$1, 0))), _xlpm.μ, _xlpm.μ_base + _xlpm.Δμ, _xlpm.σ, _xlpm.σ_base + _xlpm.Δσ, _xlpm.ρ, MAX(0, MIN(1, _xlpm.ρ_base + _xlpm.Δρ)), _xlpm.prevGrowth, G7, _xlpm.ε, _xlfn.NORM.S.INV(_xlpm.r), _xlpm.arGrowth, IF(_xlpm.age=30, 0.035, IF(AND(_xlpm.age>=31, _xlpm.age<=45), _xlpm.μ + MAX(0, _xlpm.ρ * (_xlpm.prevGrowth - _xlpm.μ) + _xlpm.σ * _xlpm.ε), IF(_xlpm.age=46, _xlpm.μ + MAX(0, _xlpm.σ * _xlpm.ε), _xlpm.μ + MAX(0, _xlpm.ρ * (_xlpm.prevGrowth - _xlpm.μ) + _xlpm.σ * _xlpm.ε) ) ) ), _xlpm.betaGrowth, IF(_xlpm.age=30, 0.0345, IF(_xlpm.age<=45, _xlfn.SWITCH(_xlpm.scenario, "Boom", _xlfn.BETA.INV(_xlpm.r, 2, 1.5, 0.03, 0.05), "Normal", _xlfn.BETA.INV(_xlpm.r, 1.364706192, 1, 0.02, 0.045991351), "Recession", _xlfn.BETA.INV(_xlpm.r, 2.699989178, 1.5, 0.01, 0.038) ), 0 ) ), _xlpm.totalGrowth, IF(_xlpm.age<=45, 0.5 * _xlpm.arGrowth + 0.5 * _xlpm.betaGrowth, _xlpm.arGrowth), _xlpm.totalGrowth )} -> 0.031068302 | P8: Early Retirement | Q8: 0 | R8: 0 | S8: 0 | T8: Marks the end of salary growth | U8: 0.00 – 0.00 | V8: 0.00 – 0.00 | W8: 0.07 – 0.13
